Workbook

Sheet Comparación unificada
A1: DIAN vs SIESA — una fila por tercero; use +/- (o botones 1/2) para ver los documentos; filtre "Estado" en la fila 4
B2: TOTAL GENERAL | E2: =SUMIF($D$5:$D$10000,"TOTAL TERCERO",E5:E10000) -> 3.4554926e+08 | F2: =SUMIF($D$5:$D$10000,"TOTAL TERCERO",F5:F10000) -> 283038611 | G2: =E2-F2 -> 62510653
A4: NIT | B4: Tercero | C4: Documento | D4: Tipo de documento | E4: Valor DIAN | F4: Valor SIESA | G4: Diferencia (DIAN − SIESA) | H4: Estado | I4: Fecha emisión
A5: 805012421 | B5: A.F.TROST HANSEN PRODUCTOS DANCALI SENC | C5: 1 documento(s) | D5: TOTAL TERCERO | E5: =SUMIFS(Base!$H:$H,Base!$A:$A,$A5) -> 0 | F5: =SUMIFS(Base!$I:$I,Base!$A:$A,$A5) -> 100600 | G5: =E5-F5 -> -100600 | H5: Tercero solo en SIESA
A6: 805012421 | B6: A.F.TROST HANSEN PRODUCTOS DANCALI SENC | C6: F20110389 | D6: Factura (solo SIESA) | F6: 100600 | G6: =N(E6)-N(F6) -> -100600 | H6: Solo en SIESA | I6: 46318
A7: 805010086 | B7: ADOCCIDENTE S.A.S. | C7: 1 documento(s) | D7: TOTAL TERCERO | E7: =SUMIFS(Base!$H:$H,Base!$A:$A,$A7) -> 14515620 | F7: =SUMIFS(Base!$I:$I,Base!$A:$A,$A7) -> 14515620 | G7: =E7-F7 -> 0 | H7: Coincide
A8: 805010086 | B8: ADOCCIDENTE S.A.S. | C8: FE1062 | D8: Factura electrónica | E8: 14515620 | F8: 14515620 | G8: =N(E8)-N(F8) -> 0 | H8: Coincide | I8: 46296
A9: 890704196 | B9: AEROVIAS DE INTEGRACION REGIONAL S.A. | C9: 2 documento(s) | D9: TOTAL TERCERO | E9: =SUMIFS(Base!$H:$H,Base!$A:$A,$A9) -> 4972558 | F9: =SUMIFS(Base!$I:$I,Base!$A:$A,$A9) -> 4450876 | G9: =E9-F9 -> 521682 | H9: Con diferencias
A10: 890704196 | B10: AEROVIAS DE INTEGRACION REGIONAL S.A. | C10: EFCC4976394 | D10: Documento equivalente - Transporte aéreo de pasajeros | E10: 521682 | G10: =N(E10)-N(F10) -> 521682 | H10: Solo en DIAN | I10: 46296
A11: 890704196 | B11: AEROVIAS DE INTEGRACION REGIONAL S.A. | C11: SPC45772 | D11: Factura electrónica | E11: 4450876 | F11: 4450876 | G11: =N(E11)-N(F11) -> 0 | H11: Coincide | I11: 46310
A12: 860023024 | B12: AGRICOLA AUTOMOTRIZ S.A.S. | C12: 1 documento(s) | D12: TOTAL TERCERO | E12: =SUMIFS(Base!$H:$H,Base!$A:$A,$A12) -> 2399877.8 | F12: =SUMIFS(Base!$I:$I,Base!$A:$A,$A12) -> 2399877.8 | G12: =E12-F12 -> 0 | H12: Coincide
A13: 860023024 | B13: AGRICOLA AUTOMOTRIZ S.A.S. | C13: 8004129026 | D13: Factura electrónica | E13: 2399877.8 | F13: 2399877.8 | G13: =N(E13)-N(F13) -> 0 | H13: Coincide | I13: 46300
A14: 66807605 | B14: AGUILAR PEREIRA HAYLEM | C14: 1 documento(s) | D14: TOTAL TERCERO | E14: =SUMIFS(Base!$H:$H,Base!$A:$A,$A14) -> 350000 | F14: =SUMIFS(Base!$I:$I,Base!$A:$A,$A14) -> 0 | G14: =E14-F14 -> 350000 | H14: Tercero solo en DIAN
A15: 66807605 | B15: AGUILAR PEREIRA HAYLEM | C15: NDSE1761 | D15: Documento soporte con no obligados | E15: 350000 | G15: =N(E15)-N(F15) -> 350000 | H15: Solo en DIAN | I15: 46317
A16: 16928075 | B16: ALMEIDA BACCA EDWARD ALEXANDER | C16: 3 documento(s) | D16: TOTAL TERCERO | E16: =SUMIFS(Base!$H:$H,Base!$A:$A,$A16) -> 602986.09 | F16: =SUMIFS(Base!$I:$I,Base!$A:$A,$A16) -> 1205969.8 | G16: =E16-F16 -> -602983.71 | H16: Con diferencias
A17: 16928075 | B17: ALMEIDA BACCA EDWARD ALEXANDER | C17: FE689 | D17: Factura electrónica | E17: 598985.31 | F17: 598985.31 | G17: =N(E17)-N(F17) -> 0 | H17: Coincide | I17: 46301
A18: 16928075 | B18: ALMEIDA BACCA EDWARD ALEXANDER | C18: NE31 | D18: Nota de crédito electrónica | E18: -602983.71 | G18: =N(E18)-N(F18) -> -602983.71 | H18: Solo en DIAN | I18: 46301
A19: 16928075 | B19: ALMEIDA BACCA EDWARD ALEXANDER | C19: FE697 | D19: Factura electrónica | E19: 606984.49 | F19: 606984.49 | G19: =N(E19)-N(F19) -> 0 | H19: Coincide | I19: 46303
A20: 900210800 | B20: ANDES SERVICIO DE CERTIFICACION DIGITAL SA | C20: 1 documento(s) | D20: TOTAL TERCERO | E20: =SUMIFS(Base!$H:$H,Base!$A:$A,$A20) -> 130900 | F20: =SUMIFS(Base!$I:$I,Base!$A:$A,$A20) -> 130900 | G20: =E20-F20 -> 0 | H20: Coincide
A21: 900210800 | B21: ANDES SERVICIO DE CERTIFICACION DIGITAL SA | C21: FE178496 | D21: Factura electrónica | E21: 130900 | F21: 130900 | G21: =N(E21)-N(F21) -> 0 | H21: Coincide | I21: 46316
A22: 7563061 | B22: BERRIO ARIAS JUAN FERNANDO | C22: 1 documento(s) | D22: TOTAL TERCERO | E22: =SUMIFS(Base!$H:$H,Base!$A:$A,$A22) -> 300000 | F22: =SUMIFS(Base!$I:$I,Base!$A:$A,$A22) -> 0 | G22: =E22-F22 -> 300000 | H22: Tercero solo en DIAN
A23: 7563061 | B23: BERRIO ARIAS JUAN FERNANDO | C23: NDSE1745 | D23: Documento soporte con no obligados | E23: 300000 | G23: =N(E23)-N(F23) -> 300000 | H23: Solo en DIAN | I23: 46302
A24: 901281572 | B24: BOLD.CO S.A.S | C24: 1 documento(s) | D24: TOTAL TERCERO | E24: =SUMIFS(Base!$H:$H,Base!$A:$A,$A24) -> 210011.46 | F24: =SUMIFS(Base!$I:$I,Base!$A:$A,$A24) -> 0 | G24: =E24-F24 -> 210011.46 | H24: Tercero solo en DIAN
A25: 901281572 | B25: BOLD.CO S.A.S | C25: FEC8813911 | D25: Factura electrónica | E25: 210011.46 | G25: =N(E25)-N(F25) -> 210011.46 | H25: Solo en DIAN | I25: 46307
A26: 901084440 | B26: BRAHAM S.A.S. | C26: 1 documento(s) | D26: TOTAL TERCERO | E26: =SUMIFS(Base!$H:$H,Base!$A:$A,$A26) -> 100000 | F26: =SUMIFS(Base!$I:$I,Base!$A:$A,$A26) -> 100000 | G26: =E26-F26 -> 0 | H26: Coincide
A27: 901084440 | B27: BRAHAM S.A.S. | C27: FELV7089 | D27: Factura electrónica | E27: 100000 | F27: 100000 | G27: =N(E27)-N(F27) -> 0 | H27: Coincide | I27: 46316
A28: 1193142852 | B28: BRAYAN DANILO CORDOBA PERAFAN | C28: 1 documento(s) | D28: TOTAL TERCERO | E28: =SUMIFS(Base!$H:$H,Base!$A:$A,$A28) -> 25000 | F28: =SUMIFS(Base!$I:$I,Base!$A:$A,$A28) -> 0 | G28: =E28-F28 -> 25000 | H28: Tercero solo en DIAN
A29: 1193142852 | B29: BRAYAN DANILO CORDOBA PERAFAN | C29: DJ1763 | D29: Factura electrónica | E29: 25000 | G29: =N(E29)-N(F29) -> 25000 | H29: Solo en DIAN | I29: 46314
A30: 1113519268 | B30: BUENO ALVAREZ WILLIAM ANDRES | C30: 2 documento(s) | D30: TOTAL TERCERO | E30: =SUMIFS(Base!$H:$H,Base!$A:$A,$A30) -> 2628000 | F30: =SUMIFS(Base!$I:$I,Base!$A:$A,$A30) -> 0 | G30: =E30-F30 -> 2628000 | H30: Tercero solo en DIAN
A31: 1113519268 | B31: BUENO ALVAREZ WILLIAM ANDRES | C31: NDSE1750 | D31: Documento soporte con no obligados | E31: 1428000 | G31: =N(E31)-N(F31) -> 1428000 | H31: Solo en DIAN | I31: 46314
A32: 1113519268 | B32: BUENO ALVAREZ WILLIAM ANDRES | C32: NDSE1751 | D32: Documento soporte con no obligados | E32: 1200000 | G32: =N(E32)-N(F32) -> 1200000 | H32: Solo en DIAN | I32: 46314
A33: 901219735 | B33: CAMINOS CREATIVOS MARKETING Y PUBLICIDAD SAS | C33: 1 documento(s) | D33: TOTAL TERCERO | E33: =SUMIFS(Base!$H:$H,Base!$A:$A,$A33) -> 4462500 | F33: =SUMIFS(Base!$I:$I,Base!$A:$A,$A33) -> 4462500 | G33: =E33-F33 -> 0 | H33: Coincide
A34: 901219735 | B34: CAMINOS CREATIVOS MARKETING Y PUBLICIDAD SAS | C34: FE2574 | D34: Factura electrónica | E34: 4462500 | F34: 4462500 | G34: =N(E34)-N(F34) -> 0 | H34: Coincide | I34: 46301
A35: 890321151 | B35: CARVAJAL TECNOLOGIA Y SERVICIOS S.A.S. | C35: 1 documento(s) | D35: TOTAL TERCERO | E35: =SUMIFS(Base!$H:$H,Base!$A:$A,$A35) -> 136776.22 | F35: =SUMIFS(Base!$I:$I,Base!$A:$A,$A35) -> 136776.22 | G35: =E35-F35 -> 0 | H35: Coincide
A36: 890321151 | B36: CARVAJAL TECNOLOGIA Y SERVICIOS S.A.S. | C36: CLOA105299392 | D36: Factura electrónica | E36: 136776.22 | F36: 136776.22 | G36: =N(E36)-N(F36) -> 0 | H36: Coincide | I36: 46300
A37: 67008730 | B37: CHACON MANZANO MARIA DEL CARMEN | C37: 1 documento(s) | D37: TOTAL TERCERO | E37: =SUMIFS(Base!$H:$H,Base!$A:$A,$A37) -> 168000 | F37: =SUMIFS(Base!$I:$I,Base!$A:$A,$A37) -> 168000 | G37: =E37-F37 -> 0 | H37: Coincide
A38: 67008730 | B38: CHACON MANZANO MARIA DEL CARMEN | C38: FEV3320 | D38: Factura electrónica | E38: 168000 | F38: 168000 | G38: =N(E38)-N(F38) -> 0 | H38: Coincide | I38: 46301
A39: 1130588761 | B39: CHRISTIAN CAMILO QUEVEDO OCHOA | C39: 1 documento(s) | D39: TOTAL TERCERO | E39: =SUMIFS(Base!$H:$H,Base!$A:$A,$A39) -> 19000 | F39: =SUMIFS(Base!$I:$I,Base!$A:$A,$A39) -> 19000 | G39: =E39-F39 -> 0 | H39: Coincide
A40: 1130588761 | B40: CHRISTIAN CAMILO QUEVEDO OCHOA | C40: ETPC420 | D40: Factura electrónica | E40: 19000 | F40: 19000 | G40: =N(E40)-N(F40) -> 0 | H40: Coincide | I40: 46298
A41: 890300521 | B41: CLUB COLOMBIA | C41: 3 documento(s) | D41: TOTAL TERCERO | E41: =SUMIFS(Base!$H:$H,Base!$A:$A,$A41) -> 1053750 | F41: =SUMIFS(Base!$I:$I,Base!$A:$A,$A41) -> 1263750 | G41: =E41-F41 -> -210000 | H41: Con diferencias
A42: 890300521 | B42: CLUB COLOMBIA | C42: FS561875 | D42: Factura electrónica | E42: 310000 | F42: 310000 | G42: =N(E42)-N(F42) -> 0 | H42: Coincide | I42: 46297
A43: 890300521 | B43: CLUB COLOMBIA | C43: FS562580 | D43: Factura electrónica | E43: 743750 | F43: 743750 | G43: =N(E43)-N(F43) -> 0 | H43: Coincide | I43: 46303
A44: 890300521 | B44: CLUB COLOMBIA | C44: RF129741 | D44: Factura (solo SIESA) | F44: 210000 | G44: =N(E44)-N(F44) -> -210000 | H44: Solo en SIESA | I44: 46318
A45: 890300225 | B45: COEXITO S.A.S. | C45: 1 documento(s) | D45: TOTAL TERCERO | E45: =SUMIFS(Base!$H:$H,Base!$A:$A,$A45) -> 15000 | F45: =SUMIFS(Base!$I:$I,Base!$A:$A,$A45) -> 15000 | G45: =E45-F45 -> 0 | H45: Coincide
A46: 890300225 | B46: COEXITO S.A.S. | C46: 129M77 | D46: Factura electrónica | E46: 15000 | F46: 15000 | G46: =N(E46)-N(F46) -> 0 | H46: Coincide | I46: 46296
A47: 901528731 | B47: COLMENA SEGUROS DE VIDA S.A. | C47: 1 documento(s) | D47: TOTAL TERCERO | E47: =SUMIFS(Base!$H:$H,Base!$A:$A,$A47) -> 374594.27 | F47: =SUMIFS(Base!$I:$I,Base!$A:$A,$A47) -> 374594.27 | G47: =E47-F47 -> 0 | H47: Coincide
A48: 901528731 | B48: COLMENA SEGUROS DE VIDA S.A. | C48: VT26386988 | D48: Factura electrónica | E48: 374594.27 | F48: 374594.27 | G48: =N(E48)-N(F48) -> 0 | H48: Coincide | I48: 46308
A49: 830122566 | B49: COLOMBIA TELECOMUNICACIONES S.A. E.S.P. BIC | C49: 18 documento(s) | D49: TOTAL TERCERO | E49: =SUMIFS(Base!$H:$H,Base!$A:$A,$A49) -> 675146 | F49: =SUMIFS(Base!$I:$I,Base!$A:$A,$A49) -> 675146 | G49: =E49-F49 -> 0 | H49: Coincide
A50: 830122566 | B50: COLOMBIA TELECOMUNICACIONES S.A. E.S.P. BIC | C50: BEC552441113 | D50: Factura electrónica | E50: 21995 | F50: 21995 | G50: =N(E50)-N(F50) -> 0 | H50: Coincide | I50: 46306
A51: 830122566 | B51: COLOMBIA TELECOMUNICACIONES S.A. E.S.P. BIC | C51: BEC552442170 | D51: Factura electrónica | E51: 53293 | F51: 53293 | G51: =N(E51)-N(F51) -> 0 | H51: Coincide | I51: 46306
A52: 830122566 | B52: COLOMBIA TELECOMUNICACIONES S.A. E.S.P. BIC | C52: BEC552442171 | D52: Factura electrónica | E52: 44875 | F52: 44875 | G52: =N(E52)-N(F52) -> 0 | H52: Coincide | I52: 46306
A53: 830122566 | B53: COLOMBIA TELECOMUNICACIONES S.A. E.S.P. BIC | C53: BEC552443055 | D53: Factura electrónica | E53: 12000 | F53: 12000 | G53: =N(E53)-N(F53) -> 0 | H53: Coincide | I53: 46306
A54: 830122566 | B54: COLOMBIA TELECOMUNICACIONES S.A. E.S.P. BIC | C54: BEC552443143 | D54: Factura electrónica | E54: 21995 | F54: 21995 | G54: =N(E54)-N(F54) -> 0 | H54: Coincide | I54: 46306
A55: 830122566 | B55: COLOMBIA TELECOMUNICACIONES S.A. E.S.P. BIC | C55: BEC552443144 | D55: Factura electrónica | E55: 66348 | F55: 66348 | G55: =N(E55)-N(F55) -> 0 | H55: Coincide | I55: 46306
A56: 830122566 | B56: COLOMBIA TELECOMUNICACIONES S.A. E.S.P. BIC | C56: BEC552443145 | D56: Factura electrónica | E56: 21995 | F56: 21995 | G56: =N(E56)-N(F56) -> 0 | H56: Coincide | I56: 46306
A57: 830122566 | B57: COLOMBIA TELECOMUNICACIONES S.A. E.S.P. BIC | C57: BEC552443146 | D57: Factura electrónica | E57: 66348 | F57: 66348 | G57: =N(E57)-N(F57) -> 0 | H57: Coincide | I57: 46306
A58: 830122566 | B58: COLOMBIA TELECOMUNICACIONES S.A. E.S.P. BIC | C58: BEC552443147 | D58: Factura electrónica | E58: 21995 | F58: 21995 | G58: =N(E58)-N(F58) -> 0 | H58: Coincide | I58: 46306
A59: 830122566 | B59: COLOMBIA TELECOMUNICACIONES S.A. E.S.P. BIC | C59: BEC552443148 | D59: Factura electrónica | E59: 44875 | F59: 44875 | G59: =N(E59)-N(F59) -> 0 | H59: Coincide | I59: 46306
A60: 830122566 | B60: COLOMBIA TELECOMUNICACIONES S.A. E.S.P. BIC | C60: BEC552443150 | D60: Factura electrónica | E60: 21995 | F60: 21995 | G60: =N(E60)-N(F60) -> 0 | H60: Coincide | I60: 46306
A61: 830122566 | B61: COLOMBIA TELECOMUNICACIONES S.A. E.S.P. BIC | C61: BEC552443151 | D61: Factura electrónica | E61: 44875 | F61: 44875 | G61: =N(E61)-N(F61) -> 0 | H61: Coincide | I61: 46306
... A67: 830122566 | B67: COLOMBIA TELECOMUNICACIONES S.A. E.S.P. BIC | C67: BEC552443149 | D67: Factura electrónica | E67: 66348 | F67: 66348 | G67: =N(E67)-N(F67) -> 0 | H67: Coincide | I67: 46307
A68: 800185306 | B68: COLVANES S.A.S | C68: 2 documento(s) | D68: TOTAL TERCERO | E68: =SUMIFS(Base!$H:$H,Base!$A:$A,$A68) -> 7831384 | F68: =SUMIFS(Base!$I:$I,Base!$A:$A,$A68) -> 7831384 | G68: =E68-F68 -> 0 | H68: Coincide
A69: 800185306 | B69: COLVANES S.A.S | C69: FE02173546 | D69: Factura electrónica | E69: 295304 | F69: 295304 | G69: =N(E69)-N(F69) -> 0 | H69: Coincide | I69: 46310
A70: 800185306 | B70: COLVANES S.A.S | C70: FE02173622 | D70: Factura electrónica | E70: 7536080 | F70: 7536080 | G70: =N(E70)-N(F70) -> 0 | H70: Coincide | I70: 46310
A71: 800153993 | B71: COMUNICACION CELULAR S A COMCEL S A | C71: 1 documento(s) | D71: TOTAL TERCERO | E71: =SUMIFS(Base!$H:$H,Base!$A:$A,$A71) -> 408700 | F71: =SUMIFS(Base!$I:$I,Base!$A:$A,$A71) -> 408700 | G71: =E71-F71 -> 0 | H71: Coincide
A72: 800153993 | B72: COMUNICACION CELULAR S A COMCEL S A | C72: 3292766260 | D72: Factura electrónica | E72: 408700 | F72: 408700 | G72: =N(E72)-N(F72) -> 0 | H72: Coincide | I72: 46296
A73: 891500277 | B73: COOPERATIVA INTEGRAL DE TAXIS BELALCAZAR | C73: 2 documento(s) | D73: TOTAL TERCERO | E73: =SUMIFS(Base!$H:$H,Base!$A:$A,$A73) -> 66000 | F73: =SUMIFS(Base!$I:$I,Base!$A:$A,$A73) -> 0 | G73: =E73-F73 -> 66000 | H73: Tercero solo en DIAN
A74: 891500277 | B74: COOPERATIVA INTEGRAL DE TAXIS BELALCAZAR | C74: FTCA352764 | D74: Documento equivalente - Transporte pasajeros terrestre | E74: 33000 | G74: =N(E74)-N(F74) -> 33000 | H74: Solo en DIAN | I74: 46314
A75: 891500277 | B75: COOPERATIVA INTEGRAL DE TAXIS BELALCAZAR | C75: FTPO639435 | D75: Documento equivalente - Transporte pasajeros terrestre | E75: 33000 | G75: =N(E75)-N(F75) -> 33000 | H75: Solo en DIAN | I75: 46316
A76: 890904713 | B76: COORDINADORA MERCANTIL S.A. | C76: 1 documento(s) | D76: TOTAL TERCERO | E76: =SUMIFS(Base!$H:$H,Base!$A:$A,$A76) -> 89720 | F76: =SUMIFS(Base!$I:$I,Base!$A:$A,$A76) -> 89720 | G76: =E76-F76 -> 0 | H76: Coincide
A77: 890904713 | B77: COORDINADORA MERCANTIL S.A. | C77: D03194002002 | D77: Factura electrónica | E77: 89720 | F77: 89720 | G77: =N(E77)-N(F77) -> 0 | H77: Coincide | I77: 46316
A78: 1144176843 | B78: CORREA MOLINA WILLIAM ANDRES | C78: 1 documento(s) | D78: TOTAL TERCERO | E78: =SUMIFS(Base!$H:$H,Base!$A:$A,$A78) -> 390000 | F78: =SUMIFS(Base!$I:$I,Base!$A:$A,$A78) -> 390000 | G78: =E78-F78 -> 0 | H78: Coincide
A79: 1144176843 | B79: CORREA MOLINA WILLIAM ANDRES | C79: FVE500 | D79: Factura electrónica | E79: 390000 | F79: 390000 | G79: =N(E79)-N(F79) -> 0 | H79: Coincide | I79: 46301
A80: 891301773 | B80: CUERPO DE BOMBEROS VOLUNTARIOS DEL CGTO DE ROZO MP PALMIRA | C80: 1 documento(s) | D80: TOTAL TERCERO | E80: =SUMIFS(Base!$H:$H,Base!$A:$A,$A80) -> 46001.83 | F80: =SUMIFS(Base!$I:$I,Base!$A:$A,$A80) -> 46001.83 | G80: =E80-F80 -> 0 | H80: Coincide
A81: 891301773 | B81: CUERPO DE BOMBEROS VOLUNTARIOS DEL CGTO DE ROZO MP PALMIRA | C81: FE3682 | D81: Factura electrónica | E81: 46001.83 | F81: 46001.83 | G81: =N(E81)-N(F81) -> 0 | H81: Coincide | I81: 46311
A82: 900276962 | B82: D1 S A S | C82: 1 documento(s) | D82: TOTAL TERCERO | E82: =SUMIFS(Base!$H:$H,Base!$A:$A,$A82) -> 114609.99 | F82: =SUMIFS(Base!$I:$I,Base!$A:$A,$A82) -> 114609.99 | G82: =E82-F82 -> 0 | H82: Coincide
A83: 900276962 | B83: D1 S A S | C83: G8H1293754 | D83: Factura electrónica | E83: 114609.99 | F83: 114609.99 | G83: =N(E83)-N(F83) -> 0 | H83: Coincide | I83: 46302
A84: 800095116 | B84: DECORWID LIMITADA | C84: 1 documento(s) | D84: TOTAL TERCERO | E84: =SUMIFS(Base!$H:$H,Base!$A:$A,$A84) -> 104000 | F84: =SUMIFS(Base!$I:$I,Base!$A:$A,$A84) -> 104000 | G84: =E84-F84 -> 0 | H84: Coincide
A85: 800095116 | B85: DECORWID LIMITADA | C85: VSFE585777 | D85: Factura electrónica | E85: 104000 | F85: 104000 | G85: =N(E85)-N(F85) -> 0 | H85: Coincide | I85: 46310
A86: 800078697 | B86: DISTRIBUIDORA FARALLONES SAS | C86: 2 documento(s) | D86: TOTAL TERCERO | E86: =SUMIFS(Base!$H:$H,Base!$A:$A,$A86) -> 582743 | F86: =SUMIFS(Base!$I:$I,Base!$A:$A,$A86) -> 582743 | G86: =E86-F86 -> 0 | H86: Coincide
A87: 800078697 | B87: DISTRIBUIDORA FARALLONES SAS | C87: E16269 | D87: Factura electrónica | E87: 214200 | F87: 214200 | G87: =N(E87)-N(F87) -> 0 | H87: Coincide | I87: 46300
A88: 800078697 | B88: DISTRIBUIDORA FARALLONES SAS | C88: E16270 | D88: Factura electrónica | E88: 368543 | F88: 368543 | G88: =N(E88)-N(F88) -> 0 | H88: Coincide | I88: 46300
A89: 800239989 | B89: DISTRIBUIDORA MAYORISTA LIMITADA | C89: 1 documento(s) | D89: TOTAL TERCERO | E89: =SUMIFS(Base!$H:$H,Base!$A:$A,$A89) -> 1120500 | F89: =SUMIFS(Base!$I:$I,Base!$A:$A,$A89) -> 1120500 | G89: =E89-F89 -> 0 | H89: Coincide
A90: 800239989 | B90: DISTRIBUIDORA MAYORISTA LIMITADA | C90: DMFE849 | D90: Factura electrónica | E90: 1120500 | F90: 1120500 | G90: =N(E90)-N(F90) -> 0 | H90: Coincide | I90: 46302
A91: 800126903 | B91: DROGUERIA ALONSO LTDA | C91: 1 documento(s) | D91: TOTAL TERCERO | E91: =SUMIFS(Base!$H:$H,Base!$A:$A,$A91) -> 954751.28 | F91: =SUMIFS(Base!$I:$I,Base!$A:$A,$A91) -> 954751.28 | G91: =E91-F91 -> 0 | H91: Coincide
A92: 800126903 | B92: DROGUERIA ALONSO LTDA | C92: CENT1167 | D92: Factura electrónica | E92: 954751.28 | F92: 954751.28 | G92: =N(E92)-N(F92) -> 0 | H92: Coincide | I92: 46308
A93: 901033735 | B93: EASY PUNTO S.A.S. | C93: 1 documento(s) | D93: TOTAL TERCERO | E93: =SUMIFS(Base!$H:$H,Base!$A:$A,$A93) -> 2400 | F93: =SUMIFS(Base!$I:$I,Base!$A:$A,$A93) -> 0 | G93: =E93-F93 -> 2400 | H93: Tercero solo en DIAN
A94: 901033735 | B94: EASY PUNTO S.A.S. | C94: EIMB489341 | D94: Factura electrónica | E94: 2400 | G94: =N(E94)-N(F94) -> 2400 | H94: Solo en DIAN | I94: 46315
A95: 900727726 | B95: ECOLDIET SAS | C95: 1 documento(s) | D95: TOTAL TERCERO | E95: =SUMIFS(Base!$H:$H,Base!$A:$A,$A95) -> 8806000 | F95: =SUMIFS(Base!$I:$I,Base!$A:$A,$A95) -> 8806000 | G95: =E95-F95 -> 0 | H95: Coincide
A96: 900727726 | B96: ECOLDIET SAS | C96: 602 | D96: Factura electrónica | E96: 8806000 | F96: 8806000 | G96: =N(E96)-N(F96) -> 0 | H96: Coincide | I96: 46308
A97: 890323635 | B97: EL COMERCIO ELECTRICO S.A.S. | C97: 6 documento(s) | D97: TOTAL TERCERO | E97: =SUMIFS(Base!$H:$H,Base!$A:$A,$A97) -> 1160342.6 | F97: =SUMIFS(Base!$I:$I,Base!$A:$A,$A97) -> 1059980.6 | G97: =E97-F97 -> 100362 | H97: Con diferencias
A98: 890323635 | B98: EL COMERCIO ELECTRICO S.A.S. | C98: NFFN33471 | D98: Factura electrónica | E98: 100361.63 | F98: 100361.63 | G98: =N(E98)-N(F98) -> 0 | H98: Coincide | I98: 46296
A99: 890323635 | B99: EL COMERCIO ELECTRICO S.A.S. | C99: NFFN34151 | D99: Factura electrónica | E99: 15083.25 | F99: 15083.25 | G99: =N(E99)-N(F99) -> 0 | H99: Coincide | I99: 46301
A100: 890323635 | B100: EL COMERCIO ELECTRICO S.A.S. | C100: NFFN34626 | D100: Factura electrónica | E100: 211785.79 | F100: 211785.79 | G100: =N(E100)-N(F100) -> 0 | H100: Coincide | I100: 46304
A101: 890323635 | B101: EL COMERCIO ELECTRICO S.A.S. | C101: NFFN35150 | D101: Factura electrónica | E101: 681832.76 | F101: 681832.76 | G101: =N(E101)-N(F101) -> 0 | H101: Coincide | I101: 46309
A102: 890323635 | B102: EL COMERCIO ELECTRICO S.A.S. | C102: NDSE1760 | D102: Documento soporte con no obligados | E102: 100362 | G102: =N(E102)-N(F102) -> 100362 | H102: Solo en DIAN | I102: 46317
A103: 890323635 | B103: EL COMERCIO ELECTRICO S.A.S. | C103: NFFN36319 | D103: Factura electrónica | E103: 50917.13 | F103: 50917.13 | G103: =N(E103)-N(F103) -> 0 | H103: Coincide | I103: 46317
A104: 890308111 | B104: EL MOLINO EDUARDO MOLINARI PALACIN S.A.S | C104: 1 documento(s) | D104: TOTAL TERCERO | E104: =SUMIFS(Base!$H:$H,Base!$A:$A,$A104) -> 14900 | F104: =SUMIFS(Base!$I:$I,Base!$A:$A,$A104) -> 14900 | G104: =E104-F104 -> 0 | H104: Coincide
A105: 890308111 | B105: EL MOLINO EDUARDO MOLINARI PALACIN S.A.S | C105: 2SEX7984 | D105: Factura electrónica | E105: 14900 | F105: 14900 | G105: =N(E105)-N(F105) -> 0 | H105: Coincide | I105: 46304
A106: 901143158 | B106: ELECTRONICA SAN NICOLAS S.A.S | C106: 1 documento(s) | D106: TOTAL TERCERO | E106: =SUMIFS(Base!$H:$H,Base!$A:$A,$A106) -> 111472.99 | F106: =SUMIFS(Base!$I:$I,Base!$A:$A,$A106) -> 0 | G106: =E106-F106 -> 111472.99 | H106: Tercero solo en DIAN
...

Sheet Base
A1: NIT | B1: Tercero | C1: Documento | D1: Tipo de documento | E1: Grupo DIAN | F1: Fecha emisión | G1: Estado documento | H1: Valor DIAN | I1: Valor SIESA | J1: Diferencia | K1: Estado tercero
A2: 805012421 | B2: A.F.TROST HANSEN PRODUCTOS DANCALI SENC | C2: F20110389 | D2: Factura (solo SIESA) | E2: No está en DIAN | F2: 46318 | G2: Solo en SIESA | I2: 100600 | J2: =N(H2)-N(I2) -> -100600 | K2: Tercero solo en SIESA
A3: 805010086 | B3: ADOCCIDENTE S.A.S. | C3: FE1062 | D3: Factura electrónica | E3: Recibido | F3: 46296 | G3: Coincide | H3: 14515620 | I3: 14515620 | J3: =N(H3)-N(I3) -> 0 | K3: Coincide
A4: 890704196 | B4: AEROVIAS DE INTEGRACION REGIONAL S.A. | C4: EFCC4976394 | D4: Documento equivalente - Transporte aéreo de pasajeros | E4: Recibido | F4: 46296 | G4: Solo en DIAN | H4: 521682 | J4: =N(H4)-N(I4) -> 521682 | K4: Con diferencias
A5: 890704196 | B5: AEROVIAS DE INTEGRACION REGIONAL S.A. | C5: SPC45772 | D5: Factura electrónica | E5: Recibido | F5: 46310 | G5: Coincide | H5: 4450876 | I5: 4450876 | J5: =N(H5)-N(I5) -> 0 | K5: Con diferencias
A6: 860023024 | B6: AGRICOLA AUTOMOTRIZ S.A.S. | C6: 8004129026 | D6: Factura electrónica | E6: Recibido | F6: 46300 | G6: Coincide | H6: 2399877.8 | I6: 2399877.8 | J6: =N(H6)-N(I6) -> 0 | K6: Coincide
A7: 66807605 | B7: AGUILAR PEREIRA HAYLEM | C7: NDSE1761 | D7: Documento soporte con no obligados | E7: Emitido | F7: 46317 | G7: Solo en DIAN | H7: 350000 | J7: =N(H7)-N(I7) -> 350000 | K7: Tercero solo en DIAN
A8: 16928075 | B8: ALMEIDA BACCA EDWARD ALEXANDER | C8: FE689 | D8: Factura electrónica | E8: Recibido | F8: 46301 | G8: Coincide | H8: 598985.31 | I8: 598985.31 | J8: =N(H8)-N(I8) -> 0 | K8: Con diferencias
A9: 16928075 | B9: ALMEIDA BACCA EDWARD ALEXANDER | C9: NE31 | D9: Nota de crédito electrónica | E9: Recibido | F9: 46301 | G9: Solo en DIAN | H9: -602983.71 | J9: =N(H9)-N(I9) -> -602983.71 | K9: Con diferencias
A10: 16928075 | B10: ALMEIDA BACCA EDWARD ALEXANDER | C10: FE697 | D10: Factura electrónica | E10: Recibido | F10: 46303 | G10: Coincide | H10: 606984.49 | I10: 606984.49 | J10: =N(H10)-N(I10) -> 0 | K10: Con diferencias
A11: 900210800 | B11: ANDES SERVICIO DE CERTIFICACION DIGITAL SA | C11: FE178496 | D11: Factura electrónica | E11: Recibido | F11: 46316 | G11: Coincide | H11: 130900 | I11: 130900 | J11: =N(H11)-N(I11) -> 0 | K11: Coincide
A12: 7563061 | B12: BERRIO ARIAS JUAN FERNANDO | C12: NDSE1745 | D12: Documento soporte con no obligados | E12: Emitido | F12: 46302 | G12: Solo en DIAN | H12: 300000 | J12: =N(H12)-N(I12) -> 300000 | K12: Tercero solo en DIAN
A13: 901281572 | B13: BOLD.CO S.A.S | C13: FEC8813911 | D13: Factura electrónica | E13: Recibido | F13: 46307 | G13: Solo en DIAN | H13: 210011.46 | J13: =N(H13)-N(I13) -> 210011.46 | K13: Tercero solo en DIAN
A14: 901084440 | B14: BRAHAM S.A.S. | C14: FELV7089 | D14: Factura electrónica | E14: Recibido | F14: 46316 | G14: Coincide | H14: 100000 | I14: 100000 | J14: =N(H14)-N(I14) -> 0 | K14: Coincide
A15: 1193142852 | B15: BRAYAN DANILO CORDOBA PERAFAN | C15: DJ1763 | D15: Factura electrónica | E15: Recibido | F15: 46314 | G15: Solo en DIAN | H15: 25000 | J15: =N(H15)-N(I15) -> 25000 | K15: Tercero solo en DIAN
A16: 1113519268 | B16: BUENO ALVAREZ WILLIAM ANDRES | C16: NDSE1750 | D16: Documento soporte con no obligados | E16: Emitido | F16: 46314 | G16: Solo en DIAN | H16: 1428000 | J16: =N(H16)-N(I16) -> 1428000 | K16: Tercero solo en DIAN
A17: 1113519268 | B17: BUENO ALVAREZ WILLIAM ANDRES | C17: NDSE1751 | D17: Documento soporte con no obligados | E17: Emitido | F17: 46314 | G17: Solo en DIAN | H17: 1200000 | J17: =N(H17)-N(I17) -> 1200000 | K17: Tercero solo en DIAN
A18: 901219735 | B18: CAMINOS CREATIVOS MARKETING Y PUBLICIDAD SAS | C18: FE2574 | D18: Factura electrónica | E18: Recibido | F18: 46301 | G18: Coincide | H18: 4462500 | I18: 4462500 | J18: =N(H18)-N(I18) -> 0 | K18: Coincide
A19: 890321151 | B19: CARVAJAL TECNOLOGIA Y SERVICIOS S.A.S. | C19: CLOA105299392 | D19: Factura electrónica | E19: Recibido | F19: 46300 | G19: Coincide | H19: 136776.22 | I19: 136776.22 | J19: =N(H19)-N(I19) -> 0 | K19: Coincide
A20: 67008730 | B20: CHACON MANZANO MARIA DEL CARMEN | C20: FEV3320 | D20: Factura electrónica | E20: Recibido | F20: 46301 | G20: Coincide | H20: 168000 | I20: 168000 | J20: =N(H20)-N(I20) -> 0 | K20: Coincide
A21: 1130588761 | B21: CHRISTIAN CAMILO QUEVEDO OCHOA | C21: ETPC420 | D21: Factura electrónica | E21: Recibido | F21: 46298 | G21: Coincide | H21: 19000 | I21: 19000 | J21: =N(H21)-N(I21) -> 0 | K21: Coincide
A22: 890300521 | B22: CLUB COLOMBIA | C22: FS561875 | D22: Factura electrónica | E22: Recibido | F22: 46297 | G22: Coincide | H22: 310000 | I22: 310000 | J22: =N(H22)-N(I22) -> 0 | K22: Con diferencias
A23: 890300521 | B23: CLUB COLOMBIA | C23: FS562580 | D23: Factura electrónica | E23: Recibido | F23: 46303 | G23: Coincide | H23: 743750 | I23: 743750 | J23: =N(H23)-N(I23) -> 0 | K23: Con diferencias
A24: 890300521 | B24: CLUB COLOMBIA | C24: RF129741 | D24: Factura (solo SIESA) | E24: No está en DIAN | F24: 46318 | G24: Solo en SIESA | I24: 210000 | J24: =N(H24)-N(I24) -> -210000 | K24: Con diferencias
A25: 890300225 | B25: COEXITO S.A.S. | C25: 129M77 | D25: Factura electrónica | E25: Recibido | F25: 46296 | G25: Coincide | H25: 15000 | I25: 15000 | J25: =N(H25)-N(I25) -> 0 | K25: Coincide
A26: 901528731 | B26: COLMENA SEGUROS DE VIDA S.A. | C26: VT26386988 | D26: Factura electrónica | E26: Recibido | F26: 46308 | G26: Coincide | H26: 374594.27 | I26: 374594.27 | J26: =N(H26)-N(I26) -> 0 | K26: Coincide
A27: 830122566 | B27: COLOMBIA TELECOMUNICACIONES S.A. E.S.P. BIC | C27: BEC552441113 | D27: Factura electrónica | E27: Recibido | F27: 46306 | G27: Coincide | H27: 21995 | I27: 21995 | J27: =N(H27)-N(I27) -> 0 | K27: Coincide
A28: 830122566 | B28: COLOMBIA TELECOMUNICACIONES S.A. E.S.P. BIC | C28: BEC552442170 | D28: Factura electrónica | E28: Recibido | F28: 46306 | G28: Coincide | H28: 53293 | I28: 53293 | J28: =N(H28)-N(I28) -> 0 | K28: Coincide
A29: 830122566 | B29: COLOMBIA TELECOMUNICACIONES S.A. E.S.P. BIC | C29: BEC552442171 | D29: Factura electrónica | E29: Recibido | F29: 46306 | G29: Coincide | H29: 44875 | I29: 44875 | J29: =N(H29)-N(I29) -> 0 | K29: Coincide
A30: 830122566 | B30: COLOMBIA TELECOMUNICACIONES S.A. E.S.P. BIC | C30: BEC552443055 | D30: Factura electrónica | E30: Recibido | F30: 46306 | G30: Coincide | H30: 12000 | I30: 12000 | J30: =N(H30)-N(I30) -> 0 | K30: Coincide
A31: 830122566 | B31: COLOMBIA TELECOMUNICACIONES S.A. E.S.P. BIC | C31: BEC552443143 | D31: Factura electrónica | E31: Recibido | F31: 46306 | G31: Coincide | H31: 21995 | I31: 21995 | J31: =N(H31)-N(I31) -> 0 | K31: Coincide
A32: 830122566 | B32: COLOMBIA TELECOMUNICACIONES S.A. E.S.P. BIC | C32: BEC552443144 | D32: Factura electrónica | E32: Recibido | F32: 46306 | G32: Coincide | H32: 66348 | I32: 66348 | J32: =N(H32)-N(I32) -> 0 | K32: Coincide
A33: 830122566 | B33: COLOMBIA TELECOMUNICACIONES S.A. E.S.P. BIC | C33: BEC552443145 | D33: Factura electrónica | E33: Recibido | F33: 46306 | G33: Coincide | H33: 21995 | I33: 21995 | J33: =N(H33)-N(I33) -> 0 | K33: Coincide
A34: 830122566 | B34: COLOMBIA TELECOMUNICACIONES S.A. E.S.P. BIC | C34: BEC552443146 | D34: Factura electrónica | E34: Recibido | F34: 46306 | G34: Coincide | H34: 66348 | I34: 66348 | J34: =N(H34)-N(I34) -> 0 | K34: Coincide
A35: 830122566 | B35: COLOMBIA TELECOMUNICACIONES S.A. E.S.P. BIC | C35: BEC552443147 | D35: Factura electrónica | E35: Recibido | F35: 46306 | G35: Coincide | H35: 21995 | I35: 21995 | J35: =N(H35)-N(I35) -> 0 | K35: Coincide
A36: 830122566 | B36: COLOMBIA TELECOMUNICACIONES S.A. E.S.P. BIC | C36: BEC552443148 | D36: Factura electrónica | E36: Recibido | F36: 46306 | G36: Coincide | H36: 44875 | I36: 44875 | J36: =N(H36)-N(I36) -> 0 | K36: Coincide
... A47: 800153993 | B47: COMUNICACION CELULAR S A COMCEL S A | C47: 3292766260 | D47: Factura electrónica | E47: Recibido | F47: 46296 | G47: Coincide | H47: 408700 | I47: 408700 | J47: =N(H47)-N(I47) -> 0 | K47: Coincide
A48: 891500277 | B48: COOPERATIVA INTEGRAL DE TAXIS BELALCAZAR | C48: FTCA352764 | D48: Documento equivalente - Transporte pasajeros terrestre | E48: Recibido | F48: 46314 | G48: Solo en DIAN | H48: 33000 | J48: =N(H48)-N(I48) -> 33000 | K48: Tercero solo en DIAN
A49: 891500277 | B49: COOPERATIVA INTEGRAL DE TAXIS BELALCAZAR | C49: FTPO639435 | D49: Documento equivalente - Transporte pasajeros terrestre | E49: Recibido | F49: 46316 | G49: Solo en DIAN | H49: 33000 | J49: =N(H49)-N(I49) -> 33000 | K49: Tercero solo en DIAN
A50: 890904713 | B50: COORDINADORA MERCANTIL S.A. | C50: D03194002002 | D50: Factura electrónica | E50: Recibido | F50: 46316 | G50: Coincide | H50: 89720 | I50: 89720 | J50: =N(H50)-N(I50) -> 0 | K50: Coincide
A51: 1144176843 | B51: CORREA MOLINA WILLIAM ANDRES | C51: FVE500 | D51: Factura electrónica | E51: Recibido | F51: 46301 | G51: Coincide | H51: 390000 | I51: 390000 | J51: =N(H51)-N(I51) -> 0 | K51: Coincide
A52: 891301773 | B52: CUERPO DE BOMBEROS VOLUNTARIOS DEL CGTO DE ROZO MP PALMIRA | C52: FE3682 | D52: Factura electrónica | E52: Recibido | F52: 46311 | G52: Coincide | H52: 46001.83 | I52: 46001.83 | J52: =N(H52)-N(I52) -> 0 | K52: Coincide
A53: 900276962 | B53: D1 S A S | C53: G8H1293754 | D53: Factura electrónica | E53: Recibido | F53: 46302 | G53: Coincide | H53: 114609.99 | I53: 114609.99 | J53: =N(H53)-N(I53) -> 0 | K53: Coincide
A54: 800095116 | B54: DECORWID LIMITADA | C54: VSFE585777 | D54: Factura electrónica | E54: Recibido | F54: 46310 | G54: Coincide | H54: 104000 | I54: 104000 | J54: =N(H54)-N(I54) -> 0 | K54: Coincide
A55: 800078697 | B55: DISTRIBUIDORA FARALLONES SAS | C55: E16269 | D55: Factura electrónica | E55: Recibido | F55: 46300 | G55: Coincide | H55: 214200 | I55: 214200 | J55: =N(H55)-N(I55) -> 0 | K55: Coincide
A56: 800078697 | B56: DISTRIBUIDORA FARALLONES SAS | C56: E16270 | D56: Factura electrónica | E56: Recibido | F56: 46300 | G56: Coincide | H56: 368543 | I56: 368543 | J56: =N(H56)-N(I56) -> 0 | K56: Coincide
A57: 800239989 | B57: DISTRIBUIDORA MAYORISTA LIMITADA | C57: DMFE849 | D57: Factura electrónica | E57: Recibido | F57: 46302 | G57: Coincide | H57: 1120500 | I57: 1120500 | J57: =N(H57)-N(I57) -> 0 | K57: Coincide
A58: 800126903 | B58: DROGUERIA ALONSO LTDA | C58: CENT1167 | D58: Factura electrónica | E58: Recibido | F58: 46308 | G58: Coincide | H58: 954751.28 | I58: 954751.28 | J58: =N(H58)-N(I58) -> 0 | K58: Coincide
A59: 901033735 | B59: EASY PUNTO S.A.S. | C59: EIMB489341 | D59: Factura electrónica | E59: Recibido | F59: 46315 | G59: Solo en DIAN | H59: 2400 | J59: =N(H59)-N(I59) -> 2400 | K59: Tercero solo en DIAN
A60: 900727726 | B60: ECOLDIET SAS | C60: 602 | D60: Factura electrónica | E60: Recibido | F60: 46308 | G60: Coincide | H60: 8806000 | I60: 8806000 | J60: =N(H60)-N(I60) -> 0 | K60: Coincide
A61: 890323635 | B61: EL COMERCIO ELECTRICO S.A.S. | C61: NFFN33471 | D61: Factura electrónica | E61: Recibido | F61: 46296 | G61: Coincide | H61: 100361.63 | I61: 100361.63 | J61: =N(H61)-N(I61) -> 0 | K61: Con diferencias
A62: 890323635 | B62: EL COMERCIO ELECTRICO S.A.S. | C62: NFFN34151 | D62: Factura electrónica | E62: Recibido | F62: 46301 | G62: Coincide | H62: 15083.25 | I62: 15083.25 | J62: =N(H62)-N(I62) -> 0 | K62: Con diferencias
A63: 890323635 | B63: EL COMERCIO ELECTRICO S.A.S. | C63: NFFN34626 | D63: Factura electrónica | E63: Recibido | F63: 46304 | G63: Coincide | H63: 211785.79 | I63: 211785.79 | J63: =N(H63)-N(I63) -> 0 | K63: Con diferencias
A64: 890323635 | B64: EL COMERCIO ELECTRICO S.A.S. | C64: NFFN35150 | D64: Factura electrónica | E64: Recibido | F64: 46309 | G64: Coincide | H64: 681832.76 | I64: 681832.76 | J64: =N(H64)-N(I64) -> 0 | K64: Con diferencias
A65: 890323635 | B65: EL COMERCIO ELECTRICO S.A.S. | C65: NDSE1760 | D65: Documento soporte con no obligados | E65: Emitido | F65: 46317 | G65: Solo en DIAN | H65: 100362 | J65: =N(H65)-N(I65) -> 100362 | K65: Con diferencias
A66: 890323635 | B66: EL COMERCIO ELECTRICO S.A.S. | C66: NFFN36319 | D66: Factura electrónica | E66: Recibido | F66: 46317 | G66: Coincide | H66: 50917.13 | I66: 50917.13 | J66: =N(H66)-N(I66) -> 0 | K66: Con diferencias
A67: 890308111 | B67: EL MOLINO EDUARDO MOLINARI PALACIN S.A.S | C67: 2SEX7984 | D67: Factura electrónica | E67: Recibido | F67: 46304 | G67: Coincide | H67: 14900 | I67: 14900 | J67: =N(H67)-N(I67) -> 0 | K67: Coincide
A68: 901143158 | B68: ELECTRONICA SAN NICOLAS S.A.S | C68: FCPE164633 | D68: Factura electrónica | E68: Recibido | F68: 46309 | G68: Solo en DIAN | H68: 111472.99 | J68: =N(H68)-N(I68) -> 111472.99 | K68: Tercero solo en DIAN
A69: 890399003 | B69: EMPRESAS MUNICIPALES DE CALI E.I.C.E. E.S.P. | C69: 10945561 | D69: Factura electrónica | E69: Recibido | F69: 46300 | G69: Solo en DIAN | H69: 16387 | J69: =N(H69)-N(I69) -> 16387 | K69: Tercero solo en DIAN
A70: 890399003 | B70: EMPRESAS MUNICIPALES DE CALI E.I.C.E. E.S.P. | C70: 10946367 | D70: Factura electrónica | E70: Recibido | F70: 46300 | G70: Solo en DIAN | H70: 428400 | J70: =N(H70)-N(I70) -> 428400 | K70: Tercero solo en DIAN
A71: 890399003 | B71: EMPRESAS MUNICIPALES DE CALI E.I.C.E. E.S.P. | C71: 10947163 | D71: Factura electrónica | E71: Recibido | F71: 46300 | G71: Solo en DIAN | H71: 189867 | J71: =N(H71)-N(I71) -> 189867 | K71: Tercero solo en DIAN
A72: 890399003 | B72: EMPRESAS MUNICIPALES DE CALI E.I.C.E. E.S.P. | C72: 11009341 | D72: Factura electrónica | E72: Recibido | F72: 46303 | G72: Solo en DIAN | H72: 968223 | J72: =N(H72)-N(I72) -> 968223 | K72: Tercero solo en DIAN
A73: 890399003 | B73: EMPRESAS MUNICIPALES DE CALI E.I.C.E. E.S.P. | C73: 19441339 | D73: Documento equivalente - Servicios públicos domiciliarios | E73: Recibido | F73: 46308 | G73: Solo en DIAN | H73: 3076676 | J73: =N(H73)-N(I73) -> 3076676 | K73: Tercero solo en DIAN
A74: 890399003 | B74: EMPRESAS MUNICIPALES DE CALI E.I.C.E. E.S.P. | C74: 19442954 | D74: Documento equivalente - Servicios públicos domiciliarios | E74: Recibido | F74: 46308 | G74: Solo en DIAN | H74: 612451 | J74: =N(H74)-N(I74) -> 612451 | K74: Tercero solo en DIAN
A75: 31886310 | B75: FERNANDEZ CABAL GLORIA ISABEL | C75: NDSE1753 | D75: Documento soporte con no obligados | E75: Emitido | F75: 46316 | G75: Solo en DIAN | H75: 9898594 | J75: =N(H75)-N(I75) -> 9898594 | K75: Tercero solo en DIAN
A76: 1144095306 | B76: GALVIS TASCON NATALIA | C76: NDSE1738 | D76: Documento soporte con no obligados | E76: Emitido | F76: 46302 | G76: Solo en DIAN | H76: 25250 | J76: =N(H76)-N(I76) -> 25250 | K76: Tercero solo en DIAN
A77: 1144095306 | B77: GALVIS TASCON NATALIA | C77: NDSE1739 | D77: Documento soporte con no obligados | E77: Emitido | F77: 46302 | G77: Solo en DIAN | H77: 29900 | J77: =N(H77)-N(I77) -> 29900 | K77: Tercero solo en DIAN
A78: 900680284 | B78: GRUPO AZC S.A.S. | C78: AZ104832 | D78: Factura electrónica | E78: Recibido | F78: 46297 | G78: Coincide | H78: 4042161.1 | I78: 4042161.1 | J78: =N(H78)-N(I78) -> 0 | K78: Coincide
A79: 902064140 | B79: GRUPO BLINDADOS DE OCCIDENTE LTDA | C79: GBO12 | D79: Factura electrónica | E79: Recibido | F79: 46296 | G79: Coincide | H79: 63070000 | I79: 63070000 | J79: =N(H79)-N(I79) -> 0 | K79: Coincide
A80: 900702496 | B80: GRUPO FMC SAS | C80: PTOE60080 | D80: Factura (solo SIESA) | E80: No está en DIAN | F80: 46296 | G80: Solo en SIESA | I80: 91238 | J80: =N(H80)-N(I80) -> -91238 | K80: Tercero solo en SIESA
A81: 900702496 | B81: GRUPO FMC SAS | C81: PTOE60085 | D81: Factura (solo SIESA) | E81: No está en DIAN | F81: 46296 | G81: Solo en SIESA | I81: 57693 | J81: =N(H81)-N(I81) -> -57693 | K81: Tercero solo en SIESA
A82: 901177349 | B82: GRUPO GESTIÓN PRODUCTIVA ORGANIZACIONAL S.A.S. | C82: FA1313 | D82: Factura electrónica | E82: Recibido | F82: 46302 | G82: Coincide | H82: 1666000 | I82: 1666000 | J82: =N(H82)-N(I82) -> 0 | K82: Coincide
A83: 16848018 | B83: GUERRERO SPITTIA ANDRES JAVIER | C83: NDSE1758 | D83: Documento soporte con no obligados | E83: Emitido | F83: 46317 | G83: Solo en DIAN | H83: 15000 | J83: =N(H83)-N(I83) -> 15000 | K83: Tercero solo en DIAN
A84: 900486588 | B84: HANGAR PARK S.A.S | C84: FEC2140859 | D84: Factura electrónica | E84: Recibido | F84: 46316 | G84: Coincide | H84: 19000 | I84: 19000 | J84: =N(H84)-N(I84) -> 0 | K84: Coincide
A85: 860039988 | B85: HDI SEGUROS COLOMBIA S.A. | C85: FPO15168314 | D85: Factura electrónica | E85: Recibido | F85: 46298 | G85: Coincide | H85: 3276502 | I85: 3276502 | J85: =N(H85)-N(I85) -> 0 | K85: Con diferencias
A86: 860039988 | B86: HDI SEGUROS COLOMBIA S.A. | C86: NCFP2160856 | D86: Nota de crédito electrónica | E86: Recibido | F86: 46302 | G86: Solo en DIAN | H86: -115352 | J86: =N(H86)-N(I86) -> -115352 | K86: Con diferencias
A87: 860039988 | B87: HDI SEGUROS COLOMBIA S.A. | C87: FPO15206840 | D87: Factura electrónica | E87: Recibido | F87: 46303 | G87: Coincide | H87: 290191 | I87: 290191 | J87: =N(H87)-N(I87) -> 0 | K87: Con diferencias
A88: 16740143 | B88: HECTOR HUGO CHACUA JIMENEZ | C88: TCFV36134 | D88: Factura electrónica | E88: Recibido | F88: 46297 | G88: Coincide | H88: 168000 | I88: 168000 | J88: =N(H88)-N(I88) -> 0 | K88: Con diferencias
A89: 16740143 | B89: HECTOR HUGO CHACUA JIMENEZ | C89: NC2600 | D89: Nota de crédito electrónica | E89: Recibido | F89: 46301 | G89: Solo en DIAN | H89: -168000 | J89: =N(H89)-N(I89) -> -168000 | K89: Con diferencias
A90: 805027722 | B90: IDEAS IMPRESIÓN Y DISEÑO S.A.S. | C90: FE1626 | D90: Factura electrónica | E90: Recibido | F90: 46312 | G90: Coincide | H90: 1630300 | I90: 1630300 | J90: =N(H90)-N(I90) -> 0 | K90: Coincide
A91: 901636923 | B91: IMPOGRAFIK SAS | C91: FEV207 | D91: Factura electrónica | E91: Recibido | F91: 46309 | G91: Coincide | H91: 45000 | I91: 45000 | J91: =N(H91)-N(I91) -> 0 | K91: Coincide
A92: 900128172 | B92: INDUSTRIAS L.H. S.A.S. | C92: PRAC54469 | D92: Factura electrónica | E92: Recibido | F92: 46296 | G92: Coincide | H92: 190749.86 | I92: 190749.86 | J92: =N(H92)-N(I92) -> 0 | K92: Coincide
A93: 10128057 | B93: JAIRO DE JESUS RAMIREZ OSSA | C93: FVE4112 | D93: Factura electrónica | E93: Recibido | F93: 46315 | G93: Coincide | H93: 241570 | I93: 241570 | J93: =N(H93)-N(I93) -> 0 | K93: Coincide
A94: 1005874702 | B94: JARAMILLO OSORIO VALERIA | C94: NDSE1743 | D94: Documento soporte con no obligados | E94: Emitido | F94: 46302 | G94: Solo en DIAN | H94: 1420000 | J94: =N(H94)-N(I94) -> 1420000 | K94: Tercero solo en DIAN
A95: 700001614 | B95: JIANG JIANPING | C95: NDSE1742 | D95: Documento soporte con no obligados | E95: Emitido | F95: 46302 | G95: Solo en DIAN | H95: 91600 | J95: =N(H95)-N(I95) -> 91600 | K95: Tercero solo en DIAN
A96: 700001614 | B96: JIANG JIANPING | C96: NDSE1757 | D96: Documento soporte con no obligados | E96: Emitido | F96: 46317 | G96: Solo en DIAN | H96: 54000 | J96: =N(H96)-N(I96) -> 54000 | K96: Tercero solo en DIAN
A97: 6645873 | B97: JOHNY EULALIO CABEZAS ORTIZ | C97: POSF17223 | D97: Factura electrónica | E97: Recibido | F97: 46300 | G97: Coincide | H97: 20000 | I97: 20000 | J97: =N(H97)-N(I97) -> 0 | K97: Coincide
A98: 6645873 | B98: JOHNY EULALIO CABEZAS ORTIZ | C98: POSF17373 | D98: Factura electrónica | E98: Recibido | F98: 46310 | G98: Coincide | H98: 20000 | I98: 20000 | J98: =N(H98)-N(I98) -> 0 | K98: Coincide
A99: 6645873 | B99: JOHNY EULALIO CABEZAS ORTIZ | C99: POSF17374 | D99: Factura electrónica | E99: Recibido | F99: 46310 | G99: Coincide | H99: 20000 | I99: 20000 | J99: =N(H99)-N(I99) -> 0 | K99: Coincide
A100: 901531447 | B100: K RAMIREZ SAS | C100: BZ597561 | D100: Factura electrónica | E100: Recibido | F100: 46297 | G100: Coincide | H100: 93300 | I100: 93300 | J100: =N(H100)-N(I100) -> 0 | K100: Coincide
A101: 901531447 | B101: K RAMIREZ SAS | C101: BZ598312 | D101: Factura electrónica | E101: Recibido | F101: 46298 | G101: Coincide | H101: 88100 | I101: 88100 | J101: =N(H101)-N(I101) -> 0 | K101: Coincide
A102: 800049104 | B102: LABORATORIO CLINICO COLMEDICOS IPS SAS | C102: FCE53668 | D102: Factura electrónica | E102: Recibido | F102: 46316 | G102: Coincide | H102: 212000 | I102: 212000 | J102: =N(H102)-N(I102) -> 0 | K102: Coincide
A103: 31579867 | B103: LOPEZ TORRES SULAY | C103: NDSE1746 | D103: Documento soporte con no obligados | E103: Emitido | F103: 46302 | G103: Solo en DIAN | H103: 5800000 | J103: =N(H103)-N(I103) -> 5800000 | K103: Tercero solo en DIAN
A104: 16591962 | B104: LUIS FERNANDO MENA SALDARRIAGA | C104: FE57 | D104: Factura electrónica | E104: Recibido | F104: 46310 | G104: Coincide | H104: 4000000 | I104: 4000000 | J104: =N(H104)-N(I104) -> 0 | K104: Coincide
A105: 16591962 | B105: LUIS FERNANDO MENA SALDARRIAGA | C105: FE58 | D105: Factura electrónica | E105: Recibido | F105: 46310 | G105: Coincide | H105: 17000000 | I105: 17000000 | J105: =N(H105)-N(I105) -> 0 | K105: Coincide
A106: 16591962 | B106: LUIS FERNANDO MENA SALDARRIAGA | C106: FE59 | D106: Factura electrónica | E106: Recibido | F106: 46310 | G106: Coincide | H106: 2379000 | I106: 2379000 | J106: =N(H106)-N(I106) -> 0 | K106: Coincide
A107: 900434009 | B107: MACROTICS S.A.S. | C107: 213089 | D107: Factura electrónica | E107: Recibido | F107: 46297 | G107: Solo en DIAN | H107: 3564000 | J107: =N(H107)-N(I107) -> 3564000 | K107: Tercero solo en DIAN
A108: 900491889 | B108: MASSER S A S | C108: KO51514645 | D108: Factura electrónica | E108: Recibido | F108: 46304 | G108: Coincide | H108: 150000 | I108: 150000 | J108: =N(H108)-N(I108) -> 0 | K108: Coincide
A109: 16601539 | B109: MENA SALDARRIAGA CARLOS ALFONSO | C109: NDSE1752 | D109: Documento soporte con no obligados | E109: Emitido | F109: 46316 | G109: Solo en DIAN | H109: 1500000 | J109: =N(H109)-N(I109) -> 1500000 | K109: Tercero solo en DIAN
A110: 900061224 | B110: MERCAMIO SA | C110: 7YFE696360 | D110: Factura (solo SIESA) | E110: No está en DIAN | F110: 46318 | G110: Solo en SIESA | I110: 40850 | J110: =N(H110)-N(I110) -> -40850 | K110: Tercero solo en SIESA
...
