Workbook

Sheet Resumen
A1: Resumen de la conciliación DIAN vs Journal — septiembre 2026
A3: Documentos revisados (DIAN + Journal sin DIAN) | B3: =COUNTA(Conciliación!$M$2:$M$486) -> 485
A4: de los cuales presentes en la DIAN | B4: =COUNTIF(Conciliación!$N$2:$N$486,"DIAN") -> 373
A5: de los cuales solo en el Journal | B5: =COUNTIF(Conciliación!$N$2:$N$486,"Journal") -> 112
A6: VERIFICADOS | B6: =COUNTIF(Conciliación!$M$2:$M$486,"VERIFICADO") -> 33
A7: PENDIENTES | B7: =COUNTIF(Conciliación!$M$2:$M$486,"PENDIENTE") -> 239
A8: INFORMACIÓN INSUFICIENTE | B8: =COUNTIF(Conciliación!$M$2:$M$486,"INFORMACIÓN INSUFICIENTE") -> 213
A9: Documentos con diferencia de valor (DIAN vs Journal) | B9: =COUNTIF(Conciliación!$G$2:$G$486,">0")+COUNTIF(Conciliación!$G$2:$G$486,"<0") -> 46
A10: Valor acumulado de diferencias (absoluto) | B10: =SUMIF(Conciliación!$G$2:$G$486,">0")-SUMIF(Conciliación!$G$2:$G$486,"<0") -> 10945453
A11: Valor neto de diferencias (DIAN − Journal) | B11: =SUM(Conciliación!$G$2:$G$486) -> 21837.349
A12: Pendientes + insuficientes enviados a revisión manual | B12: =COUNTA('Pendientes de revisión manual'!$M$2:$M$453) -> 452
A14: Notas de método y límites
A15: 1. Se usaron únicamente los dos archivos (DIAN y Journal); los originales no se modificaron.
A16: 2. Documento DIAN = Prefijo+Folio; el tercero es el Emisor (recibidos) o el Receptor (documentos soporte emitidos). Se cruza por NIT del tercero y folio citado en la referencia/descripción de las líneas del Journal.
A17: 3. Valor en el Journal = suma de las líneas del comprobante de causación del tercero (IVA + otros impuestos + gastos + inventarios/activos + otros). Verificación cruzada: lado proveedor (2205/2210/2335) + retenciones (2365/2367/2368) debe ser igual a esa suma.
A18: 4. ESTADO "Contabilizado": el Journal es un auxiliar contable exportado y NO trae columna de estado. Se asumió que un movimiento en el auxiliar está contabilizado; si existe otro criterio de estado, validar.
A19: 5. LÍMITE DEL ARCHIVO: el Journal tiene 16,383 filas y termina en la cuenta 51251001 (clase 5 incompleta; faltan cuentas de gasto posteriores, clases 6 y 7). Por eso muchas facturas no tienen completas sus líneas de gasto: si el lado proveedor + retenciones coincide con la DIAN quedan como INFORMACIÓN INSUFICIENTE, no VERIFICADO. Volver a exportar el Journal completo (o por rangos de cuenta) y ejecutar de nuevo conciliar.py.
A20: 6. Los registros "solo en el Journal" se limitan a comprobantes que abonan (causan) proveedores/acreedores (2205, 2210, 2335); no se listan pagos, legalizaciones ni notas que solo reducen la cuenta por pagar, ni pagos directos de banco/caja sin causación.
A21: 7. Las diferencias son exactas (sin tolerancia); no se ajustó ningún valor.

Sheet Conciliación
A1: Nombre del tercero | B1: NIT o identificación | C1: Número del documento | D1: Cuenta contable y auxiliar | E1: Valor total según la DIAN | F1: Valor total sumado en el Journal | G1: Diferencia (DIAN − Journal) | H1: Desglose de conceptos contables | I1: Estado en la DIAN | J1: Estado en el Journal | K1: Motivo por el cual queda pendiente | L1: Observaciones para revisión manual | M1: Clasificación | N1: Origen | O1: Comprobante(s) Journal | P1: Fila(s) en el Journal | Q1: Método de cruce | R1: Lado gasto/IVA completo en el Journal
A2: ACEVEDO JOSE NORBEY | B2: 6137792 | C2: NDSE1703 | D2: 23359501 OTROS; 23652507 SERVICIOS GENERALES (DECLARANTES) 4%; 23680203 DEMAS ACTIVIDADES SERVICIOS 10 X 1000 | E2: 289000 | F2: 289000 | G2: =IF(AND(ISNUMBER(E2),ISNUMBER(F2)),E2-F2,"No disponible") -> 0 | H2: Retenciones (crédito): 14,450.00 | Gasto/otros: No disponible (líneas fuera del archivo exportado) | I2: Aprobado con notificación (Documento soporte con no obligados, Emitido) | J2: Presente en el auxiliar (el archivo no trae columna de estado; se infiere Contabilizado) | K2: El lado proveedor + retenciones coincide exacto con la DIAN, pero las líneas de gasto/IVA no están completas en el Journal exportado (el archivo se corta en la fila 16.383); no se puede confirmar la suma de conceptos. | L2: — | M2: INFORMACIÓN INSUFICIENTE | N2: DIAN | O2: 001-DSE-00001703 | P2: 7510, 8236, 9198 | Q2: número del comprobante | R2: No (gasto/IVA cortado en la exportación)
A3: ADOCCIDENTE S.A.S. | B3: 805010086 | C3: FE1043 | D3: 23359501 OTROS; 23652507 SERVICIOS GENERALES (DECLARANTES) 4%; 23653002 BIENES INMUEBLES 3,5%; 24081513 IVA TRANSITORIO SERVICIOS 19% | E3: 17074120 | F3: 17074120 | G3: =IF(AND(ISNUMBER(E3),ISNUMBER(F3)),E3-F3,"No disponible") -> 0 | H3: IVA: 2,726,120.00 | Retenciones (crédito): 523,680.00 | Gasto/otros: No disponible (líneas fuera del archivo exportado) | I3: Aprobado con notificación (Factura electrónica, Recibido) | J3: Presente en el auxiliar (el archivo no trae columna de estado; se infiere Contabilizado) | K3: El lado proveedor + retenciones coincide exacto con la DIAN, pero las líneas de gasto/IVA no están completas en el Journal exportado (el archivo se corta en la fila 16.383); no se puede confirmar la suma de conceptos. | L3: — | M3: INFORMACIÓN INSUFICIENTE | N3: DIAN | O3: 001-FSC-00011343 | P3: 7642, 8252, 8326, 11263 | Q3: referencia | R3: No (gasto/IVA cortado en la exportación)
A4: AEROVIAS DE INTEGRACION REGIONAL S.A. | B4: 890704196 | C4: A3933 | D4: 23354501 TRANSPORTES, FLETES Y ACARREOS | E4: 939272 | F4: 939272 | G4: =IF(AND(ISNUMBER(E4),ISNUMBER(F4)),E4-F4,"No disponible") -> 0 | H4: Retenciones (crédito): 0.00 | Gasto/otros: No disponible (líneas fuera del archivo exportado) | I4: Aprobado con notificación (Nota de crédito electrónica, Recibido) | J4: Presente en el auxiliar (el archivo no trae columna de estado; se infiere Contabilizado) | K4: El lado proveedor + retenciones coincide exacto con la DIAN, pero las líneas de gasto/IVA no están completas en el Journal exportado (el archivo se corta en la fila 16.383); no se puede confirmar la suma de conceptos. | L4: La descripción del comprobante menciona ANULACIÓN: confirmar que no esté anulado. | M4: INFORMACIÓN INSUFICIENTE | N4: DIAN | O4: 001-NT-00012697 | P4: 7357 | Q4: texto/descripción | R4: No (gasto/IVA cortado en la exportación)
A5: AEROVIAS DE INTEGRACION REGIONAL S.A. | B5: 890704196 | C5: SPC44755 | D5: 23354501 TRANSPORTES, FLETES Y ACARREOS | E5: 13701380 | F5: 13701380 | G5: =IF(AND(ISNUMBER(E5),ISNUMBER(F5)),E5-F5,"No disponible") -> 0 | H5: Retenciones (crédito): 0.00 | Gasto/otros: No disponible (líneas fuera del archivo exportado) | I5: Aprobado con notificación (Factura electrónica, Recibido) | J5: Presente en el auxiliar (el archivo no trae columna de estado; se infiere Contabilizado) | K5: El lado proveedor + retenciones coincide exacto con la DIAN, pero las líneas de gasto/IVA no están completas en el Journal exportado (el archivo se corta en la fila 16.383); no se puede confirmar la suma de conceptos. | L5: — | M5: INFORMACIÓN INSUFICIENTE | N5: DIAN | O5: 001-FSC-00011436 | P5: 7353 | Q5: referencia | R5: No (gasto/IVA cortado en la exportación)
A6: AEROVIAS DE INTEGRACION REGIONAL S.A. | B6: 890704196 | C6: SPC45219 | D6: 23354501 TRANSPORTES, FLETES Y ACARREOS | E6: 4535050 | F6: 4535050 | G6: =IF(AND(ISNUMBER(E6),ISNUMBER(F6)),E6-F6,"No disponible") -> 0 | H6: Retenciones (crédito): 0.00 | Gasto/otros: No disponible (líneas fuera del archivo exportado) | I6: Aprobado con notificación (Factura electrónica, Recibido) | J6: Presente en el auxiliar (el archivo no trae columna de estado; se infiere Contabilizado) | K6: El lado proveedor + retenciones coincide exacto con la DIAN, pero las líneas de gasto/IVA no están completas en el Journal exportado (el archivo se corta en la fila 16.383); no se puede confirmar la suma de conceptos. | L6: — | M6: INFORMACIÓN INSUFICIENTE | N6: DIAN | O6: 001-FSC-00011580 | P6: 7356 | Q6: referencia | R6: No (gasto/IVA cortado en la exportación)
A7: AEROVIAS DE INTEGRACIÓN REGIONAL S.A. | B7: 890704196 | C7: EFCC4800912 | D7: 23354501 TRANSPORTES, FLETES Y ACARREOS; 24081513 IVA TRANSITORIO SERVICIOS 19% | E7: 3317339 | F7: 3317399 | G7: =IF(AND(ISNUMBER(E7),ISNUMBER(F7)),E7-F7,"No disponible") -> -60 | H7: IVA: 521,750.00 | Retenciones (crédito): 0.00 | Gasto/otros: No disponible (líneas fuera del archivo exportado) | I7: Aprobado con notificación (Documento equivalente - Transporte aéreo de pasajeros, Recibido) | J7: Presente en el auxiliar (el archivo no trae columna de estado; se infiere Contabilizado) | K7: El lado proveedor + retenciones del Journal no coincide con el total de la DIAN. | L7: — | M7: PENDIENTE | N7: DIAN | O7: 001-FSC-00011488 | P7: 7354, 11339 | Q7: referencia | R7: No (gasto/IVA cortado en la exportación)
A8: AEROVIAS DE INTEGRACIÓN REGIONAL S.A. | B8: 890704196 | C8: EFCC4858340 | D8: No disponible | E8: 417940 | F8: No encontrado | G8: =IF(AND(ISNUMBER(E8),ISNUMBER(F8)),E8-F8,"No disponible") -> No disponible | H8: No disponible | I8: Aprobado con notificación (Documento equivalente - Transporte aéreo de pasajeros, Recibido) | J8: No encontrado | K8: No se encontró el documento en el Journal (el tercero sí tiene otros movimientos). | L8: El tercero aparece en el Journal pero ninguna línea cita este folio ni coincide su valor. | M8: PENDIENTE | N8: DIAN | O8: No encontrado | Q8: No encontrado | R8: No disponible
A9: AEROVIAS DEL CONTINENTE AMERICANO, S.A. AVIANCA - COLOMBIA | B9: 890100577 | C9: TQT26949290 | D9: 23359501 OTROS; 24081513 IVA TRANSITORIO SERVICIOS 19% | E9: 553160 | F9: 553160 | G9: =IF(AND(ISNUMBER(E9),ISNUMBER(F9)),E9-F9,"No disponible") -> 0 | H9: IVA: 84,360.00 | Retenciones (crédito): 0.00 | Gasto/otros: No disponible (líneas fuera del archivo exportado) | I9: Aprobado con notificación (Factura electrónica, Recibido) | J9: Presente en el auxiliar (el archivo no trae columna de estado; se infiere Contabilizado) | K9: El lado proveedor + retenciones coincide exacto con la DIAN, pero las líneas de gasto/IVA no están completas en el Journal exportado (el archivo se corta en la fila 16.383); no se puede confirmar la suma de conceptos. | L9: — | M9: INFORMACIÓN INSUFICIENTE | N9: DIAN | O9: 001-FSC-00011450 | P9: 7747, 11304 | Q9: referencia | R9: No (gasto/IVA cortado en la exportación)
A10: AGENCIA DE ADUANAS SANTIAGO RICO & BAÑOL LTDA. NIVEL 4 | B10: 827000059 | C10: SRFE804 | D10: 23359501 OTROS; 23652507 SERVICIOS GENERALES (DECLARANTES) 4% | E10: 450000 | F10: 450000 | G10: =IF(AND(ISNUMBER(E10),ISNUMBER(F10)),E10-F10,"No disponible") -> 0 | H10: Retenciones (crédito): 18,000.00 | Gasto/otros: No disponible (líneas fuera del archivo exportado) | I10: Aprobado con notificación (Factura electrónica, Recibido) | J10: Presente en el auxiliar (el archivo no trae columna de estado; se infiere Contabilizado) | K10: El lado proveedor + retenciones coincide exacto con la DIAN, pero las líneas de gasto/IVA no están completas en el Journal exportado (el archivo se corta en la fila 16.383); no se puede confirmar la suma de conceptos. | L10: — | M10: INFORMACIÓN INSUFICIENTE | N10: DIAN | O10: 001-FSC-00011385 | P10: 7680, 8256 | Q10: referencia | R10: No (gasto/IVA cortado en la exportación)
A11: AGENCIA DE ADUANAS SANTIAGO RICO & BAÑOL LTDA. NIVEL 4 | B11: 827000059 | C11: SRFE813 | D11: 23359501 OTROS; 23652507 SERVICIOS GENERALES (DECLARANTES) 4%; 26952001 PARA OPERACION | E11: 3150000 | F11: 3150000 | G11: =IF(AND(ISNUMBER(E11),ISNUMBER(F11)),E11-F11,"No disponible") -> 0 | H11: Otros conceptos: 3,150,000.00 | Retenciones (crédito): 126,000.00 | I11: Aprobado con notificación (Factura electrónica, Recibido) | J11: Presente en el auxiliar (el archivo no trae columna de estado; se infiere Contabilizado) | K11: Coincide exacto (débitos = créditos = DIAN). | L11: — | M11: VERIFICADO | N11: DIAN | O11: 001-CC-00023130 | P11: 7682, 8257, 12537 | Q11: referencia | R11: Sí
A12: AGENCIA DE ADUANAS SANTIAGO RICO & BAÑOL LTDA. NIVEL 4 | B12: 827000059 | C12: SRFE817 | D12: 23359501 OTROS; 23652507 SERVICIOS GENERALES (DECLARANTES) 4%; 26952001 PARA OPERACION | E12: 450000 | F12: 449999 | G12: =IF(AND(ISNUMBER(E12),ISNUMBER(F12)),E12-F12,"No disponible") -> 1 | H12: Otros conceptos: 449,999.00 | Retenciones (crédito): 18,000.00 | I12: Aprobado con notificación (Factura electrónica, Recibido) | J12: Presente en el auxiliar (el archivo no trae columna de estado; se infiere Contabilizado) | K12: La suma de los conceptos contables no coincide con el total de la DIAN. | L12: — | M12: PENDIENTE | N12: DIAN | O12: 001-CC-00023131 | P12: 7683, 8258, 12538 | Q12: referencia | R12: Sí
A13: ALMACEN LAS GEMELAS SAS | B13: 901849101 | C13: FE2169 | D13: 23359501 OTROS; 23654002 COMPRAS GENERALES 2,5%; 24081510 IVA TRANSITORIO COMPRAS 19% | E13: 792000.02 | F13: 792000 | G13: =IF(AND(ISNUMBER(E13),ISNUMBER(F13)),E13-F13,"No disponible") -> 0.02 | H13: IVA: 126,454.00 | Retenciones (crédito): 16,639.00 | Gasto/otros: No disponible (líneas fuera del archivo exportado) | I13: Aprobado con notificación (Factura electrónica, Recibido) | J13: Presente en el auxiliar (el archivo no trae columna de estado; se infiere Contabilizado) | K13: El lado proveedor + retenciones del Journal no coincide con el total de la DIAN. | L13: — | M13: PENDIENTE | N13: DIAN | O13: 001-FSC-00011456 | P13: 8028, 8415, 11207 | Q13: referencia | R13: No (gasto/IVA cortado en la exportación)
A14: ALMACENES ÉXITO S.A | B14: 890900608 | C14: RC06172758 | D14: 23359501 OTROS | E14: 37080 | F14: 37080 | G14: =IF(AND(ISNUMBER(E14),ISNUMBER(F14)),E14-F14,"No disponible") -> 0 | H14: Retenciones (crédito): 0.00 | Gasto/otros: No disponible (líneas fuera del archivo exportado) | I14: Aprobado con notificación (Factura electrónica, Recibido) | J14: Presente en el auxiliar (el archivo no trae columna de estado; se infiere Contabilizado) | K14: El lado proveedor + retenciones coincide exacto con la DIAN, pero las líneas de gasto/IVA no están completas en el Journal exportado (el archivo se corta en la fila 16.383); no se puede confirmar la suma de conceptos. | L14: — | M14: INFORMACIÓN INSUFICIENTE | N14: DIAN | O14: 001-FSC-00011592 | P14: 7822 | Q14: referencia | R14: No (gasto/IVA cortado en la exportación)
A15: ALMAZONE SAS | B15: 901881638 | C15: ALZ2401 | D15: 22050501 PROVEEDORES NACIONALES; 23652501 TRANSPORTE 1%; 26959501 OTRAS | E15: 1850000 | F15: 1850000 | G15: =IF(AND(ISNUMBER(E15),ISNUMBER(F15)),E15-F15,"No disponible") -> 0 | H15: Otros conceptos: 1,850,000.00 | Retenciones (crédito): 18,500.00 | I15: Aprobado con notificación (Factura electrónica, Recibido) | J15: Presente en el auxiliar (el archivo no trae columna de estado; se infiere Contabilizado) | K15: Coincide exacto (débitos = créditos = DIAN). | L15: — | M15: VERIFICADO | N15: DIAN | O15: 001-FPI-00000500 | P15: 7247, 8197, 12632 | Q15: referencia | R15: Sí
A16: ALMEIDA BACCA EDWARD ALEXANDER | B16: 16928075 | C16: FE681 | D16: No disponible | E16: 601985.3 | F16: No encontrado | G16: =IF(AND(ISNUMBER(E16),ISNUMBER(F16)),E16-F16,"No disponible") -> No disponible | H16: No disponible | I16: Aprobado con notificación (Factura electrónica, Recibido) | J16: No encontrado | K16: El tercero no aparece en el Journal. | L16: NIT sin movimientos en el archivo del Journal. | M16: PENDIENTE | N16: DIAN | O16: No encontrado | Q16: No encontrado | R16: No disponible
A17: ANILLANDO CALI LTDA | B17: 800038947 | C17: PFS10547 | D17: 22050501 PROVEEDORES NACIONALES; 24081510 IVA TRANSITORIO COMPRAS 19% | E17: 138900 | F17: 138900 | G17: =IF(AND(ISNUMBER(E17),ISNUMBER(F17)),E17-F17,"No disponible") -> 0 | H17: IVA: 22,177.00 | Retenciones (crédito): 0.00 | Gasto/otros: No disponible (líneas fuera del archivo exportado) | I17: Aprobado con notificación (Factura electrónica, Recibido) | J17: Presente en el auxiliar (el archivo no trae columna de estado; se infiere Contabilizado) | K17: El lado proveedor + retenciones coincide exacto con la DIAN, pero las líneas de gasto/IVA no están completas en el Journal exportado (el archivo se corta en la fila 16.383); no se puede confirmar la suma de conceptos. | L17: — | M17: INFORMACIÓN INSUFICIENTE | N17: DIAN | O17: 001-FSC-00011410 | P17: 7203, 11063 | Q17: referencia | R17: No (gasto/IVA cortado en la exportación)
A18: APONTE CASTILLO CARLOS DANIEL | B18: 1010204688 | C18: 422 | D18: 13309501 OTROS; 23359501 OTROS; 23654002 COMPRAS GENERALES 2,5%; 24081510 IVA TRANSITORIO COMPRAS 19% | E18: 6961500 | F18: 3553875 | G18: =IF(AND(ISNUMBER(E18),ISNUMBER(F18)),E18-F18,"No disponible") -> 3407625 | H18: IVA: 1,111,500.00 | Otros conceptos: -3,407,625.00 | Retenciones (crédito): 146,250.00 | Gasto/otros: No disponible (líneas fuera del archivo exportado) | I18: Aprobado con notificación (Factura electrónica, Recibido) | J18: Presente en el auxiliar (el archivo no trae columna de estado; se infiere Contabilizado) | K18: El lado proveedor + retenciones del Journal no coincide con el total de la DIAN. | L18: — | M18: PENDIENTE | N18: DIAN | O18: 001-FSC-00011398 | P18: 3306, 7373, 7374, 8332, 11047 | Q18: referencia | R18: No (gasto/IVA cortado en la exportación)
A19: AQUASISTEMAS DEL CARIBE S.A.S | B19: 802018827 | C19: FE232 | D19: 23359501 OTROS; 23654002 COMPRAS GENERALES 2,5% | E19: 561300 | F19: 561300 | G19: =IF(AND(ISNUMBER(E19),ISNUMBER(F19)),E19-F19,"No disponible") -> 0 | H19: Retenciones (crédito): 14,033.00 | Gasto/otros: No disponible (líneas fuera del archivo exportado) | I19: Aprobado con notificación (Factura electrónica, Recibido) | J19: Presente en el auxiliar (el archivo no trae columna de estado; se infiere Contabilizado) | K19: El lado proveedor + retenciones coincide exacto con la DIAN, pero las líneas de gasto/IVA no están completas en el Journal exportado (el archivo se corta en la fila 16.383); no se puede confirmar la suma de conceptos. | L19: — | M19: INFORMACIÓN INSUFICIENTE | N19: DIAN | O19: 001-FSC-00011582 | P19: 7637, 8367 | Q19: referencia | R19: No (gasto/IVA cortado en la exportación)
A20: ARIAS GLORIA PATRICIA | B20: 31411095 | C20: NDSE1700 | D20: 23359501 OTROS; 23654002 COMPRAS GENERALES 2,5%; 23680302 DEMAS ACTIVIDADES COMERCIALES 7,7 X 1000 | E20: 1620000 | F20: 1620000 | G20: =IF(AND(ISNUMBER(E20),ISNUMBER(F20)),E20-F20,"No disponible") -> 0 | H20: Retenciones (crédito): 52,974.00 | Gasto/otros: No disponible (líneas fuera del archivo exportado) | I20: Aprobado con notificación (Documento soporte con no obligados, Emitido) | J20: Presente en el auxiliar (el archivo no trae columna de estado; se infiere Contabilizado) | K20: El lado proveedor + retenciones coincide exacto con la DIAN, pero las líneas de gasto/IVA no están completas en el Journal exportado (el archivo se corta en la fila 16.383); no se puede confirmar la suma de conceptos. | L20: — | M20: INFORMACIÓN INSUFICIENTE | N20: DIAN | O20: 001-DSE-00001700 | P20: 7458, 8344, 9261 | Q20: referencia | R20: No (gasto/IVA cortado en la exportación)
A21: ARIAS GLORIA PATRICIA | B21: 31411095 | C21: NDSE1708 | D21: 23359501 OTROS; 23654002 COMPRAS GENERALES 2,5%; 23680203 DEMAS ACTIVIDADES SERVICIOS 10 X 1000 | E21: 3000000 | F21: 3000000 | G21: =IF(AND(ISNUMBER(E21),ISNUMBER(F21)),E21-F21,"No disponible") -> 0 | H21: Retenciones (crédito): 105,000.00 | Gasto/otros: No disponible (líneas fuera del archivo exportado) | I21: Aprobado con notificación (Documento soporte con no obligados, Emitido) | J21: Presente en el auxiliar (el archivo no trae columna de estado; se infiere Contabilizado) | K21: El lado proveedor + retenciones coincide exacto con la DIAN, pero las líneas de gasto/IVA no están completas en el Journal exportado (el archivo se corta en la fila 16.383); no se puede confirmar la suma de conceptos. | L21: — | M21: INFORMACIÓN INSUFICIENTE | N21: DIAN | O21: 001-DSE-00001708 | P21: 7460, 7461, 8345, 9195 | Q21: referencia | R21: No (gasto/IVA cortado en la exportación)
A22: ARIAS GLORIA PATRICIA | B22: 31411095 | C22: NDSE1734 | D22: 23359501 OTROS; 23652507 SERVICIOS GENERALES (DECLARANTES) 4%; 23680203 DEMAS ACTIVIDADES SERVICIOS 10 X 1000; 51055101 DOTACION Y SUMINISTRO A TRABAJADORES | E22: 636500 | F22: 636500 | G22: =IF(AND(ISNUMBER(E22),ISNUMBER(F22)),E22-F22,"No disponible") -> 0 | H22: Gastos: 38,000.00 | Retenciones (crédito): 31,825.00 | Gasto/otros: No disponible (líneas fuera del archivo exportado) | I22: Aprobado con notificación (Documento soporte con no obligados, Emitido) | J22: Presente en el auxiliar (el archivo no trae columna de estado; se infiere Contabilizado) | K22: El lado proveedor + retenciones coincide exacto con la DIAN, pero las líneas de gasto/IVA no están completas en el Journal exportado (el archivo se corta en la fila 16.383); no se puede confirmar la suma de conceptos. | L22: — | M22: INFORMACIÓN INSUFICIENTE | N22: DIAN | O22: 001-DSE-00001734 | P22: 7464, 8234, 9196, 16105 | Q22: referencia | R22: No (gasto/IVA cortado en la exportación)
A23: ASESORIAS REPRESENTACIONES ADMINISTRACION Y SERVICIOS ARAS SAS. | B23: 860506531 | C23: MCBU162585 | D23: 23359501 OTROS; 26959501 OTRAS | E23: 275000 | F23: 275000 | G23: =IF(AND(ISNUMBER(E23),ISNUMBER(F23)),E23-F23,"No disponible") -> 0 | H23: Otros conceptos: 275,000.00 | Retenciones (crédito): 0.00 | I23: Aprobado con notificación (Factura electrónica, Recibido) | J23: Presente en el auxiliar (el archivo no trae columna de estado; se infiere Contabilizado) | K23: Coincide exacto (débitos = créditos = DIAN). | L23: — | M23: VERIFICADO | N23: DIAN | O23: 001-FPI-00000496 | P23: 7740, 12625 | Q23: referencia | R23: Sí
A24: AZUL RESTAURANT AIRPORT | B24: 79308344 | C24: PAZ6314 | D24: 23359501 OTROS | E24: 24000 | F24: 24000 | G24: =IF(AND(ISNUMBER(E24),ISNUMBER(F24)),E24-F24,"No disponible") -> 0 | H24: Retenciones (crédito): 0.00 | Gasto/otros: No disponible (líneas fuera del archivo exportado) | I24: Aprobado con notificación (Factura electrónica, Recibido) | J24: Presente en el auxiliar (el archivo no trae columna de estado; se infiere Contabilizado) | K24: Coincide el NIT y el valor exacto, pero ninguna línea del Journal cita el número del documento; no se puede identificar con certeza. | L24: — | M24: INFORMACIÓN INSUFICIENTE | N24: DIAN | O24: 001-FSC-00011438 | P24: 7540 | Q24: NIT + valor (sin folio) | R24: No (gasto/IVA cortado en la exportación)
A25: AZUL RESTAURANT AIRPORT | B25: 79308344 | C25: PAZ6315 | D25: 23359501 OTROS | E25: 26000 | F25: 26000 | G25: =IF(AND(ISNUMBER(E25),ISNUMBER(F25)),E25-F25,"No disponible") -> 0 | H25: Retenciones (crédito): 0.00 | Gasto/otros: No disponible (líneas fuera del archivo exportado) | I25: Aprobado con notificación (Factura electrónica, Recibido) | J25: Presente en el auxiliar (el archivo no trae columna de estado; se infiere Contabilizado) | K25: El lado proveedor + retenciones coincide exacto con la DIAN, pero las líneas de gasto/IVA no están completas en el Journal exportado (el archivo se corta en la fila 16.383); no se puede confirmar la suma de conceptos. | L25: — | M25: INFORMACIÓN INSUFICIENTE | N25: DIAN | O25: 001-FSC-00011482 | P25: 7545 | Q25: referencia | R25: No (gasto/IVA cortado en la exportación)
A26: AZUL RESTAURANT AIRPORT | B26: 79308344 | C26: PAZ6316 | D26: No disponible | E26: 10000 | F26: No encontrado | G26: =IF(AND(ISNUMBER(E26),ISNUMBER(F26)),E26-F26,"No disponible") -> No disponible | H26: No disponible | I26: Aprobado con notificación (Factura electrónica, Recibido) | J26: No encontrado | K26: No se encontró el documento en el Journal (el tercero sí tiene otros movimientos). | L26: El tercero aparece en el Journal pero ninguna línea cita este folio ni coincide su valor. | M26: PENDIENTE | N26: DIAN | O26: No encontrado | Q26: No encontrado | R26: No disponible
A27: BAL STUDIO SAS | B27: 901986829 | C27: FE2458 | D27: 22050501 PROVEEDORES NACIONALES; 23670501 IVA RET. COMPRAS RC 15%; 24081513 IVA TRANSITORIO SERVICIOS 19% | E27: 2023000 | F27: 2023000 | G27: =IF(AND(ISNUMBER(E27),ISNUMBER(F27)),E27-F27,"No disponible") -> 0 | H27: IVA: 323,000.00 | Retenciones (crédito): 48,450.00 | Gasto/otros: No disponible (líneas fuera del archivo exportado) | I27: Aprobado con notificación (Factura electrónica, Recibido) | J27: Presente en el auxiliar (el archivo no trae columna de estado; se infiere Contabilizado) | K27: El lado proveedor + retenciones coincide exacto con la DIAN, pero las líneas de gasto/IVA no están completas en el Journal exportado (el archivo se corta en la fila 16.383); no se puede confirmar la suma de conceptos. | L27: — | M27: INFORMACIÓN INSUFICIENTE | N27: DIAN | O27: 001-FSC-00011483 | P27: 7250, 9156, 11501 | Q27: referencia | R27: No (gasto/IVA cortado en la exportación)
A28: BBVA SEGUROS COLOMBIA S.A. | B28: 800226098 | C28: FEAG1134986 | D28: 23359501 OTROS; 24081513 IVA TRANSITORIO SERVICIOS 19% | E28: 178364 | F28: 178364 | G28: =IF(AND(ISNUMBER(E28),ISNUMBER(F28)),E28-F28,"No disponible") -> 0 | H28: IVA: 28,478.00 | Retenciones (crédito): 0.00 | Gasto/otros: No disponible (líneas fuera del archivo exportado) | I28: Aprobado con notificación (Factura electrónica, Recibido) | J28: Presente en el auxiliar (el archivo no trae columna de estado; se infiere Contabilizado) | K28: El lado proveedor + retenciones coincide exacto con la DIAN, pero las líneas de gasto/IVA no están completas en el Journal exportado (el archivo se corta en la fila 16.383); no se puede confirmar la suma de conceptos. | L28: — | M28: INFORMACIÓN INSUFICIENTE | N28: DIAN | O28: 001-FSC-00011380 | P28: 7588, 11253 | Q28: referencia | R28: No (gasto/IVA cortado en la exportación)
A29: BENEMERITO CUERPO DE BOMBEROS VOLUNTARIOS DE CALI | B29: 890399000 | C29: FK72753 | D29: 23359501 OTROS; 24081513 IVA TRANSITORIO SERVICIOS 19% | E29: 942994 | F29: 942994 | G29: =IF(AND(ISNUMBER(E29),ISNUMBER(F29)),E29-F29,"No disponible") -> 0 | H29: IVA: 150,562.00 | Retenciones (crédito): 0.00 | Gasto/otros: No disponible (líneas fuera del archivo exportado) | I29: Aprobado con notificación (Factura electrónica, Recibido) | J29: Presente en el auxiliar (el archivo no trae columna de estado; se infiere Contabilizado) | K29: El lado proveedor + retenciones coincide exacto con la DIAN, pero las líneas de gasto/IVA no están completas en el Journal exportado (el archivo se corta en la fila 16.383); no se puede confirmar la suma de conceptos. | L29: — | M29: INFORMACIÓN INSUFICIENTE | N29: DIAN | O29: 001-FSC-00011563 | P29: 7799, 11332 | Q29: referencia | R29: No (gasto/IVA cortado en la exportación)
A30: BERMUDEZ RAMIREZ EUCARIO | B30: 16752920 | C30: NDSE1709 | D30: 22050501 PROVEEDORES NACIONALES; 23654002 COMPRAS GENERALES 2,5%; 23680302 DEMAS ACTIVIDADES COMERCIALES 7,7 X 1000 | E30: 11480000 | F30: 11480000 | G30: =IF(AND(ISNUMBER(E30),ISNUMBER(F30)),E30-F30,"No disponible") -> 0 | H30: Retenciones (crédito): 375,396.00 | Gasto/otros: No disponible (líneas fuera del archivo exportado) | I30: Aprobado con notificación (Documento soporte con no obligados, Emitido) | J30: Presente en el auxiliar (el archivo no trae columna de estado; se infiere Contabilizado) | K30: El lado proveedor + retenciones coincide exacto con la DIAN, pero las líneas de gasto/IVA no están completas en el Journal exportado (el archivo se corta en la fila 16.383); no se puede confirmar la suma de conceptos. | L30: — | M30: INFORMACIÓN INSUFICIENTE | N30: DIAN | O30: 001-DSE-00001709 | P30: 7195, 8335, 9255 | Q30: referencia | R30: No (gasto/IVA cortado en la exportación)
A31: BERNARDA VALENCIA MOYA | B31: 29951774 | C31: FEBV2769 | D31: 23359502 CUENTA PUENTE CAJA MENOR | E31: 20000 | F31: 20000 | G31: =IF(AND(ISNUMBER(E31),ISNUMBER(F31)),E31-F31,"No disponible") -> 0 | H31: Retenciones (crédito): 0.00 | Gasto/otros: No disponible (líneas fuera del archivo exportado) | I31: Aprobado con notificación (Factura electrónica, Recibido) | J31: Presente en el auxiliar (el archivo no trae columna de estado; se infiere Contabilizado) | K31: El lado proveedor + retenciones coincide exacto con la DIAN, pero las líneas de gasto/IVA no están completas en el Journal exportado (el archivo se corta en la fila 16.383); no se puede confirmar la suma de conceptos. | L31: — | M31: INFORMACIÓN INSUFICIENTE | N31: DIAN | O31: 001-FSC-00011557 | P31: 8084 | Q31: referencia | R31: No (gasto/IVA cortado en la exportación)
A32: BERRIO ARIAS JUAN FERNANDO | B32: 7563061 | C32: NDSE1733 | D32: 23359501 OTROS; 23652507 SERVICIOS GENERALES (DECLARANTES) 4% | E32: 145000 | F32: 145000 | G32: =IF(AND(ISNUMBER(E32),ISNUMBER(F32)),E32-F32,"No disponible") -> 0 | H32: Retenciones (crédito): 5,800.00 | Gasto/otros: No disponible (líneas fuera del archivo exportado) | I32: Aprobado con notificación (Documento soporte con no obligados, Emitido) | J32: Presente en el auxiliar (el archivo no trae columna de estado; se infiere Contabilizado) | K32: El lado proveedor + retenciones coincide exacto con la DIAN, pero las líneas de gasto/IVA no están completas en el Journal exportado (el archivo se corta en la fila 16.383); no se puede confirmar la suma de conceptos. | L32: — | M32: INFORMACIÓN INSUFICIENTE | N32: DIAN | O32: 001-DSE-00001733 | P32: 7538, 8238 | Q32: número del comprobante | R32: No (gasto/IVA cortado en la exportación)
A33: BOLD.CO S.A.S | B33: 901281572 | C33: FEC8613219 | D33: No disponible | E33: 137076.57 | F33: No encontrado | G33: =IF(AND(ISNUMBER(E33),ISNUMBER(F33)),E33-F33,"No disponible") -> No disponible | H33: No disponible | I33: Aprobado con notificación (Factura electrónica, Recibido) | J33: No encontrado | K33: No se encontró el documento en el Journal (el tercero sí tiene otros movimientos). | L33: El tercero aparece en el Journal pero ninguna línea cita este folio ni coincide su valor. | M33: PENDIENTE | N33: DIAN | O33: No encontrado | Q33: No encontrado | R33: No disponible
A34: BUENO ALVAREZ WILLIAM ANDRES | B34: 1113519268 | C34: NDSE1704 | D34: 23359501 OTROS | E34: 1730560 | F34: 1730560 | G34: =IF(AND(ISNUMBER(E34),ISNUMBER(F34)),E34-F34,"No disponible") -> 0 | H34: Retenciones (crédito): 0.00 | Gasto/otros: No disponible (líneas fuera del archivo exportado) | I34: Aprobado con notificación (Documento soporte con no obligados, Emitido) | J34: Presente en el auxiliar (el archivo no trae columna de estado; se infiere Contabilizado) | K34: El lado proveedor + retenciones coincide exacto con la DIAN, pero las líneas de gasto/IVA no están completas en el Journal exportado (el archivo se corta en la fila 16.383); no se puede confirmar la suma de conceptos. | L34: — | M34: INFORMACIÓN INSUFICIENTE | N34: DIAN | O34: 001-DSE-00001704 | P34: 7387 | Q34: referencia | R34: No (gasto/IVA cortado en la exportación)
A35: BUENO ALVAREZ WILLIAM ANDRES | B35: 1113519268 | C35: NDSE1705 | D35: 23359501 OTROS | E35: 1732000 | F35: 1732000 | G35: =IF(AND(ISNUMBER(E35),ISNUMBER(F35)),E35-F35,"No disponible") -> 0 | H35: Retenciones (crédito): 0.00 | Gasto/otros: No disponible (líneas fuera del archivo exportado) | I35: Aprobado con notificación (Documento soporte con no obligados, Emitido) | J35: Presente en el auxiliar (el archivo no trae columna de estado; se infiere Contabilizado) | K35: El lado proveedor + retenciones coincide exacto con la DIAN, pero las líneas de gasto/IVA no están completas en el Journal exportado (el archivo se corta en la fila 16.383); no se puede confirmar la suma de conceptos. | L35: — | M35: INFORMACIÓN INSUFICIENTE | N35: DIAN | O35: 001-DSE-00001705 | P35: 7388 | Q35: referencia | R35: No (gasto/IVA cortado en la exportación)
A36: CABRALES SALGADO ROLANDO ALBERTO | B36: 73571583 | C36: NDSE1724 | D36: 23359501 OTROS | E36: 79000 | F36: 79000 | G36: =IF(AND(ISNUMBER(E36),ISNUMBER(F36)),E36-F36,"No disponible") -> 0 | H36: Retenciones (crédito): 0.00 | Gasto/otros: No disponible (líneas fuera del archivo exportado) | I36: Aprobado con notificación (Documento soporte con no obligados, Emitido) | J36: Presente en el auxiliar (el archivo no trae columna de estado; se infiere Contabilizado) | K36: El lado proveedor + retenciones coincide exacto con la DIAN, pero las líneas de gasto/IVA no están completas en el Journal exportado (el archivo se corta en la fila 16.383); no se puede confirmar la suma de conceptos. | L36: — | M36: INFORMACIÓN INSUFICIENTE | N36: DIAN | O36: 001-DSE-00001724 | P36: 7530 | Q36: referencia | R36: No (gasto/IVA cortado en la exportación)
A37: CABRALES SALGADO ROLANDO ALBERTO | B37: 73571583 | C37: NDSE1725 | D37: 23359501 OTROS | E37: 119000 | F37: 119000 | G37: =IF(AND(ISNUMBER(E37),ISNUMBER(F37)),E37-F37,"No disponible") -> 0 | H37: Retenciones (crédito): 0.00 | Gasto/otros: No disponible (líneas fuera del archivo exportado) | I37: Aprobado con notificación (Documento soporte con no obligados, Emitido) | J37: Presente en el auxiliar (el archivo no trae columna de estado; se infiere Contabilizado) | K37: El lado proveedor + retenciones coincide exacto con la DIAN, pero las líneas de gasto/IVA no están completas en el Journal exportado (el archivo se corta en la fila 16.383); no se puede confirmar la suma de conceptos. | L37: — | M37: INFORMACIÓN INSUFICIENTE | N37: DIAN | O37: 001-DSE-00001725 | P37: 7531 | Q37: referencia | R37: No (gasto/IVA cortado en la exportación)
A38: CABRALES SALGADO ROLANDO ALBERTO | B38: 73571583 | C38: NDSE1729 | D38: 23359501 OTROS | E38: 316000 | F38: 316000 | G38: =IF(AND(ISNUMBER(E38),ISNUMBER(F38)),E38-F38,"No disponible") -> 0 | H38: Retenciones (crédito): 0.00 | Gasto/otros: No disponible (líneas fuera del archivo exportado) | I38: Aprobado con notificación (Documento soporte con no obligados, Emitido) | J38: Presente en el auxiliar (el archivo no trae columna de estado; se infiere Contabilizado) | K38: El lado proveedor + retenciones coincide exacto con la DIAN, pero las líneas de gasto/IVA no están completas en el Journal exportado (el archivo se corta en la fila 16.383); no se puede confirmar la suma de conceptos. | L38: — | M38: INFORMACIÓN INSUFICIENTE | N38: DIAN | O38: 001-DSE-00001729 | P38: 7532 | Q38: referencia | R38: No (gasto/IVA cortado en la exportación)
A39: CALVACHE JARAMILLO LUIS MIGUEL | B39: 1144093853 | C39: NDSE1715 | D39: 23359501 OTROS | E39: 2400 | F39: 2400 | G39: =IF(AND(ISNUMBER(E39),ISNUMBER(F39)),E39-F39,"No disponible") -> 0 | H39: Retenciones (crédito): 0.00 | Gasto/otros: No disponible (líneas fuera del archivo exportado) | I39: Aprobado con notificación (Documento soporte con no obligados, Emitido) | J39: Presente en el auxiliar (el archivo no trae columna de estado; se infiere Contabilizado) | K39: El lado proveedor + retenciones coincide exacto con la DIAN, pero las líneas de gasto/IVA no están completas en el Journal exportado (el archivo se corta en la fila 16.383); no se puede confirmar la suma de conceptos. | L39: — | M39: INFORMACIÓN INSUFICIENTE | N39: DIAN | O39: 001-DSE-00001715 | P39: 7401 | Q39: número del comprobante | R39: No (gasto/IVA cortado en la exportación)
A40: CARTONES AMERICA S.A. CAME | B40: 860026759 | C40: 8200455422 | D40: 23359501 OTROS; 24081510 IVA TRANSITORIO COMPRAS 19% | E40: 6999152 | F40: 6999152 | G40: =IF(AND(ISNUMBER(E40),ISNUMBER(F40)),E40-F40,"No disponible") -> 0 | H40: IVA: 1,117,512.00 | Retenciones (crédito): 0.00 | Gasto/otros: No disponible (líneas fuera del archivo exportado) | I40: Aprobado con notificación (Factura electrónica, Recibido) | J40: Presente en el auxiliar (el archivo no trae columna de estado; se infiere Contabilizado) | K40: El lado proveedor + retenciones coincide exacto con la DIAN, pero las líneas de gasto/IVA no están completas en el Journal exportado (el archivo se corta en la fila 16.383); no se puede confirmar la suma de conceptos. | L40: — | M40: INFORMACIÓN INSUFICIENTE | N40: DIAN | O40: 001-FSC-00011382 | P40: 7729, 11114 | Q40: referencia | R40: No (gasto/IVA cortado en la exportación)
A41: CARVAJAL TECNOLOGIA Y SERVICIOS S.A.S. | B41: 890321151 | C41: CLOA105291184 | D41: 23359501 OTROS; 24081513 IVA TRANSITORIO SERVICIOS 19% | E41: 142949.94 | F41: 142950 | G41: =IF(AND(ISNUMBER(E41),ISNUMBER(F41)),E41-F41,"No disponible") -> -0.06 | H41: IVA: 22,824.00 | Retenciones (crédito): 0.00 | Gasto/otros: No disponible (líneas fuera del archivo exportado) | I41: Aprobado con notificación (Factura electrónica, Recibido) | J41: Presente en el auxiliar (el archivo no trae columna de estado; se infiere Contabilizado) | K41: El lado proveedor + retenciones del Journal no coincide con el total de la DIAN. | L41: — | M41: PENDIENTE | N41: DIAN | O41: 001-FSC-00011383 | P41: 7789, 11329 | Q41: referencia | R41: No (gasto/IVA cortado en la exportación)
A42: CASTANEDA VARGAS JULIAN | B42: 16917650 | C42: NDSE1736 | D42: 23359501 OTROS | E42: 133000 | F42: 133000 | G42: =IF(AND(ISNUMBER(E42),ISNUMBER(F42)),E42-F42,"No disponible") -> 0 | H42: Retenciones (crédito): 0.00 | Gasto/otros: No disponible (líneas fuera del archivo exportado) | I42: Aprobado con notificación (Documento soporte con no obligados, Emitido) | J42: Presente en el auxiliar (el archivo no trae columna de estado; se infiere Contabilizado) | K42: El lado proveedor + retenciones coincide exacto con la DIAN, pero las líneas de gasto/IVA no están completas en el Journal exportado (el archivo se corta en la fila 16.383); no se puede confirmar la suma de conceptos. | L42: — | M42: INFORMACIÓN INSUFICIENTE | N42: DIAN | O42: 001-DSE-00001736 | P42: 7454 | Q42: número del comprobante | R42: No (gasto/IVA cortado en la exportación)
A43: CESAR AUGUSTO GIRALDO HOYOS | B43: 16460791 | C43: FPDP7016 | D43: 23359501 OTROS; 24081510 IVA TRANSITORIO COMPRAS 19% | E43: 34000 | F43: 33999 | G43: =IF(AND(ISNUMBER(E43),ISNUMBER(F43)),E43-F43,"No disponible") -> 1 | H43: IVA: 5,428.00 | Retenciones (crédito): 0.00 | Gasto/otros: No disponible (líneas fuera del archivo exportado) | I43: Aprobado con notificación (Factura electrónica, Recibido) | J43: Presente en el auxiliar (el archivo no trae columna de estado; se infiere Contabilizado) | K43: El lado proveedor + retenciones del Journal no coincide con el total de la DIAN. | L43: — | M43: PENDIENTE | N43: DIAN | O43: 001-FSC-00011541 | P43: 7420, 11051 | Q43: referencia | R43: No (gasto/IVA cortado en la exportación)
A44: CHAVEZ ASPRILLA EDWARD ANDRES | B44: 94410977 | C44: NDSE1713 | D44: 23359501 OTROS | E44: 450000 | F44: 450000 | G44: =IF(AND(ISNUMBER(E44),ISNUMBER(F44)),E44-F44,"No disponible") -> 0 | H44: Retenciones (crédito): 0.00 | Gasto/otros: No disponible (líneas fuera del archivo exportado) | I44: Aprobado con notificación (Documento soporte con no obligados, Emitido) | J44: Presente en el auxiliar (el archivo no trae columna de estado; se infiere Contabilizado) | K44: El lado proveedor + retenciones coincide exacto con la DIAN, pero las líneas de gasto/IVA no están completas en el Journal exportado (el archivo se corta en la fila 16.383); no se puede confirmar la suma de conceptos. | L44: — | M44: INFORMACIÓN INSUFICIENTE | N44: DIAN | O44: 001-DSE-00001713 | P44: 8047 | Q44: referencia | R44: No (gasto/IVA cortado en la exportación)
A45: CHRISTIAN CAMILO QUEVEDO OCHOA | B45: 1130588761 | C45: ETPC406 | D45: No disponible | E45: 28000 | F45: No encontrado | G45: =IF(AND(ISNUMBER(E45),ISNUMBER(F45)),E45-F45,"No disponible") -> No disponible | H45: No disponible | I45: Aprobado con notificación (Factura electrónica, Recibido) | J45: No encontrado | K45: El tercero no aparece en el Journal. | L45: NIT sin movimientos en el archivo del Journal. | M45: PENDIENTE | N45: DIAN | O45: No encontrado | Q45: No encontrado | R45: No disponible
A46: CHRISTIAN CAMILO QUEVEDO OCHOA | B46: 1130588761 | C46: ETPC418 | D46: No disponible | E46: 23000 | F46: No encontrado | G46: =IF(AND(ISNUMBER(E46),ISNUMBER(F46)),E46-F46,"No disponible") -> No disponible | H46: No disponible | I46: Aprobado con notificación (Factura electrónica, Recibido) | J46: No encontrado | K46: El tercero no aparece en el Journal. | L46: NIT sin movimientos en el archivo del Journal. | M46: PENDIENTE | N46: DIAN | O46: No encontrado | Q46: No encontrado | R46: No disponible
A47: CIMEX COLOMBIA S.A.S | B47: 800202146 | C47: 2FE84768 | D47: 23359501 OTROS | E47: 28000 | F47: 28000 | G47: =IF(AND(ISNUMBER(E47),ISNUMBER(F47)),E47-F47,"No disponible") -> 0 | H47: Retenciones (crédito): 0.00 | Gasto/otros: No disponible (líneas fuera del archivo exportado) | I47: Aprobado con notificación (Factura electrónica, Recibido) | J47: Presente en el auxiliar (el archivo no trae columna de estado; se infiere Contabilizado) | K47: Coincide el NIT y el valor exacto, pero ninguna línea del Journal cita el número del documento; no se puede identificar con certeza. | L47: — | M47: INFORMACIÓN INSUFICIENTE | N47: DIAN | O47: 001-FSC-00011490 | P47: 7581 | Q47: NIT + valor (sin folio) | R47: No (gasto/IVA cortado en la exportación)
A48: CIMEX COLOMBIA S.A.S | B48: 800202146 | C48: 2FE85515 | D48: 23359501 OTROS; 24081510 IVA TRANSITORIO COMPRAS 19% | E48: 60999.9 | F48: 61000 | G48: =IF(AND(ISNUMBER(E48),ISNUMBER(F48)),E48-F48,"No disponible") -> -0.1 | H48: IVA: 4,790.00 | Retenciones (crédito): 0.00 | Gasto/otros: No disponible (líneas fuera del archivo exportado) | I48: Aprobado con notificación (Factura electrónica, Recibido) | J48: Presente en el auxiliar (el archivo no trae columna de estado; se infiere Contabilizado) | K48: El lado proveedor + retenciones del Journal no coincide con el total de la DIAN. | L48: — | M48: PENDIENTE | N48: DIAN | O48: 001-FSC-00011547 | P48: 7583, 11073 | Q48: referencia | R48: No (gasto/IVA cortado en la exportación)
A49: CLINICA DEL COLON S A S | B49: 805019003 | C49: FEPC9504 | D49: 23359501 OTROS; 24081510 IVA TRANSITORIO COMPRAS 19%; 51058401 GASTOS MEDICOS Y DROGAS | E49: 418000 | F49: 418001 | G49: =IF(AND(ISNUMBER(E49),ISNUMBER(F49)),E49-F49,"No disponible") -> -1 | H49: IVA: 66,740.00 | Gastos: 351,261.00 | Retenciones (crédito): 0.00 | I49: Aprobado con notificación (Factura electrónica, Recibido) | J49: Presente en el auxiliar (el archivo no trae columna de estado; se infiere Contabilizado) | K49: La suma de los conceptos contables no coincide con el total de la DIAN. | L49: — | M49: PENDIENTE | N49: DIAN | O49: 001-FSC-00011514 | P49: 7651, 11098, 16192 | Q49: referencia | R49: Sí
A50: COEXITO S.A.S. | B50: 890300225 | C50: 129B89379 | D50: No disponible | E50: 15000 | F50: No encontrado | G50: =IF(AND(ISNUMBER(E50),ISNUMBER(F50)),E50-F50,"No disponible") -> No disponible | H50: No disponible | I50: Aprobado con notificación (Factura electrónica, Recibido) | J50: No encontrado | K50: El tercero no aparece en el Journal. | L50: NIT sin movimientos en el archivo del Journal. | M50: PENDIENTE | N50: DIAN | O50: No encontrado | Q50: No encontrado | R50: No disponible
A51: COEXITO S.A.S. | B51: 890300225 | C51: 129B92054 | D51: No disponible | E51: 10000 | F51: No encontrado | G51: =IF(AND(ISNUMBER(E51),ISNUMBER(F51)),E51-F51,"No disponible") -> No disponible | H51: No disponible | I51: Aprobado con notificación (Factura electrónica, Recibido) | J51: No encontrado | K51: El tercero no aparece en el Journal. | L51: NIT sin movimientos en el archivo del Journal. | M51: PENDIENTE | N51: DIAN | O51: No encontrado | Q51: No encontrado | R51: No disponible
A52: COLOMBIA TELECOMUNICACIONES S.A. E.S.P. BIC | B52: 830122566 | C52: BEC546849816 | D52: 23359501 OTROS; 24081513 IVA TRANSITORIO SERVICIOS 19% | E52: 21995 | F52: 21995 | G52: =IF(AND(ISNUMBER(E52),ISNUMBER(F52)),E52-F52,"No disponible") -> 0 | H52: IVA: 3,498.00 | Retenciones (crédito): 0.00 | Gasto/otros: No disponible (líneas fuera del archivo exportado) | I52: Aprobado con notificación (Factura electrónica, Recibido) | J52: Presente en el auxiliar (el archivo no trae columna de estado; se infiere Contabilizado) | K52: El lado proveedor + retenciones coincide exacto con la DIAN, pero las líneas de gasto/IVA no están completas en el Journal exportado (el archivo se corta en la fila 16.383); no se puede confirmar la suma de conceptos. | L52: — | M52: INFORMACIÓN INSUFICIENTE | N52: DIAN | O52: 001-FSC-00011434 | P52: 7703, 11291 | Q52: referencia | R52: No (gasto/IVA cortado en la exportación)
A53: COLOMBIA TELECOMUNICACIONES S.A. E.S.P. BIC | B53: 830122566 | C53: BEC546849819 | D53: 23359501 OTROS; 24081513 IVA TRANSITORIO SERVICIOS 19% | E53: 10996 | F53: 10996 | G53: =IF(AND(ISNUMBER(E53),ISNUMBER(F53)),E53-F53,"No disponible") -> 0 | H53: IVA: 1,756.00 | Retenciones (crédito): 0.00 | Gasto/otros: No disponible (líneas fuera del archivo exportado) | I53: Aprobado con notificación (Factura electrónica, Recibido) | J53: Presente en el auxiliar (el archivo no trae columna de estado; se infiere Contabilizado) | K53: Coincide el NIT y el valor exacto, pero ninguna línea del Journal cita el número del documento; no se puede identificar con certeza. | L53: — | M53: INFORMACIÓN INSUFICIENTE | N53: DIAN | O53: 001-FSC-00011435 | P53: 7704, 11292 | Q53: NIT + valor (sin folio) | R53: No (gasto/IVA cortado en la exportación)
A54: COLOMBIA TELECOMUNICACIONES S.A. E.S.P. BIC | B54: 830122566 | C54: BEC546850762 | D54: 23359501 OTROS; 24081513 IVA TRANSITORIO SERVICIOS 19% | E54: 44875 | F54: 44875 | G54: =IF(AND(ISNUMBER(E54),ISNUMBER(F54)),E54-F54,"No disponible") -> 0 | H54: IVA: 7,152.00 | Retenciones (crédito): 0.00 | Gasto/otros: No disponible (líneas fuera del archivo exportado) | I54: Aprobado con notificación (Factura electrónica, Recibido) | J54: Presente en el auxiliar (el archivo no trae columna de estado; se infiere Contabilizado) | K54: El lado proveedor + retenciones coincide exacto con la DIAN, pero las líneas de gasto/IVA no están completas en el Journal exportado (el archivo se corta en la fila 16.383); no se puede confirmar la suma de conceptos. | L54: — | M54: INFORMACIÓN INSUFICIENTE | N54: DIAN | O54: 001-FSC-00011428 | P54: 7697, 11285 | Q54: referencia | R54: No (gasto/IVA cortado en la exportación)
A55: COLOMBIA TELECOMUNICACIONES S.A. E.S.P. BIC | B55: 830122566 | C55: BEC546850764 | D55: 23359501 OTROS; 24081513 IVA TRANSITORIO SERVICIOS 19% | E55: 21995 | F55: 21995 | G55: =IF(AND(ISNUMBER(E55),ISNUMBER(F55)),E55-F55,"No disponible") -> 0 | H55: IVA: 3,498.00 | Retenciones (crédito): 0.00 | Gasto/otros: No disponible (líneas fuera del archivo exportado) | I55: Aprobado con notificación (Factura electrónica, Recibido) | J55: Presente en el auxiliar (el archivo no trae columna de estado; se infiere Contabilizado) | K55: El lado proveedor + retenciones coincide exacto con la DIAN, pero las líneas de gasto/IVA no están completas en el Journal exportado (el archivo se corta en la fila 16.383); no se puede confirmar la suma de conceptos. | L55: — | M55: INFORMACIÓN INSUFICIENTE | N55: DIAN | O55: 001-FSC-00011433 | P55: 7702, 11290 | Q55: referencia | R55: No (gasto/IVA cortado en la exportación)
A56: COLOMBIA TELECOMUNICACIONES S.A. E.S.P. BIC | B56: 830122566 | C56: BEC546850765 | D56: 23359501 OTROS; 24081513 IVA TRANSITORIO SERVICIOS 19% | E56: 66348 | F56: 66348 | G56: =IF(AND(ISNUMBER(E56),ISNUMBER(F56)),E56-F56,"No disponible") -> 0 | H56: IVA: 10,580.00 | Retenciones (crédito): 0.00 | Gasto/otros: No disponible (líneas fuera del archivo exportado) | I56: Aprobado con notificación (Factura electrónica, Recibido) | J56: Presente en el auxiliar (el archivo no trae columna de estado; se infiere Contabilizado) | K56: El lado proveedor + retenciones coincide exacto con la DIAN, pero las líneas de gasto/IVA no están completas en el Journal exportado (el archivo se corta en la fila 16.383); no se puede confirmar la suma de conceptos. | L56: — | M56: INFORMACIÓN INSUFICIENTE | N56: DIAN | O56: 001-FSC-00011430 | P56: 7699, 11287 | Q56: referencia | R56: No (gasto/IVA cortado en la exportación)
A57: COLOMBIA TELECOMUNICACIONES S.A. E.S.P. BIC | B57: 830122566 | C57: BEC546851208 | D57: 23359501 OTROS; 24081513 IVA TRANSITORIO SERVICIOS 19% | E57: 10996 | F57: 10996 | G57: =IF(AND(ISNUMBER(E57),ISNUMBER(F57)),E57-F57,"No disponible") -> 0 | H57: IVA: 1,756.00 | Retenciones (crédito): 0.00 | Gasto/otros: No disponible (líneas fuera del archivo exportado) | I57: Aprobado con notificación (Factura electrónica, Recibido) | J57: Presente en el auxiliar (el archivo no trae columna de estado; se infiere Contabilizado) | K57: El lado proveedor + retenciones coincide exacto con la DIAN, pero las líneas de gasto/IVA no están completas en el Journal exportado (el archivo se corta en la fila 16.383); no se puede confirmar la suma de conceptos. | L57: — | M57: INFORMACIÓN INSUFICIENTE | N57: DIAN | O57: 001-FSC-00011435 | P57: 7704, 11292 | Q57: referencia | R57: No (gasto/IVA cortado en la exportación)
A58: COLOMBIA TELECOMUNICACIONES S.A. E.S.P. BIC | B58: 830122566 | C58: BEC546851212 | D58: 23359501 OTROS; 24081513 IVA TRANSITORIO SERVICIOS 19% | E58: 21995 | F58: 21995 | G58: =IF(AND(ISNUMBER(E58),ISNUMBER(F58)),E58-F58,"No disponible") -> 0 | H58: IVA: 3,498.00 | Retenciones (crédito): 0.00 | Gasto/otros: No disponible (líneas fuera del archivo exportado) | I58: Aprobado con notificación (Factura electrónica, Recibido) | J58: Presente en el auxiliar (el archivo no trae columna de estado; se infiere Contabilizado) | K58: El lado proveedor + retenciones coincide exacto con la DIAN, pero las líneas de gasto/IVA no están completas en el Journal exportado (el archivo se corta en la fila 16.383); no se puede confirmar la suma de conceptos. | L58: — | M58: INFORMACIÓN INSUFICIENTE | N58: DIAN | O58: 001-FSC-00011427 | P58: 7696, 11284 | Q58: referencia | R58: No (gasto/IVA cortado en la exportación)
A59: COLOMBIA TELECOMUNICACIONES S.A. E.S.P. BIC | B59: 830122566 | C59: BEC546906901 | D59: 23359501 OTROS; 24081513 IVA TRANSITORIO SERVICIOS 19%; 51159502 IMPUESTO AL CONSUMO 8% | E59: 65852 | F59: 65852 | G59: =IF(AND(ISNUMBER(E59),ISNUMBER(F59)),E59-F59,"No disponible") -> 0 | H59: IVA: 10,501.00 | Otros impuestos: 82.00 | Retenciones (crédito): 0.00 | Gasto/otros: No disponible (líneas fuera del archivo exportado) | I59: Aprobado con notificación (Factura electrónica, Recibido) | J59: Presente en el auxiliar (el archivo no trae columna de estado; se infiere Contabilizado) | K59: El lado proveedor + retenciones coincide exacto con la DIAN, pero las líneas de gasto/IVA no están completas en el Journal exportado (el archivo se corta en la fila 16.383); no se puede confirmar la suma de conceptos. | L59: — | M59: INFORMACIÓN INSUFICIENTE | N59: DIAN | O59: 001-FSC-00011425 | P59: 7694, 11282, 16329 | Q59: referencia | R59: No (gasto/IVA cortado en la exportación)
A60: COLOMBIA TELECOMUNICACIONES S.A. E.S.P. BIC | B60: 830122566 | C60: BEC546906902 | D60: 23359501 OTROS; 24081513 IVA TRANSITORIO SERVICIOS 19%; 51159502 IMPUESTO AL CONSUMO 8% | E60: 21995 | F60: 21995 | G60: =IF(AND(ISNUMBER(E60),ISNUMBER(F60)),E60-F60,"No disponible") -> 0 | H60: IVA: 3,498.00 | Otros impuestos: 84.00 | Retenciones (crédito): 0.00 | Gasto/otros: No disponible (líneas fuera del archivo exportado) | I60: Aprobado con notificación (Factura electrónica, Recibido) | J60: Presente en el auxiliar (el archivo no trae columna de estado; se infiere Contabilizado) | K60: El lado proveedor + retenciones coincide exacto con la DIAN, pero las líneas de gasto/IVA no están completas en el Journal exportado (el archivo se corta en la fila 16.383); no se puede confirmar la suma de conceptos. | L60: — | M60: INFORMACIÓN INSUFICIENTE | N60: DIAN | O60: 001-FSC-00011422 | P60: 7691, 11279, 16327 | Q60: referencia | R60: No (gasto/IVA cortado en la exportación)
A61: COLOMBIA TELECOMUNICACIONES S.A. E.S.P. BIC | B61: 830122566 | C61: BEC546906905 | D61: 23359501 OTROS; 24081513 IVA TRANSITORIO SERVICIOS 19% | E61: 44875 | F61: 44875 | G61: =IF(AND(ISNUMBER(E61),ISNUMBER(F61)),E61-F61,"No disponible") -> 0 | H61: IVA: 7,152.00 | Retenciones (crédito): 0.00 | Gasto/otros: No disponible (líneas fuera del archivo exportado) | I61: Aprobado con notificación (Factura electrónica, Recibido) | J61: Presente en el auxiliar (el archivo no trae columna de estado; se infiere Contabilizado) | K61: El lado proveedor + retenciones coincide exacto con la DIAN, pero las líneas de gasto/IVA no están completas en el Journal exportado (el archivo se corta en la fila 16.383); no se puede confirmar la suma de conceptos. | L61: — | M61: INFORMACIÓN INSUFICIENTE | N61: DIAN | O61: 001-FSC-00011432 | P61: 7701, 11289 | Q61: referencia | R61: No (gasto/IVA cortado en la exportación)
A62: COLOMBIA TELECOMUNICACIONES S.A. E.S.P. BIC | B62: 830122566 | C62: BEC546906906 | D62: 23359501 OTROS; 24081513 IVA TRANSITORIO SERVICIOS 19% | E62: 12000 | F62: 12000 | G62: =IF(AND(ISNUMBER(E62),ISNUMBER(F62)),E62-F62,"No disponible") -> 0 | H62: IVA: 1,916.00 | Retenciones (crédito): 0.00 | Gasto/otros: No disponible (líneas fuera del archivo exportado) | I62: Aprobado con notificación (Factura electrónica, Recibido) | J62: Presente en el auxiliar (el archivo no trae columna de estado; se infiere Contabilizado) | K62: El lado proveedor + retenciones coincide exacto con la DIAN, pero las líneas de gasto/IVA no están completas en el Journal exportado (el archivo se corta en la fila 16.383); no se puede confirmar la suma de conceptos. | L62: — | M62: INFORMACIÓN INSUFICIENTE | N62: DIAN | O62: 001-FSC-00011429 | P62: 7698, 11286 | Q62: referencia | R62: No (gasto/IVA cortado en la exportación)
A63: COLOMBIA TELECOMUNICACIONES S.A. E.S.P. BIC | B63: 830122566 | C63: BEC546906982 | D63: 23359501 OTROS; 24081513 IVA TRANSITORIO SERVICIOS 19% | E63: 53293 | F63: 53293 | G63: =IF(AND(ISNUMBER(E63),ISNUMBER(F63)),E63-F63,"No disponible") -> 0 | H63: IVA: 8,490.00 | Retenciones (crédito): 0.00 | Gasto/otros: No disponible (líneas fuera del archivo exportado) | I63: Aprobado con notificación (Factura electrónica, Recibido) | J63: Presente en el auxiliar (el archivo no trae columna de estado; se infiere Contabilizado) | K63: El lado proveedor + retenciones coincide exacto con la DIAN, pero las líneas de gasto/IVA no están completas en el Journal exportado (el archivo se corta en la fila 16.383); no se puede confirmar la suma de conceptos. | L63: — | M63: INFORMACIÓN INSUFICIENTE | N63: DIAN | O63: 001-FSC-00011431 | P63: 7700, 11288 | Q63: referencia | R63: No (gasto/IVA cortado en la exportación)
... A70: COLOMBIA TELECOMUNICACIONES S.A. E.S.P. BIC | B70: 830122566 | C70: BEC546906989 | D70: 23359501 OTROS; 24081513 IVA TRANSITORIO SERVICIOS 19% | E70: 44875 | F70: 44875 | G70: =IF(AND(ISNUMBER(E70),ISNUMBER(F70)),E70-F70,"No disponible") -> 0 | H70: IVA: 7,152.00 | Retenciones (crédito): 0.00 | Gasto/otros: No disponible (líneas fuera del archivo exportado) | I70: Aprobado con notificación (Factura electrónica, Recibido) | J70: Presente en el auxiliar (el archivo no trae columna de estado; se infiere Contabilizado) | K70: El lado proveedor + retenciones coincide exacto con la DIAN, pero las líneas de gasto/IVA no están completas en el Journal exportado (el archivo se corta en la fila 16.383); no se puede confirmar la suma de conceptos. | L70: — | M70: INFORMACIÓN INSUFICIENTE | N70: DIAN | O70: 001-FSC-00011426 | P70: 7695, 11283 | Q70: referencia | R70: No (gasto/IVA cortado en la exportación)
A71: COLOMBIA TELECOMUNICACIONES S.A. E.S.P. BIC | B71: 830122566 | C71: BEV25925571 | D71: No disponible | E71: 8800 | F71: No encontrado | G71: =IF(AND(ISNUMBER(E71),ISNUMBER(F71)),E71-F71,"No disponible") -> No disponible | H71: No disponible | I71: Aprobado con notificación (Factura electrónica, Recibido) | J71: No encontrado | K71: No se encontró el documento en el Journal (el tercero sí tiene otros movimientos). | L71: El tercero aparece en el Journal pero ninguna línea cita este folio ni coincide su valor. | M71: PENDIENTE | N71: DIAN | O71: No encontrado | Q71: No encontrado | R71: No disponible
A72: COLOMBIA TELECOMUNICACIONES S.A. E.S.P. BIC | B72: 830122566 | C72: BEV25925624 | D72: No disponible | E72: 8800 | F72: No encontrado | G72: =IF(AND(ISNUMBER(E72),ISNUMBER(F72)),E72-F72,"No disponible") -> No disponible | H72: No disponible | I72: Aprobado con notificación (Factura electrónica, Recibido) | J72: No encontrado | K72: No se encontró el documento en el Journal (el tercero sí tiene otros movimientos). | L72: El tercero aparece en el Journal pero ninguna línea cita este folio ni coincide su valor. | M72: PENDIENTE | N72: DIAN | O72: No encontrado | Q72: No encontrado | R72: No disponible
A73: COLVANES S.A.S | B73: 800185306 | C73: FE02172053 | D73: 23354501 TRANSPORTES, FLETES Y ACARREOS | E73: 843093 | F73: 843093 | G73: =IF(AND(ISNUMBER(E73),ISNUMBER(F73)),E73-F73,"No disponible") -> 0 | H73: Retenciones (crédito): 0.00 | Gasto/otros: No disponible (líneas fuera del archivo exportado) | I73: Aprobado con notificación (Factura electrónica, Recibido) | J73: Presente en el auxiliar (el archivo no trae columna de estado; se infiere Contabilizado) | K73: El lado proveedor + retenciones coincide exacto con la DIAN, pero las líneas de gasto/IVA no están completas en el Journal exportado (el archivo se corta en la fila 16.383); no se puede confirmar la suma de conceptos. | L73: — | M73: INFORMACIÓN INSUFICIENTE | N73: DIAN | O73: 001-FSC-00011466 | P73: 7338 | Q73: referencia | R73: No (gasto/IVA cortado en la exportación)
A74: COLVANES S.A.S | B74: 800185306 | C74: FE02172101 | D74: 23354501 TRANSPORTES, FLETES Y ACARREOS | E74: 8375367 | F74: 8375367 | G74: =IF(AND(ISNUMBER(E74),ISNUMBER(F74)),E74-F74,"No disponible") -> 0 | H74: Retenciones (crédito): 0.00 | Gasto/otros: No disponible (líneas fuera del archivo exportado) | I74: Aprobado con notificación (Factura electrónica, Recibido) | J74: Presente en el auxiliar (el archivo no trae columna de estado; se infiere Contabilizado) | K74: El lado proveedor + retenciones coincide exacto con la DIAN, pero las líneas de gasto/IVA no están completas en el Journal exportado (el archivo se corta en la fila 16.383); no se puede confirmar la suma de conceptos. | L74: — | M74: INFORMACIÓN INSUFICIENTE | N74: DIAN | O74: 001-FSC-00011461 | P74: 7337 | Q74: referencia | R74: No (gasto/IVA cortado en la exportación)
A75: COLVANES S.A.S | B75: 800185306 | C75: FE02172909 | D75: 23354501 TRANSPORTES, FLETES Y ACARREOS | E75: 584463 | F75: 584463 | G75: =IF(AND(ISNUMBER(E75),ISNUMBER(F75)),E75-F75,"No disponible") -> 0 | H75: Retenciones (crédito): 0.00 | Gasto/otros: No disponible (líneas fuera del archivo exportado) | I75: Aprobado con notificación (Factura electrónica, Recibido) | J75: Presente en el auxiliar (el archivo no trae columna de estado; se infiere Contabilizado) | K75: El lado proveedor + retenciones coincide exacto con la DIAN, pero las líneas de gasto/IVA no están completas en el Journal exportado (el archivo se corta en la fila 16.383); no se puede confirmar la suma de conceptos. | L75: — | M75: INFORMACIÓN INSUFICIENTE | N75: DIAN | O75: 001-FSC-00011571 | P75: 7339 | Q75: referencia | R75: No (gasto/IVA cortado en la exportación)
A76: COLVANES S.A.S | B76: 800185306 | C76: FE02172910 | D76: 23354501 TRANSPORTES, FLETES Y ACARREOS | E76: 8723906 | F76: 8723906 | G76: =IF(AND(ISNUMBER(E76),ISNUMBER(F76)),E76-F76,"No disponible") -> 0 | H76: Retenciones (crédito): 0.00 | Gasto/otros: No disponible (líneas fuera del archivo exportado) | I76: Aprobado con notificación (Factura electrónica, Recibido) | J76: Presente en el auxiliar (el archivo no trae columna de estado; se infiere Contabilizado) | K76: El lado proveedor + retenciones coincide exacto con la DIAN, pero las líneas de gasto/IVA no están completas en el Journal exportado (el archivo se corta en la fila 16.383); no se puede confirmar la suma de conceptos. | L76: — | M76: INFORMACIÓN INSUFICIENTE | N76: DIAN | O76: 001-FSC-00011572 | P76: 7340 | Q76: referencia | R76: No (gasto/IVA cortado en la exportación)
A77: COMBUSTIBLES LIQUIDOS DE COLOMBIA SA ESP | B77: 900175830 | C77: 2YUM22779 | D77: 23359501 OTROS | E77: 96900 | F77: 96900 | G77: =IF(AND(ISNUMBER(E77),ISNUMBER(F77)),E77-F77,"No disponible") -> 0 | H77: Retenciones (crédito): 0.00 | Gasto/otros: No disponible (líneas fuera del archivo exportado) | I77: Aprobado con notificación (Factura electrónica, Recibido) | J77: Presente en el auxiliar (el archivo no trae columna de estado; se infiere Contabilizado) | K77: Coincide el NIT y el valor exacto, pero ninguna línea del Journal cita el número del documento; no se puede identificar con certeza. | L77: — | M77: INFORMACIÓN INSUFICIENTE | N77: DIAN | O77: 001-FSC-00011407 | P77: 7850 | Q77: NIT + valor (sin folio) | R77: No (gasto/IVA cortado en la exportación)
A78: COMBUSTIBLES LIQUIDOS DE COLOMBIA SA ESP | B78: 900175830 | C78: 2YUM23349 | D78: 23359501 OTROS | E78: 98900 | F78: 98900 | G78: =IF(AND(ISNUMBER(E78),ISNUMBER(F78)),E78-F78,"No disponible") -> 0 | H78: Retenciones (crédito): 0.00 | Gasto/otros: No disponible (líneas fuera del archivo exportado) | I78: Aprobado con notificación (Factura electrónica, Recibido) | J78: Presente en el auxiliar (el archivo no trae columna de estado; se infiere Contabilizado) | K78: Coincide el NIT y el valor exacto, pero ninguna línea del Journal cita el número del documento; no se puede identificar con certeza. | L78: — | M78: INFORMACIÓN INSUFICIENTE | N78: DIAN | O78: 001-FSC-00011516 | P78: 7852 | Q78: NIT + valor (sin folio) | R78: No (gasto/IVA cortado en la exportación)
A79: COMERCIALIZADORA MARDEN LTDA | B79: 800004599 | C79: PECO410957 | D79: 23359501 OTROS; 24081510 IVA TRANSITORIO COMPRAS 19% | E79: 27399.75 | F79: 27400 | G79: =IF(AND(ISNUMBER(E79),ISNUMBER(F79)),E79-F79,"No disponible") -> -0.25 | H79: IVA: 4,375.00 | Retenciones (crédito): 0.00 | Gasto/otros: No disponible (líneas fuera del archivo exportado) | I79: Aprobado con notificación (Factura electrónica, Recibido) | J79: Presente en el auxiliar (el archivo no trae columna de estado; se infiere Contabilizado) | K79: El lado proveedor + retenciones del Journal no coincide con el total de la DIAN. | L79: — | M79: PENDIENTE | N79: DIAN | O79: 001-FSC-00011549 | P79: 7552, 11060 | Q79: referencia | R79: No (gasto/IVA cortado en la exportación)
A80: COMPAÑÍA MUNDIAL DE SEGUROS S.A. | B80: 860037013 | C80: 014F21554007 | D80: No disponible | E80: 946600 | F80: No encontrado | G80: =IF(AND(ISNUMBER(E80),ISNUMBER(F80)),E80-F80,"No disponible") -> No disponible | H80: No disponible | I80: Aprobado con notificación (Factura electrónica, Recibido) | J80: No encontrado | K80: El tercero no aparece en el Journal. | L80: NIT sin movimientos en el archivo del Journal. | M80: PENDIENTE | N80: DIAN | O80: No encontrado | Q80: No encontrado | R80: No disponible
A81: COMUNICACION CELULAR S A COMCEL S A | B81: 800153993 | C81: 3292734891 | D81: 23359501 OTROS; 24081513 IVA TRANSITORIO SERVICIOS 19% | E81: 511867 | F81: 511867 | G81: =IF(AND(ISNUMBER(E81),ISNUMBER(F81)),E81-F81,"No disponible") -> 0 | H81: IVA: 81,727.00 | Retenciones (crédito): 0.00 | Gasto/otros: No disponible (líneas fuera del archivo exportado) | I81: Aprobado con notificación (Factura electrónica, Recibido) | J81: Presente en el auxiliar (el archivo no trae columna de estado; se infiere Contabilizado) | K81: El lado proveedor + retenciones coincide exacto con la DIAN, pero las líneas de gasto/IVA no están completas en el Journal exportado (el archivo se corta en la fila 16.383); no se puede confirmar la suma de conceptos. | L81: — | M81: INFORMACIÓN INSUFICIENTE | N81: DIAN | O81: 001-FSC-00011355 | P81: 7578, 11245 | Q81: referencia | R81: No (gasto/IVA cortado en la exportación)
A82: CONSTRUIR INGENIERIA S.A.S. | B82: 800222034 | C82: FEH417 | D82: 23359501 OTROS; 23652507 SERVICIOS GENERALES (DECLARANTES) 4%; 23680203 DEMAS ACTIVIDADES SERVICIOS 10 X 1000; 24081513 IVA TRANSITORIO SERVICIOS 19% | E82: 9520000 | F82: 9520000 | G82: =IF(AND(ISNUMBER(E82),ISNUMBER(F82)),E82-F82,"No disponible") -> 0 | H82: IVA: 1,520,000.00 | Retenciones (crédito): 400,000.00 | Gasto/otros: No disponible (líneas fuera del archivo exportado) | I82: Aprobado con notificación (Factura electrónica, Recibido) | J82: Presente en el auxiliar (el archivo no trae columna de estado; se infiere Contabilizado) | K82: El lado proveedor + retenciones coincide exacto con la DIAN, pero las líneas de gasto/IVA no están completas en el Journal exportado (el archivo se corta en la fila 16.383); no se puede confirmar la suma de conceptos. | L82: — | M82: INFORMACIÓN INSUFICIENTE | N82: DIAN | O82: 001-NT-00012705 | P82: 7586, 8245, 9204, 11251 | Q82: referencia | R82: No (gasto/IVA cortado en la exportación)
A83: COOPERATIVA INTEGRAL DE TAXIS BELALCAZAR | B83: 891500277 | C83: FTPI650564 | D83: No disponible | E83: 6500 | F83: No encontrado | G83: =IF(AND(ISNUMBER(E83),ISNUMBER(F83)),E83-F83,"No disponible") -> No disponible | H83: No disponible | I83: Aprobado (Documento equivalente - Transporte pasajeros terrestre, Recibido) | J83: No encontrado | K83: El tercero no aparece en el Journal. | L83: NIT sin movimientos en el archivo del Journal. | M83: PENDIENTE | N83: DIAN | O83: No encontrado | Q83: No encontrado | R83: No disponible
A84: COOPERATIVA INTEGRAL DE TAXIS BELALCAZAR | B84: 891500277 | C84: FTPO614139 | D84: No disponible | E84: 33000 | F84: No encontrado | G84: =IF(AND(ISNUMBER(E84),ISNUMBER(F84)),E84-F84,"No disponible") -> No disponible | H84: No disponible | I84: Aprobado (Documento equivalente - Transporte pasajeros terrestre, Recibido) | J84: No encontrado | K84: El tercero no aparece en el Journal. | L84: NIT sin movimientos en el archivo del Journal. | M84: PENDIENTE | N84: DIAN | O84: No encontrado | Q84: No encontrado | R84: No disponible
A85: COORDINADORA MERCANTIL S.A. | B85: 890904713 | C85: D03194001448 | D85: 23359501 OTROS | E85: 65830 | F85: 65830 | G85: =IF(AND(ISNUMBER(E85),ISNUMBER(F85)),E85-F85,"No disponible") -> 0 | H85: Retenciones (crédito): 0.00 | Gasto/otros: No disponible (líneas fuera del archivo exportado) | I85: Aprobado con notificación (Factura electrónica, Recibido) | J85: Presente en el auxiliar (el archivo no trae columna de estado; se infiere Contabilizado) | K85: Coincide el NIT y el valor exacto, pero ninguna línea del Journal cita el número del documento; no se puede identificar con certeza. | L85: — | M85: INFORMACIÓN INSUFICIENTE | N85: DIAN | O85: 001-FSC-00011517 | P85: 7827 | Q85: NIT + valor (sin folio) | R85: No (gasto/IVA cortado en la exportación)
A86: COQUEZ GONZALEZ JHON ALEXANDER | B86: 94501120 | C86: NDSE1714 | D86: 23359501 OTROS | E86: 80000 | F86: 80000 | G86: =IF(AND(ISNUMBER(E86),ISNUMBER(F86)),E86-F86,"No disponible") -> 0 | H86: Retenciones (crédito): 0.00 | Gasto/otros: No disponible (líneas fuera del archivo exportado) | I86: Aprobado con notificación (Documento soporte con no obligados, Emitido) | J86: Presente en el auxiliar (el archivo no trae columna de estado; se infiere Contabilizado) | K86: El lado proveedor + retenciones coincide exacto con la DIAN, pero las líneas de gasto/IVA no están completas en el Journal exportado (el archivo se corta en la fila 16.383); no se puede confirmar la suma de conceptos. | L86: — | M86: INFORMACIÓN INSUFICIENTE | N86: DIAN | O86: 001-DSE-00001714 | P86: 8053 | Q86: referencia | R86: No (gasto/IVA cortado en la exportación)
A87: CORREDOR DEL PACIFICO S.A.S. | B87: 900394298 | C87: 12054711 | D87: No disponible | E87: 42000 | F87: No encontrado | G87: =IF(AND(ISNUMBER(E87),ISNUMBER(F87)),E87-F87,"No disponible") -> No disponible | H87: No disponible | I87: Aprobado con notificación (Documento equivalente - Transporte pasajeros terrestre, Recibido) | J87: No encontrado | K87: El tercero no aparece en el Journal. | L87: NIT sin movimientos en el archivo del Journal. | M87: PENDIENTE | N87: DIAN | O87: No encontrado | Q87: No encontrado | R87: No disponible
A88: CORTES CAMPANA JOSE DAVID | B88: 1144187764 | C88: NDSE1728 | D88: 23359501 OTROS | E88: 600000 | F88: 600000 | G88: =IF(AND(ISNUMBER(E88),ISNUMBER(F88)),E88-F88,"No disponible") -> 0 | H88: Retenciones (crédito): 0.00 | Gasto/otros: No disponible (líneas fuera del archivo exportado) | I88: Aprobado con notificación (Documento soporte con no obligados, Emitido) | J88: Presente en el auxiliar (el archivo no trae columna de estado; se infiere Contabilizado) | K88: El lado proveedor + retenciones coincide exacto con la DIAN, pero las líneas de gasto/IVA no están completas en el Journal exportado (el archivo se corta en la fila 16.383); no se puede confirmar la suma de conceptos. | L88: — | M88: INFORMACIÓN INSUFICIENTE | N88: DIAN | O88: 001-DSE-00001728 | P88: 7404 | Q88: referencia | R88: No (gasto/IVA cortado en la exportación)
A89: CORTULUA FUTBOL CLUB S.A. | B89: 800097185 | C89: FEDV540 | D89: 23359501 OTROS; 23651505 HONORARIOS 11%; 24081513 IVA TRANSITORIO SERVICIOS 19% | E89: 11656675 | F89: 11656675 | G89: =IF(AND(ISNUMBER(E89),ISNUMBER(F89)),E89-F89,"No disponible") -> 0 | H89: IVA: 1,861,150.00 | Retenciones (crédito): 1,077,508.00 | Gasto/otros: No disponible (líneas fuera del archivo exportado) | I89: Aprobado con notificación (Factura electrónica, Recibido) | J89: Presente en el auxiliar (el archivo no trae columna de estado; se infiere Contabilizado) | K89: El lado proveedor + retenciones coincide exacto con la DIAN, pero las líneas de gasto/IVA no están completas en el Journal exportado (el archivo se corta en la fila 16.383); no se puede confirmar la suma de conceptos. | L89: — | M89: INFORMACIÓN INSUFICIENTE | N89: DIAN | O89: 001-FSC-00011583 | P89: 7574, 8150, 11240 | Q89: referencia | R89: No (gasto/IVA cortado en la exportación)
A90: CUEVAS COLORADO WALTER ARNULFO | B90: 94527988 | C90: 1462 | D90: 23359501 OTROS; 23652507 SERVICIOS GENERALES (DECLARANTES) 4% | E90: 250000 | F90: 250000 | G90: =IF(AND(ISNUMBER(E90),ISNUMBER(F90)),E90-F90,"No disponible") -> 0 | H90: Retenciones (crédito): 10,000.00 | Gasto/otros: No disponible (líneas fuera del archivo exportado) | I90: Aprobado con notificación (Factura electrónica, Recibido) | J90: Presente en el auxiliar (el archivo no trae columna de estado; se infiere Contabilizado) | K90: El lado proveedor + retenciones coincide exacto con la DIAN, pero las líneas de gasto/IVA no están completas en el Journal exportado (el archivo se corta en la fila 16.383); no se puede confirmar la suma de conceptos. | L90: — | M90: INFORMACIÓN INSUFICIENTE | N90: DIAN | O90: 001-FSC-00011351 | P90: 8061, 8286 | Q90: referencia | R90: No (gasto/IVA cortado en la exportación)
A91: Catalina Zuniga Araujo | B91: 66990687 | C91: FE17 | D91: 23359501 OTROS; 24081513 IVA TRANSITORIO SERVICIOS 19% | E91: 10710000 | F91: 10710000 | G91: =IF(AND(ISNUMBER(E91),ISNUMBER(F91)),E91-F91,"No disponible") -> 0 | H91: IVA: 1,710,000.00 | Retenciones (crédito): 0.00 | Gasto/otros: No disponible (líneas fuera del archivo exportado) | I91: Aprobado con notificación (Factura electrónica, Recibido) | J91: Presente en el auxiliar (el archivo no trae columna de estado; se infiere Contabilizado) | K91: El lado proveedor + retenciones coincide exacto con la DIAN, pero las líneas de gasto/IVA no están completas en el Journal exportado (el archivo se corta en la fila 16.383); no se puede confirmar la suma de conceptos. | L91: — | M91: INFORMACIÓN INSUFICIENTE | N91: DIAN | O91: 001-FSC-00011350 | P91: 7514, 11236 | Q91: referencia | R91: No (gasto/IVA cortado en la exportación)
A92: Catalina Zuniga Araujo | B92: 66990687 | C92: FE18 | D92: 23359501 OTROS; 23651505 HONORARIOS 11%; 24081513 IVA TRANSITORIO SERVICIOS 19%; 23359501 OTROS; 23651505 HONORARIOS 11% | E92: 10710000 | F92: 10710000 | G92: =IF(AND(ISNUMBER(E92),ISNUMBER(F92)),E92-F92,"No disponible") -> 0 | H92: IVA: 1,710,000.00 | Retenciones (crédito): 0.00 | Gasto/otros: No disponible (líneas fuera del archivo exportado) | I92: Aprobado con notificación (Factura electrónica, Recibido) | J92: Presente en el auxiliar (el archivo no trae columna de estado; se infiere Contabilizado) | K92: El lado proveedor + retenciones coincide exacto con la DIAN, pero las líneas de gasto/IVA no están completas en el Journal exportado (el archivo se corta en la fila 16.383); no se puede confirmar la suma de conceptos. | L92: Contabilizado en 2 comprobantes del Journal (001-FSC-00011539, 001-NT-00012685); se sumaron todos. | M92: INFORMACIÓN INSUFICIENTE | N92: DIAN | O92: 001-FSC-00011539, 001-NT-00012685 | P92: 7516, 8147, 11237, 7517, 8148 | Q92: referencia | R92: No (gasto/IVA cortado en la exportación)
A93: Club Colombia | B93: 890300521 | C93: FS561133 | D93: 23359501 OTROS; 51251001 AFILIACIONES Y SOSTENIMIENTO | E93: 310000 | F93: 310000 | G93: =IF(AND(ISNUMBER(E93),ISNUMBER(F93)),E93-F93,"No disponible") -> 0 | H93: Gastos: 310,000.00 | Retenciones (crédito): 0.00 | I93: Aprobado con notificación (Factura electrónica, Recibido) | J93: Presente en el auxiliar (el archivo no trae columna de estado; se infiere Contabilizado) | K93: Coincide exacto (débitos = créditos = DIAN). | L93: — | M93: VERIFICADO | N93: DIAN | O93: 001-FSC-00011369 | P93: 7753, 16365 | Q93: referencia | R93: Sí
A94: Colmena Seguros de Vida S.A. | B94: 901528731 | C94: VT25555830 | D94: 23359501 OTROS | E94: 374594.27 | F94: 374595 | G94: =IF(AND(ISNUMBER(E94),ISNUMBER(F94)),E94-F94,"No disponible") -> -0.73 | H94: Retenciones (crédito): 0.00 | Gasto/otros: No disponible (líneas fuera del archivo exportado) | I94: Aprobado con notificación (Factura electrónica, Recibido) | J94: Presente en el auxiliar (el archivo no trae columna de estado; se infiere Contabilizado) | K94: El lado proveedor + retenciones del Journal no coincide con el total de la DIAN. | L94: — | M94: PENDIENTE | N94: DIAN | O94: 001-FSC-00011564 | P94: 7986 | Q94: referencia | R94: No (gasto/IVA cortado en la exportación)
A95: D1 S A S | B95: 900276962 | C95: G5I0261523 | D95: No disponible | E95: 29049.99 | F95: No encontrado | G95: =IF(AND(ISNUMBER(E95),ISNUMBER(F95)),E95-F95,"No disponible") -> No disponible | H95: No disponible | I95: Aprobado con notificación (Factura electrónica, Recibido) | J95: No encontrado | K95: No se encontró el documento en el Journal (el tercero sí tiene otros movimientos). | L95: El tercero aparece en el Journal pero ninguna línea cita este folio ni coincide su valor. | M95: PENDIENTE | N95: DIAN | O95: No encontrado | Q95: No encontrado | R95: No disponible
A96: D1 S A S | B96: 900276962 | C96: M3F859913 | D96: 23359501 OTROS | E96: 5380 | F96: 5380 | G96: =IF(AND(ISNUMBER(E96),ISNUMBER(F96)),E96-F96,"No disponible") -> 0 | H96: Retenciones (crédito): 0.00 | Gasto/otros: No disponible (líneas fuera del archivo exportado) | I96: Aprobado con notificación (Factura electrónica, Recibido) | J96: Presente en el auxiliar (el archivo no trae columna de estado; se infiere Contabilizado) | K96: Coincide el NIT y el valor exacto, pero ninguna línea del Journal cita el número del documento; no se puede identificar con certeza. | L96: — | M96: INFORMACIÓN INSUFICIENTE | N96: DIAN | O96: 001-FSC-00011470 | P96: 7863 | Q96: NIT + valor (sin folio) | R96: No (gasto/IVA cortado en la exportación)
A97: D1 S A S | B97: 900276962 | C97: M3F859914 | D97: 23359501 OTROS | E97: 1950 | F97: 2000 | G97: =IF(AND(ISNUMBER(E97),ISNUMBER(F97)),E97-F97,"No disponible") -> -50 | H97: Retenciones (crédito): 0.00 | Gasto/otros: No disponible (líneas fuera del archivo exportado) | I97: Aprobado con notificación (Factura electrónica, Recibido) | J97: Presente en el auxiliar (el archivo no trae columna de estado; se infiere Contabilizado) | K97: El lado proveedor + retenciones del Journal no coincide con el total de la DIAN. | L97: — | M97: PENDIENTE | N97: DIAN | O97: 001-FSC-00011446 | P97: 7861 | Q97: referencia | R97: No (gasto/IVA cortado en la exportación)
A98: D1 S A S | B98: 900276962 | C98: M3F964991 | D98: 23359501 OTROS | E98: 1950 | F98: 1980 | G98: =IF(AND(ISNUMBER(E98),ISNUMBER(F98)),E98-F98,"No disponible") -> -30 | H98: Retenciones (crédito): 0.00 | Gasto/otros: No disponible (líneas fuera del archivo exportado) | I98: Aprobado con notificación (Factura electrónica, Recibido) | J98: Presente en el auxiliar (el archivo no trae columna de estado; se infiere Contabilizado) | K98: El lado proveedor + retenciones del Journal no coincide con el total de la DIAN. | L98: — | M98: PENDIENTE | N98: DIAN | O98: 001-FSC-00011479 | P98: 7864 | Q98: referencia | R98: No (gasto/IVA cortado en la exportación)
A99: DE LA PAVA Y COMPANIA S A S | B99: 805002135 | C99: NORT57479 | D99: 23359501 OTROS; 24081510 IVA TRANSITORIO COMPRAS 19% | E99: 4500 | F99: 4501 | G99: =IF(AND(ISNUMBER(E99),ISNUMBER(F99)),E99-F99,"No disponible") -> -1 | H99: IVA: 719.00 | Retenciones (crédito): 0.00 | Gasto/otros: No disponible (líneas fuera del archivo exportado) | I99: Aprobado con notificación (Factura electrónica, Recibido) | J99: Presente en el auxiliar (el archivo no trae columna de estado; se infiere Contabilizado) | K99: El lado proveedor + retenciones del Journal no coincide con el total de la DIAN. | L99: — | M99: PENDIENTE | N99: DIAN | O99: 001-FSC-00011409 | P99: 7639, 11093 | Q99: referencia | R99: No (gasto/IVA cortado en la exportación)
A100: DESPEGAR COLOMBIA SAS | B100: 900610518 | C100: FV10521699 | D100: No disponible | E100: 844372 | F100: No encontrado | G100: =IF(AND(ISNUMBER(E100),ISNUMBER(F100)),E100-F100,"No disponible") -> No disponible | H100: No disponible | I100: Aprobado con notificación (Factura electrónica, Recibido) | J100: No encontrado | K100: El tercero no aparece en el Journal. | L100: NIT sin movimientos en el archivo del Journal. | M100: PENDIENTE | N100: DIAN | O100: No encontrado | Q100: No encontrado | R100: No disponible
A101: DISTRACOM S.A. | B101: 811009788 | C101: DST7544954 | D101: No disponible | E101: 12000 | F101: No encontrado | G101: =IF(AND(ISNUMBER(E101),ISNUMBER(F101)),E101-F101,"No disponible") -> No disponible | H101: No disponible | I101: Aprobado con notificación (Factura electrónica, Recibido) | J101: No encontrado | K101: El tercero no aparece en el Journal. | L101: NIT sin movimientos en el archivo del Journal. | M101: PENDIENTE | N101: DIAN | O101: No encontrado | Q101: No encontrado | R101: No disponible
A102: DISTRIBUIDORA MAYORISTA LIMITADA | B102: 800239989 | C102: DMFE832 | D102: 22050501 PROVEEDORES NACIONALES; 23652507 SERVICIOS GENERALES (DECLARANTES) 4% | E102: 163377 | F102: 163377 | G102: =IF(AND(ISNUMBER(E102),ISNUMBER(F102)),E102-F102,"No disponible") -> 0 | H102: Retenciones (crédito): 6,535.00 | Gasto/otros: No disponible (líneas fuera del archivo exportado) | I102: Aprobado con notificación (Factura electrónica, Recibido) | J102: Presente en el auxiliar (el archivo no trae columna de estado; se infiere Contabilizado) | K102: El lado proveedor + retenciones coincide exacto con la DIAN, pero las líneas de gasto/IVA no están completas en el Journal exportado (el archivo se corta en la fila 16.383); no se puede confirmar la suma de conceptos. | L102: — | M102: INFORMACIÓN INSUFICIENTE | N102: DIAN | O102: 001-FSC-00011384 | P102: 7214, 8247 | Q102: referencia | R102: No (gasto/IVA cortado en la exportación)
A103: DISTRIBUIDORA MAYORISTA LIMITADA | B103: 800239989 | C103: DMFE833 | D103: No disponible | E103: 17284533 | F103: No encontrado | G103: =IF(AND(ISNUMBER(E103),ISNUMBER(F103)),E103-F103,"No disponible") -> No disponible | H103: No disponible | I103: Aprobado con notificación (Factura electrónica, Recibido) | J103: Solo comprobantes de pago/legalización, sin causación | K103: El documento se cita en comprobantes que no lo causan (pago, legalización o anticipo), pero no hay un comprobante de causación para él. | L103: Revisar: 001-FSC-00011386, 001-NT-00012655 | M103: PENDIENTE | N103: DIAN | O103: 001-FSC-00011386, 001-NT-00012655 | Q103: referencia | R103: No disponible
A104: DISTRIBUIDORA MAYORISTA LIMITADA | B104: 800239989 | C104: DMFE835 | D104: 22050501 PROVEEDORES NACIONALES; 23652507 SERVICIOS GENERALES (DECLARANTES) 4% | E104: 936203 | F104: 936203 | G104: =IF(AND(ISNUMBER(E104),ISNUMBER(F104)),E104-F104,"No disponible") -> 0 | H104: Retenciones (crédito): 37,448.00 | Gasto/otros: No disponible (líneas fuera del archivo exportado) | I104: Aprobado con notificación (Factura electrónica, Recibido) | J104: Presente en el auxiliar (el archivo no trae columna de estado; se infiere Contabilizado) | K104: El lado proveedor + retenciones coincide exacto con la DIAN, pero las líneas de gasto/IVA no están completas en el Journal exportado (el archivo se corta en la fila 16.383); no se puede confirmar la suma de conceptos. | L104: — | M104: INFORMACIÓN INSUFICIENTE | N104: DIAN | O104: 001-FSC-00011417 | P104: 7219, 8248 | Q104: referencia | R104: No (gasto/IVA cortado en la exportación)
A105: DISTRIBUIDORA MAYORISTA LIMITADA | B105: 800239989 | C105: DMFE837 | D105: 22050501 PROVEEDORES NACIONALES; 23652507 SERVICIOS GENERALES (DECLARANTES) 4% | E105: 1524400 | F105: 1524400 | G105: =IF(AND(ISNUMBER(E105),ISNUMBER(F105)),E105-F105,"No disponible") -> 0 | H105: Retenciones (crédito): 60,976.00 | Gasto/otros: No disponible (líneas fuera del archivo exportado) | I105: Aprobado con notificación (Factura electrónica, Recibido) | J105: Presente en el auxiliar (el archivo no trae columna de estado; se infiere Contabilizado) | K105: El lado proveedor + retenciones coincide exacto con la DIAN, pero las líneas de gasto/IVA no están completas en el Journal exportado (el archivo se corta en la fila 16.383); no se puede confirmar la suma de conceptos. | L105: — | M105: INFORMACIÓN INSUFICIENTE | N105: DIAN | O105: 001-FSC-00011460 | P105: 7221, 8249 | Q105: referencia | R105: No (gasto/IVA cortado en la exportación)
A106: DISTRIBUIDORA MAYORISTA LIMITADA | B106: 800239989 | C106: DMFE838 | D106: 22050501 PROVEEDORES NACIONALES; 23652501 TRANSPORTE 1% | E106: 17182828 | F106: 17182828 | G106: =IF(AND(ISNUMBER(E106),ISNUMBER(F106)),E106-F106,"No disponible") -> 0 | H106: Retenciones (crédito): 171,828.00 | Gasto/otros: No disponible (líneas fuera del archivo exportado) | I106: Aprobado con notificación (Factura electrónica, Recibido) | J106: Presente en el auxiliar (el archivo no trae columna de estado; se infiere Contabilizado) | K106: El lado proveedor + retenciones coincide exacto con la DIAN, pero las líneas de gasto/IVA no están completas en el Journal exportado (el archivo se corta en la fila 16.383); no se puede confirmar la suma de conceptos. | L106: — | M106: INFORMACIÓN INSUFICIENTE | N106: DIAN | O106: 001-FSC-00011536 | P106: 7226, 8185 | Q106: referencia | R106: No (gasto/IVA cortado en la exportación)
...

Sheet Pendientes de revisión manual
A1: Nombre del tercero | B1: NIT o identificación | C1: Número del documento | D1: Cuenta contable y auxiliar | E1: Valor total según la DIAN | F1: Valor total sumado en el Journal | G1: Diferencia (DIAN − Journal) | H1: Desglose de conceptos contables | I1: Estado en la DIAN | J1: Estado en el Journal | K1: Motivo por el cual queda pendiente | L1: Observaciones para revisión manual | M1: Clasificación | N1: Origen | O1: Comprobante(s) Journal | P1: Fila(s) en el Journal | Q1: Método de cruce | R1: Lado gasto/IVA completo en el Journal
A2: ACEVEDO JOSE NORBEY | B2: 6137792 | C2: NDSE1703 | D2: 23359501 OTROS; 23652507 SERVICIOS GENERALES (DECLARANTES) 4%; 23680203 DEMAS ACTIVIDADES SERVICIOS 10 X 1000 | E2: 289000 | F2: 289000 | G2: =IF(AND(ISNUMBER(E2),ISNUMBER(F2)),E2-F2,"No disponible") -> 0 | H2: Retenciones (crédito): 14,450.00 | Gasto/otros: No disponible (líneas fuera del archivo exportado) | I2: Aprobado con notificación (Documento soporte con no obligados, Emitido) | J2: Presente en el auxiliar (el archivo no trae columna de estado; se infiere Contabilizado) | K2: El lado proveedor + retenciones coincide exacto con la DIAN, pero las líneas de gasto/IVA no están completas en el Journal exportado (el archivo se corta en la fila 16.383); no se puede confirmar la suma de conceptos. | L2: — | M2: INFORMACIÓN INSUFICIENTE | N2: DIAN | O2: 001-DSE-00001703 | P2: 7510, 8236, 9198 | Q2: número del comprobante | R2: No (gasto/IVA cortado en la exportación)
A3: ADOCCIDENTE S.A.S. | B3: 805010086 | C3: FE1043 | D3: 23359501 OTROS; 23652507 SERVICIOS GENERALES (DECLARANTES) 4%; 23653002 BIENES INMUEBLES 3,5%; 24081513 IVA TRANSITORIO SERVICIOS 19% | E3: 17074120 | F3: 17074120 | G3: =IF(AND(ISNUMBER(E3),ISNUMBER(F3)),E3-F3,"No disponible") -> 0 | H3: IVA: 2,726,120.00 | Retenciones (crédito): 523,680.00 | Gasto/otros: No disponible (líneas fuera del archivo exportado) | I3: Aprobado con notificación (Factura electrónica, Recibido) | J3: Presente en el auxiliar (el archivo no trae columna de estado; se infiere Contabilizado) | K3: El lado proveedor + retenciones coincide exacto con la DIAN, pero las líneas de gasto/IVA no están completas en el Journal exportado (el archivo se corta en la fila 16.383); no se puede confirmar la suma de conceptos. | L3: — | M3: INFORMACIÓN INSUFICIENTE | N3: DIAN | O3: 001-FSC-00011343 | P3: 7642, 8252, 8326, 11263 | Q3: referencia | R3: No (gasto/IVA cortado en la exportación)
A4: AEROVIAS DE INTEGRACION REGIONAL S.A. | B4: 890704196 | C4: A3933 | D4: 23354501 TRANSPORTES, FLETES Y ACARREOS | E4: 939272 | F4: 939272 | G4: =IF(AND(ISNUMBER(E4),ISNUMBER(F4)),E4-F4,"No disponible") -> 0 | H4: Retenciones (crédito): 0.00 | Gasto/otros: No disponible (líneas fuera del archivo exportado) | I4: Aprobado con notificación (Nota de crédito electrónica, Recibido) | J4: Presente en el auxiliar (el archivo no trae columna de estado; se infiere Contabilizado) | K4: El lado proveedor + retenciones coincide exacto con la DIAN, pero las líneas de gasto/IVA no están completas en el Journal exportado (el archivo se corta en la fila 16.383); no se puede confirmar la suma de conceptos. | L4: La descripción del comprobante menciona ANULACIÓN: confirmar que no esté anulado. | M4: INFORMACIÓN INSUFICIENTE | N4: DIAN | O4: 001-NT-00012697 | P4: 7357 | Q4: texto/descripción | R4: No (gasto/IVA cortado en la exportación)
A5: AEROVIAS DE INTEGRACION REGIONAL S.A. | B5: 890704196 | C5: SPC44755 | D5: 23354501 TRANSPORTES, FLETES Y ACARREOS | E5: 13701380 | F5: 13701380 | G5: =IF(AND(ISNUMBER(E5),ISNUMBER(F5)),E5-F5,"No disponible") -> 0 | H5: Retenciones (crédito): 0.00 | Gasto/otros: No disponible (líneas fuera del archivo exportado) | I5: Aprobado con notificación (Factura electrónica, Recibido) | J5: Presente en el auxiliar (el archivo no trae columna de estado; se infiere Contabilizado) | K5: El lado proveedor + retenciones coincide exacto con la DIAN, pero las líneas de gasto/IVA no están completas en el Journal exportado (el archivo se corta en la fila 16.383); no se puede confirmar la suma de conceptos. | L5: — | M5: INFORMACIÓN INSUFICIENTE | N5: DIAN | O5: 001-FSC-00011436 | P5: 7353 | Q5: referencia | R5: No (gasto/IVA cortado en la exportación)
A6: AEROVIAS DE INTEGRACION REGIONAL S.A. | B6: 890704196 | C6: SPC45219 | D6: 23354501 TRANSPORTES, FLETES Y ACARREOS | E6: 4535050 | F6: 4535050 | G6: =IF(AND(ISNUMBER(E6),ISNUMBER(F6)),E6-F6,"No disponible") -> 0 | H6: Retenciones (crédito): 0.00 | Gasto/otros: No disponible (líneas fuera del archivo exportado) | I6: Aprobado con notificación (Factura electrónica, Recibido) | J6: Presente en el auxiliar (el archivo no trae columna de estado; se infiere Contabilizado) | K6: El lado proveedor + retenciones coincide exacto con la DIAN, pero las líneas de gasto/IVA no están completas en el Journal exportado (el archivo se corta en la fila 16.383); no se puede confirmar la suma de conceptos. | L6: — | M6: INFORMACIÓN INSUFICIENTE | N6: DIAN | O6: 001-FSC-00011580 | P6: 7356 | Q6: referencia | R6: No (gasto/IVA cortado en la exportación)
A7: AEROVIAS DE INTEGRACIÓN REGIONAL S.A. | B7: 890704196 | C7: EFCC4800912 | D7: 23354501 TRANSPORTES, FLETES Y ACARREOS; 24081513 IVA TRANSITORIO SERVICIOS 19% | E7: 3317339 | F7: 3317399 | G7: =IF(AND(ISNUMBER(E7),ISNUMBER(F7)),E7-F7,"No disponible") -> -60 | H7: IVA: 521,750.00 | Retenciones (crédito): 0.00 | Gasto/otros: No disponible (líneas fuera del archivo exportado) | I7: Aprobado con notificación (Documento equivalente - Transporte aéreo de pasajeros, Recibido) | J7: Presente en el auxiliar (el archivo no trae columna de estado; se infiere Contabilizado) | K7: El lado proveedor + retenciones del Journal no coincide con el total de la DIAN. | L7: — | M7: PENDIENTE | N7: DIAN | O7: 001-FSC-00011488 | P7: 7354, 11339 | Q7: referencia | R7: No (gasto/IVA cortado en la exportación)
A8: AEROVIAS DE INTEGRACIÓN REGIONAL S.A. | B8: 890704196 | C8: EFCC4858340 | D8: No disponible | E8: 417940 | F8: No encontrado | G8: =IF(AND(ISNUMBER(E8),ISNUMBER(F8)),E8-F8,"No disponible") -> No disponible | H8: No disponible | I8: Aprobado con notificación (Documento equivalente - Transporte aéreo de pasajeros, Recibido) | J8: No encontrado | K8: No se encontró el documento en el Journal (el tercero sí tiene otros movimientos). | L8: El tercero aparece en el Journal pero ninguna línea cita este folio ni coincide su valor. | M8: PENDIENTE | N8: DIAN | O8: No encontrado | Q8: No encontrado | R8: No disponible
A9: AEROVIAS DEL CONTINENTE AMERICANO, S.A. AVIANCA - COLOMBIA | B9: 890100577 | C9: TQT26949290 | D9: 23359501 OTROS; 24081513 IVA TRANSITORIO SERVICIOS 19% | E9: 553160 | F9: 553160 | G9: =IF(AND(ISNUMBER(E9),ISNUMBER(F9)),E9-F9,"No disponible") -> 0 | H9: IVA: 84,360.00 | Retenciones (crédito): 0.00 | Gasto/otros: No disponible (líneas fuera del archivo exportado) | I9: Aprobado con notificación (Factura electrónica, Recibido) | J9: Presente en el auxiliar (el archivo no trae columna de estado; se infiere Contabilizado) | K9: El lado proveedor + retenciones coincide exacto con la DIAN, pero las líneas de gasto/IVA no están completas en el Journal exportado (el archivo se corta en la fila 16.383); no se puede confirmar la suma de conceptos. | L9: — | M9: INFORMACIÓN INSUFICIENTE | N9: DIAN | O9: 001-FSC-00011450 | P9: 7747, 11304 | Q9: referencia | R9: No (gasto/IVA cortado en la exportación)
A10: AGENCIA DE ADUANAS SANTIAGO RICO & BAÑOL LTDA. NIVEL 4 | B10: 827000059 | C10: SRFE804 | D10: 23359501 OTROS; 23652507 SERVICIOS GENERALES (DECLARANTES) 4% | E10: 450000 | F10: 450000 | G10: =IF(AND(ISNUMBER(E10),ISNUMBER(F10)),E10-F10,"No disponible") -> 0 | H10: Retenciones (crédito): 18,000.00 | Gasto/otros: No disponible (líneas fuera del archivo exportado) | I10: Aprobado con notificación (Factura electrónica, Recibido) | J10: Presente en el auxiliar (el archivo no trae columna de estado; se infiere Contabilizado) | K10: El lado proveedor + retenciones coincide exacto con la DIAN, pero las líneas de gasto/IVA no están completas en el Journal exportado (el archivo se corta en la fila 16.383); no se puede confirmar la suma de conceptos. | L10: — | M10: INFORMACIÓN INSUFICIENTE | N10: DIAN | O10: 001-FSC-00011385 | P10: 7680, 8256 | Q10: referencia | R10: No (gasto/IVA cortado en la exportación)
A11: AGENCIA DE ADUANAS SANTIAGO RICO & BAÑOL LTDA. NIVEL 4 | B11: 827000059 | C11: SRFE817 | D11: 23359501 OTROS; 23652507 SERVICIOS GENERALES (DECLARANTES) 4%; 26952001 PARA OPERACION | E11: 450000 | F11: 449999 | G11: =IF(AND(ISNUMBER(E11),ISNUMBER(F11)),E11-F11,"No disponible") -> 1 | H11: Otros conceptos: 449,999.00 | Retenciones (crédito): 18,000.00 | I11: Aprobado con notificación (Factura electrónica, Recibido) | J11: Presente en el auxiliar (el archivo no trae columna de estado; se infiere Contabilizado) | K11: La suma de los conceptos contables no coincide con el total de la DIAN. | L11: — | M11: PENDIENTE | N11: DIAN | O11: 001-CC-00023131 | P11: 7683, 8258, 12538 | Q11: referencia | R11: Sí
A12: ALMACEN LAS GEMELAS SAS | B12: 901849101 | C12: FE2169 | D12: 23359501 OTROS; 23654002 COMPRAS GENERALES 2,5%; 24081510 IVA TRANSITORIO COMPRAS 19% | E12: 792000.02 | F12: 792000 | G12: =IF(AND(ISNUMBER(E12),ISNUMBER(F12)),E12-F12,"No disponible") -> 0.02 | H12: IVA: 126,454.00 | Retenciones (crédito): 16,639.00 | Gasto/otros: No disponible (líneas fuera del archivo exportado) | I12: Aprobado con notificación (Factura electrónica, Recibido) | J12: Presente en el auxiliar (el archivo no trae columna de estado; se infiere Contabilizado) | K12: El lado proveedor + retenciones del Journal no coincide con el total de la DIAN. | L12: — | M12: PENDIENTE | N12: DIAN | O12: 001-FSC-00011456 | P12: 8028, 8415, 11207 | Q12: referencia | R12: No (gasto/IVA cortado en la exportación)
A13: ALMACENES ÉXITO S.A | B13: 890900608 | C13: RC06172758 | D13: 23359501 OTROS | E13: 37080 | F13: 37080 | G13: =IF(AND(ISNUMBER(E13),ISNUMBER(F13)),E13-F13,"No disponible") -> 0 | H13: Retenciones (crédito): 0.00 | Gasto/otros: No disponible (líneas fuera del archivo exportado) | I13: Aprobado con notificación (Factura electrónica, Recibido) | J13: Presente en el auxiliar (el archivo no trae columna de estado; se infiere Contabilizado) | K13: El lado proveedor + retenciones coincide exacto con la DIAN, pero las líneas de gasto/IVA no están completas en el Journal exportado (el archivo se corta en la fila 16.383); no se puede confirmar la suma de conceptos. | L13: — | M13: INFORMACIÓN INSUFICIENTE | N13: DIAN | O13: 001-FSC-00011592 | P13: 7822 | Q13: referencia | R13: No (gasto/IVA cortado en la exportación)
A14: ALMEIDA BACCA EDWARD ALEXANDER | B14: 16928075 | C14: FE681 | D14: No disponible | E14: 601985.3 | F14: No encontrado | G14: =IF(AND(ISNUMBER(E14),ISNUMBER(F14)),E14-F14,"No disponible") -> No disponible | H14: No disponible | I14: Aprobado con notificación (Factura electrónica, Recibido) | J14: No encontrado | K14: El tercero no aparece en el Journal. | L14: NIT sin movimientos en el archivo del Journal. | M14: PENDIENTE | N14: DIAN | O14: No encontrado | Q14: No encontrado | R14: No disponible
A15: ANILLANDO CALI LTDA | B15: 800038947 | C15: PFS10547 | D15: 22050501 PROVEEDORES NACIONALES; 24081510 IVA TRANSITORIO COMPRAS 19% | E15: 138900 | F15: 138900 | G15: =IF(AND(ISNUMBER(E15),ISNUMBER(F15)),E15-F15,"No disponible") -> 0 | H15: IVA: 22,177.00 | Retenciones (crédito): 0.00 | Gasto/otros: No disponible (líneas fuera del archivo exportado) | I15: Aprobado con notificación (Factura electrónica, Recibido) | J15: Presente en el auxiliar (el archivo no trae columna de estado; se infiere Contabilizado) | K15: El lado proveedor + retenciones coincide exacto con la DIAN, pero las líneas de gasto/IVA no están completas en el Journal exportado (el archivo se corta en la fila 16.383); no se puede confirmar la suma de conceptos. | L15: — | M15: INFORMACIÓN INSUFICIENTE | N15: DIAN | O15: 001-FSC-00011410 | P15: 7203, 11063 | Q15: referencia | R15: No (gasto/IVA cortado en la exportación)
A16: APONTE CASTILLO CARLOS DANIEL | B16: 1010204688 | C16: 422 | D16: 13309501 OTROS; 23359501 OTROS; 23654002 COMPRAS GENERALES 2,5%; 24081510 IVA TRANSITORIO COMPRAS 19% | E16: 6961500 | F16: 3553875 | G16: =IF(AND(ISNUMBER(E16),ISNUMBER(F16)),E16-F16,"No disponible") -> 3407625 | H16: IVA: 1,111,500.00 | Otros conceptos: -3,407,625.00 | Retenciones (crédito): 146,250.00 | Gasto/otros: No disponible (líneas fuera del archivo exportado) | I16: Aprobado con notificación (Factura electrónica, Recibido) | J16: Presente en el auxiliar (el archivo no trae columna de estado; se infiere Contabilizado) | K16: El lado proveedor + retenciones del Journal no coincide con el total de la DIAN. | L16: — | M16: PENDIENTE | N16: DIAN | O16: 001-FSC-00011398 | P16: 3306, 7373, 7374, 8332, 11047 | Q16: referencia | R16: No (gasto/IVA cortado en la exportación)
A17: AQUASISTEMAS DEL CARIBE S.A.S | B17: 802018827 | C17: FE232 | D17: 23359501 OTROS; 23654002 COMPRAS GENERALES 2,5% | E17: 561300 | F17: 561300 | G17: =IF(AND(ISNUMBER(E17),ISNUMBER(F17)),E17-F17,"No disponible") -> 0 | H17: Retenciones (crédito): 14,033.00 | Gasto/otros: No disponible (líneas fuera del archivo exportado) | I17: Aprobado con notificación (Factura electrónica, Recibido) | J17: Presente en el auxiliar (el archivo no trae columna de estado; se infiere Contabilizado) | K17: El lado proveedor + retenciones coincide exacto con la DIAN, pero las líneas de gasto/IVA no están completas en el Journal exportado (el archivo se corta en la fila 16.383); no se puede confirmar la suma de conceptos. | L17: — | M17: INFORMACIÓN INSUFICIENTE | N17: DIAN | O17: 001-FSC-00011582 | P17: 7637, 8367 | Q17: referencia | R17: No (gasto/IVA cortado en la exportación)
A18: ARIAS GLORIA PATRICIA | B18: 31411095 | C18: NDSE1700 | D18: 23359501 OTROS; 23654002 COMPRAS GENERALES 2,5%; 23680302 DEMAS ACTIVIDADES COMERCIALES 7,7 X 1000 | E18: 1620000 | F18: 1620000 | G18: =IF(AND(ISNUMBER(E18),ISNUMBER(F18)),E18-F18,"No disponible") -> 0 | H18: Retenciones (crédito): 52,974.00 | Gasto/otros: No disponible (líneas fuera del archivo exportado) | I18: Aprobado con notificación (Documento soporte con no obligados, Emitido) | J18: Presente en el auxiliar (el archivo no trae columna de estado; se infiere Contabilizado) | K18: El lado proveedor + retenciones coincide exacto con la DIAN, pero las líneas de gasto/IVA no están completas en el Journal exportado (el archivo se corta en la fila 16.383); no se puede confirmar la suma de conceptos. | L18: — | M18: INFORMACIÓN INSUFICIENTE | N18: DIAN | O18: 001-DSE-00001700 | P18: 7458, 8344, 9261 | Q18: referencia | R18: No (gasto/IVA cortado en la exportación)
A19: ARIAS GLORIA PATRICIA | B19: 31411095 | C19: NDSE1708 | D19: 23359501 OTROS; 23654002 COMPRAS GENERALES 2,5%; 23680203 DEMAS ACTIVIDADES SERVICIOS 10 X 1000 | E19: 3000000 | F19: 3000000 | G19: =IF(AND(ISNUMBER(E19),ISNUMBER(F19)),E19-F19,"No disponible") -> 0 | H19: Retenciones (crédito): 105,000.00 | Gasto/otros: No disponible (líneas fuera del archivo exportado) | I19: Aprobado con notificación (Documento soporte con no obligados, Emitido) | J19: Presente en el auxiliar (el archivo no trae columna de estado; se infiere Contabilizado) | K19: El lado proveedor + retenciones coincide exacto con la DIAN, pero las líneas de gasto/IVA no están completas en el Journal exportado (el archivo se corta en la fila 16.383); no se puede confirmar la suma de conceptos. | L19: — | M19: INFORMACIÓN INSUFICIENTE | N19: DIAN | O19: 001-DSE-00001708 | P19: 7460, 7461, 8345, 9195 | Q19: referencia | R19: No (gasto/IVA cortado en la exportación)
A20: ARIAS GLORIA PATRICIA | B20: 31411095 | C20: NDSE1734 | D20: 23359501 OTROS; 23652507 SERVICIOS GENERALES (DECLARANTES) 4%; 23680203 DEMAS ACTIVIDADES SERVICIOS 10 X 1000; 51055101 DOTACION Y SUMINISTRO A TRABAJADORES | E20: 636500 | F20: 636500 | G20: =IF(AND(ISNUMBER(E20),ISNUMBER(F20)),E20-F20,"No disponible") -> 0 | H20: Gastos: 38,000.00 | Retenciones (crédito): 31,825.00 | Gasto/otros: No disponible (líneas fuera del archivo exportado) | I20: Aprobado con notificación (Documento soporte con no obligados, Emitido) | J20: Presente en el auxiliar (el archivo no trae columna de estado; se infiere Contabilizado) | K20: El lado proveedor + retenciones coincide exacto con la DIAN, pero las líneas de gasto/IVA no están completas en el Journal exportado (el archivo se corta en la fila 16.383); no se puede confirmar la suma de conceptos. | L20: — | M20: INFORMACIÓN INSUFICIENTE | N20: DIAN | O20: 001-DSE-00001734 | P20: 7464, 8234, 9196, 16105 | Q20: referencia | R20: No (gasto/IVA cortado en la exportación)
A21: AZUL RESTAURANT AIRPORT | B21: 79308344 | C21: PAZ6314 | D21: 23359501 OTROS | E21: 24000 | F21: 24000 | G21: =IF(AND(ISNUMBER(E21),ISNUMBER(F21)),E21-F21,"No disponible") -> 0 | H21: Retenciones (crédito): 0.00 | Gasto/otros: No disponible (líneas fuera del archivo exportado) | I21: Aprobado con notificación (Factura electrónica, Recibido) | J21: Presente en el auxiliar (el archivo no trae columna de estado; se infiere Contabilizado) | K21: Coincide el NIT y el valor exacto, pero ninguna línea del Journal cita el número del documento; no se puede identificar con certeza. | L21: — | M21: INFORMACIÓN INSUFICIENTE | N21: DIAN | O21: 001-FSC-00011438 | P21: 7540 | Q21: NIT + valor (sin folio) | R21: No (gasto/IVA cortado en la exportación)
A22: AZUL RESTAURANT AIRPORT | B22: 79308344 | C22: PAZ6315 | D22: 23359501 OTROS | E22: 26000 | F22: 26000 | G22: =IF(AND(ISNUMBER(E22),ISNUMBER(F22)),E22-F22,"No disponible") -> 0 | H22: Retenciones (crédito): 0.00 | Gasto/otros: No disponible (líneas fuera del archivo exportado) | I22: Aprobado con notificación (Factura electrónica, Recibido) | J22: Presente en el auxiliar (el archivo no trae columna de estado; se infiere Contabilizado) | K22: El lado proveedor + retenciones coincide exacto con la DIAN, pero las líneas de gasto/IVA no están completas en el Journal exportado (el archivo se corta en la fila 16.383); no se puede confirmar la suma de conceptos. | L22: — | M22: INFORMACIÓN INSUFICIENTE | N22: DIAN | O22: 001-FSC-00011482 | P22: 7545 | Q22: referencia | R22: No (gasto/IVA cortado en la exportación)
A23: AZUL RESTAURANT AIRPORT | B23: 79308344 | C23: PAZ6316 | D23: No disponible | E23: 10000 | F23: No encontrado | G23: =IF(AND(ISNUMBER(E23),ISNUMBER(F23)),E23-F23,"No disponible") -> No disponible | H23: No disponible | I23: Aprobado con notificación (Factura electrónica, Recibido) | J23: No encontrado | K23: No se encontró el documento en el Journal (el tercero sí tiene otros movimientos). | L23: El tercero aparece en el Journal pero ninguna línea cita este folio ni coincide su valor. | M23: PENDIENTE | N23: DIAN | O23: No encontrado | Q23: No encontrado | R23: No disponible
A24: BAL STUDIO SAS | B24: 901986829 | C24: FE2458 | D24: 22050501 PROVEEDORES NACIONALES; 23670501 IVA RET. COMPRAS RC 15%; 24081513 IVA TRANSITORIO SERVICIOS 19% | E24: 2023000 | F24: 2023000 | G24: =IF(AND(ISNUMBER(E24),ISNUMBER(F24)),E24-F24,"No disponible") -> 0 | H24: IVA: 323,000.00 | Retenciones (crédito): 48,450.00 | Gasto/otros: No disponible (líneas fuera del archivo exportado) | I24: Aprobado con notificación (Factura electrónica, Recibido) | J24: Presente en el auxiliar (el archivo no trae columna de estado; se infiere Contabilizado) | K24: El lado proveedor + retenciones coincide exacto con la DIAN, pero las líneas de gasto/IVA no están completas en el Journal exportado (el archivo se corta en la fila 16.383); no se puede confirmar la suma de conceptos. | L24: — | M24: INFORMACIÓN INSUFICIENTE | N24: DIAN | O24: 001-FSC-00011483 | P24: 7250, 9156, 11501 | Q24: referencia | R24: No (gasto/IVA cortado en la exportación)
A25: BBVA SEGUROS COLOMBIA S.A. | B25: 800226098 | C25: FEAG1134986 | D25: 23359501 OTROS; 24081513 IVA TRANSITORIO SERVICIOS 19% | E25: 178364 | F25: 178364 | G25: =IF(AND(ISNUMBER(E25),ISNUMBER(F25)),E25-F25,"No disponible") -> 0 | H25: IVA: 28,478.00 | Retenciones (crédito): 0.00 | Gasto/otros: No disponible (líneas fuera del archivo exportado) | I25: Aprobado con notificación (Factura electrónica, Recibido) | J25: Presente en el auxiliar (el archivo no trae columna de estado; se infiere Contabilizado) | K25: El lado proveedor + retenciones coincide exacto con la DIAN, pero las líneas de gasto/IVA no están completas en el Journal exportado (el archivo se corta en la fila 16.383); no se puede confirmar la suma de conceptos. | L25: — | M25: INFORMACIÓN INSUFICIENTE | N25: DIAN | O25: 001-FSC-00011380 | P25: 7588, 11253 | Q25: referencia | R25: No (gasto/IVA cortado en la exportación)
A26: BENEMERITO CUERPO DE BOMBEROS VOLUNTARIOS DE CALI | B26: 890399000 | C26: FK72753 | D26: 23359501 OTROS; 24081513 IVA TRANSITORIO SERVICIOS 19% | E26: 942994 | F26: 942994 | G26: =IF(AND(ISNUMBER(E26),ISNUMBER(F26)),E26-F26,"No disponible") -> 0 | H26: IVA: 150,562.00 | Retenciones (crédito): 0.00 | Gasto/otros: No disponible (líneas fuera del archivo exportado) | I26: Aprobado con notificación (Factura electrónica, Recibido) | J26: Presente en el auxiliar (el archivo no trae columna de estado; se infiere Contabilizado) | K26: El lado proveedor + retenciones coincide exacto con la DIAN, pero las líneas de gasto/IVA no están completas en el Journal exportado (el archivo se corta en la fila 16.383); no se puede confirmar la suma de conceptos. | L26: — | M26: INFORMACIÓN INSUFICIENTE | N26: DIAN | O26: 001-FSC-00011563 | P26: 7799, 11332 | Q26: referencia | R26: No (gasto/IVA cortado en la exportación)
A27: BERMUDEZ RAMIREZ EUCARIO | B27: 16752920 | C27: NDSE1709 | D27: 22050501 PROVEEDORES NACIONALES; 23654002 COMPRAS GENERALES 2,5%; 23680302 DEMAS ACTIVIDADES COMERCIALES 7,7 X 1000 | E27: 11480000 | F27: 11480000 | G27: =IF(AND(ISNUMBER(E27),ISNUMBER(F27)),E27-F27,"No disponible") -> 0 | H27: Retenciones (crédito): 375,396.00 | Gasto/otros: No disponible (líneas fuera del archivo exportado) | I27: Aprobado con notificación (Documento soporte con no obligados, Emitido) | J27: Presente en el auxiliar (el archivo no trae columna de estado; se infiere Contabilizado) | K27: El lado proveedor + retenciones coincide exacto con la DIAN, pero las líneas de gasto/IVA no están completas en el Journal exportado (el archivo se corta en la fila 16.383); no se puede confirmar la suma de conceptos. | L27: — | M27: INFORMACIÓN INSUFICIENTE | N27: DIAN | O27: 001-DSE-00001709 | P27: 7195, 8335, 9255 | Q27: referencia | R27: No (gasto/IVA cortado en la exportación)
A28: BERNARDA VALENCIA MOYA | B28: 29951774 | C28: FEBV2769 | D28: 23359502 CUENTA PUENTE CAJA MENOR | E28: 20000 | F28: 20000 | G28: =IF(AND(ISNUMBER(E28),ISNUMBER(F28)),E28-F28,"No disponible") -> 0 | H28: Retenciones (crédito): 0.00 | Gasto/otros: No disponible (líneas fuera del archivo exportado) | I28: Aprobado con notificación (Factura electrónica, Recibido) | J28: Presente en el auxiliar (el archivo no trae columna de estado; se infiere Contabilizado) | K28: El lado proveedor + retenciones coincide exacto con la DIAN, pero las líneas de gasto/IVA no están completas en el Journal exportado (el archivo se corta en la fila 16.383); no se puede confirmar la suma de conceptos. | L28: — | M28: INFORMACIÓN INSUFICIENTE | N28: DIAN | O28: 001-FSC-00011557 | P28: 8084 | Q28: referencia | R28: No (gasto/IVA cortado en la exportación)
A29: BERRIO ARIAS JUAN FERNANDO | B29: 7563061 | C29: NDSE1733 | D29: 23359501 OTROS; 23652507 SERVICIOS GENERALES (DECLARANTES) 4% | E29: 145000 | F29: 145000 | G29: =IF(AND(ISNUMBER(E29),ISNUMBER(F29)),E29-F29,"No disponible") -> 0 | H29: Retenciones (crédito): 5,800.00 | Gasto/otros: No disponible (líneas fuera del archivo exportado) | I29: Aprobado con notificación (Documento soporte con no obligados, Emitido) | J29: Presente en el auxiliar (el archivo no trae columna de estado; se infiere Contabilizado) | K29: El lado proveedor + retenciones coincide exacto con la DIAN, pero las líneas de gasto/IVA no están completas en el Journal exportado (el archivo se corta en la fila 16.383); no se puede confirmar la suma de conceptos. | L29: — | M29: INFORMACIÓN INSUFICIENTE | N29: DIAN | O29: 001-DSE-00001733 | P29: 7538, 8238 | Q29: número del comprobante | R29: No (gasto/IVA cortado en la exportación)
A30: BOLD.CO S.A.S | B30: 901281572 | C30: FEC8613219 | D30: No disponible | E30: 137076.57 | F30: No encontrado | G30: =IF(AND(ISNUMBER(E30),ISNUMBER(F30)),E30-F30,"No disponible") -> No disponible | H30: No disponible | I30: Aprobado con notificación (Factura electrónica, Recibido) | J30: No encontrado | K30: No se encontró el documento en el Journal (el tercero sí tiene otros movimientos). | L30: El tercero aparece en el Journal pero ninguna línea cita este folio ni coincide su valor. | M30: PENDIENTE | N30: DIAN | O30: No encontrado | Q30: No encontrado | R30: No disponible
A31: BUENO ALVAREZ WILLIAM ANDRES | B31: 1113519268 | C31: NDSE1704 | D31: 23359501 OTROS | E31: 1730560 | F31: 1730560 | G31: =IF(AND(ISNUMBER(E31),ISNUMBER(F31)),E31-F31,"No disponible") -> 0 | H31: Retenciones (crédito): 0.00 | Gasto/otros: No disponible (líneas fuera del archivo exportado) | I31: Aprobado con notificación (Documento soporte con no obligados, Emitido) | J31: Presente en el auxiliar (el archivo no trae columna de estado; se infiere Contabilizado) | K31: El lado proveedor + retenciones coincide exacto con la DIAN, pero las líneas de gasto/IVA no están completas en el Journal exportado (el archivo se corta en la fila 16.383); no se puede confirmar la suma de conceptos. | L31: — | M31: INFORMACIÓN INSUFICIENTE | N31: DIAN | O31: 001-DSE-00001704 | P31: 7387 | Q31: referencia | R31: No (gasto/IVA cortado en la exportación)
A32: BUENO ALVAREZ WILLIAM ANDRES | B32: 1113519268 | C32: NDSE1705 | D32: 23359501 OTROS | E32: 1732000 | F32: 1732000 | G32: =IF(AND(ISNUMBER(E32),ISNUMBER(F32)),E32-F32,"No disponible") -> 0 | H32: Retenciones (crédito): 0.00 | Gasto/otros: No disponible (líneas fuera del archivo exportado) | I32: Aprobado con notificación (Documento soporte con no obligados, Emitido) | J32: Presente en el auxiliar (el archivo no trae columna de estado; se infiere Contabilizado) | K32: El lado proveedor + retenciones coincide exacto con la DIAN, pero las líneas de gasto/IVA no están completas en el Journal exportado (el archivo se corta en la fila 16.383); no se puede confirmar la suma de conceptos. | L32: — | M32: INFORMACIÓN INSUFICIENTE | N32: DIAN | O32: 001-DSE-00001705 | P32: 7388 | Q32: referencia | R32: No (gasto/IVA cortado en la exportación)
A33: CABRALES SALGADO ROLANDO ALBERTO | B33: 73571583 | C33: NDSE1724 | D33: 23359501 OTROS | E33: 79000 | F33: 79000 | G33: =IF(AND(ISNUMBER(E33),ISNUMBER(F33)),E33-F33,"No disponible") -> 0 | H33: Retenciones (crédito): 0.00 | Gasto/otros: No disponible (líneas fuera del archivo exportado) | I33: Aprobado con notificación (Documento soporte con no obligados, Emitido) | J33: Presente en el auxiliar (el archivo no trae columna de estado; se infiere Contabilizado) | K33: El lado proveedor + retenciones coincide exacto con la DIAN, pero las líneas de gasto/IVA no están completas en el Journal exportado (el archivo se corta en la fila 16.383); no se puede confirmar la suma de conceptos. | L33: — | M33: INFORMACIÓN INSUFICIENTE | N33: DIAN | O33: 001-DSE-00001724 | P33: 7530 | Q33: referencia | R33: No (gasto/IVA cortado en la exportación)
A34: CABRALES SALGADO ROLANDO ALBERTO | B34: 73571583 | C34: NDSE1725 | D34: 23359501 OTROS | E34: 119000 | F34: 119000 | G34: =IF(AND(ISNUMBER(E34),ISNUMBER(F34)),E34-F34,"No disponible") -> 0 | H34: Retenciones (crédito): 0.00 | Gasto/otros: No disponible (líneas fuera del archivo exportado) | I34: Aprobado con notificación (Documento soporte con no obligados, Emitido) | J34: Presente en el auxiliar (el archivo no trae columna de estado; se infiere Contabilizado) | K34: El lado proveedor + retenciones coincide exacto con la DIAN, pero las líneas de gasto/IVA no están completas en el Journal exportado (el archivo se corta en la fila 16.383); no se puede confirmar la suma de conceptos. | L34: — | M34: INFORMACIÓN INSUFICIENTE | N34: DIAN | O34: 001-DSE-00001725 | P34: 7531 | Q34: referencia | R34: No (gasto/IVA cortado en la exportación)
A35: CABRALES SALGADO ROLANDO ALBERTO | B35: 73571583 | C35: NDSE1729 | D35: 23359501 OTROS | E35: 316000 | F35: 316000 | G35: =IF(AND(ISNUMBER(E35),ISNUMBER(F35)),E35-F35,"No disponible") -> 0 | H35: Retenciones (crédito): 0.00 | Gasto/otros: No disponible (líneas fuera del archivo exportado) | I35: Aprobado con notificación (Documento soporte con no obligados, Emitido) | J35: Presente en el auxiliar (el archivo no trae columna de estado; se infiere Contabilizado) | K35: El lado proveedor + retenciones coincide exacto con la DIAN, pero las líneas de gasto/IVA no están completas en el Journal exportado (el archivo se corta en la fila 16.383); no se puede confirmar la suma de conceptos. | L35: — | M35: INFORMACIÓN INSUFICIENTE | N35: DIAN | O35: 001-DSE-00001729 | P35: 7532 | Q35: referencia | R35: No (gasto/IVA cortado en la exportación)
A36: CALVACHE JARAMILLO LUIS MIGUEL | B36: 1144093853 | C36: NDSE1715 | D36: 23359501 OTROS | E36: 2400 | F36: 2400 | G36: =IF(AND(ISNUMBER(E36),ISNUMBER(F36)),E36-F36,"No disponible") -> 0 | H36: Retenciones (crédito): 0.00 | Gasto/otros: No disponible (líneas fuera del archivo exportado) | I36: Aprobado con notificación (Documento soporte con no obligados, Emitido) | J36: Presente en el auxiliar (el archivo no trae columna de estado; se infiere Contabilizado) | K36: El lado proveedor + retenciones coincide exacto con la DIAN, pero las líneas de gasto/IVA no están completas en el Journal exportado (el archivo se corta en la fila 16.383); no se puede confirmar la suma de conceptos. | L36: — | M36: INFORMACIÓN INSUFICIENTE | N36: DIAN | O36: 001-DSE-00001715 | P36: 7401 | Q36: número del comprobante | R36: No (gasto/IVA cortado en la exportación)
A37: CARTONES AMERICA S.A. CAME | B37: 860026759 | C37: 8200455422 | D37: 23359501 OTROS; 24081510 IVA TRANSITORIO COMPRAS 19% | E37: 6999152 | F37: 6999152 | G37: =IF(AND(ISNUMBER(E37),ISNUMBER(F37)),E37-F37,"No disponible") -> 0 | H37: IVA: 1,117,512.00 | Retenciones (crédito): 0.00 | Gasto/otros: No disponible (líneas fuera del archivo exportado) | I37: Aprobado con notificación (Factura electrónica, Recibido) | J37: Presente en el auxiliar (el archivo no trae columna de estado; se infiere Contabilizado) | K37: El lado proveedor + retenciones coincide exacto con la DIAN, pero las líneas de gasto/IVA no están completas en el Journal exportado (el archivo se corta en la fila 16.383); no se puede confirmar la suma de conceptos. | L37: — | M37: INFORMACIÓN INSUFICIENTE | N37: DIAN | O37: 001-FSC-00011382 | P37: 7729, 11114 | Q37: referencia | R37: No (gasto/IVA cortado en la exportación)
A38: CARVAJAL TECNOLOGIA Y SERVICIOS S.A.S. | B38: 890321151 | C38: CLOA105291184 | D38: 23359501 OTROS; 24081513 IVA TRANSITORIO SERVICIOS 19% | E38: 142949.94 | F38: 142950 | G38: =IF(AND(ISNUMBER(E38),ISNUMBER(F38)),E38-F38,"No disponible") -> -0.06 | H38: IVA: 22,824.00 | Retenciones (crédito): 0.00 | Gasto/otros: No disponible (líneas fuera del archivo exportado) | I38: Aprobado con notificación (Factura electrónica, Recibido) | J38: Presente en el auxiliar (el archivo no trae columna de estado; se infiere Contabilizado) | K38: El lado proveedor + retenciones del Journal no coincide con el total de la DIAN. | L38: — | M38: PENDIENTE | N38: DIAN | O38: 001-FSC-00011383 | P38: 7789, 11329 | Q38: referencia | R38: No (gasto/IVA cortado en la exportación)
A39: CASTANEDA VARGAS JULIAN | B39: 16917650 | C39: NDSE1736 | D39: 23359501 OTROS | E39: 133000 | F39: 133000 | G39: =IF(AND(ISNUMBER(E39),ISNUMBER(F39)),E39-F39,"No disponible") -> 0 | H39: Retenciones (crédito): 0.00 | Gasto/otros: No disponible (líneas fuera del archivo exportado) | I39: Aprobado con notificación (Documento soporte con no obligados, Emitido) | J39: Presente en el auxiliar (el archivo no trae columna de estado; se infiere Contabilizado) | K39: El lado proveedor + retenciones coincide exacto con la DIAN, pero las líneas de gasto/IVA no están completas en el Journal exportado (el archivo se corta en la fila 16.383); no se puede confirmar la suma de conceptos. | L39: — | M39: INFORMACIÓN INSUFICIENTE | N39: DIAN | O39: 001-DSE-00001736 | P39: 7454 | Q39: número del comprobante | R39: No (gasto/IVA cortado en la exportación)
A40: CESAR AUGUSTO GIRALDO HOYOS | B40: 16460791 | C40: FPDP7016 | D40: 23359501 OTROS; 24081510 IVA TRANSITORIO COMPRAS 19% | E40: 34000 | F40: 33999 | G40: =IF(AND(ISNUMBER(E40),ISNUMBER(F40)),E40-F40,"No disponible") -> 1 | H40: IVA: 5,428.00 | Retenciones (crédito): 0.00 | Gasto/otros: No disponible (líneas fuera del archivo exportado) | I40: Aprobado con notificación (Factura electrónica, Recibido) | J40: Presente en el auxiliar (el archivo no trae columna de estado; se infiere Contabilizado) | K40: El lado proveedor + retenciones del Journal no coincide con el total de la DIAN. | L40: — | M40: PENDIENTE | N40: DIAN | O40: 001-FSC-00011541 | P40: 7420, 11051 | Q40: referencia | R40: No (gasto/IVA cortado en la exportación)
A41: CHAVEZ ASPRILLA EDWARD ANDRES | B41: 94410977 | C41: NDSE1713 | D41: 23359501 OTROS | E41: 450000 | F41: 450000 | G41: =IF(AND(ISNUMBER(E41),ISNUMBER(F41)),E41-F41,"No disponible") -> 0 | H41: Retenciones (crédito): 0.00 | Gasto/otros: No disponible (líneas fuera del archivo exportado) | I41: Aprobado con notificación (Documento soporte con no obligados, Emitido) | J41: Presente en el auxiliar (el archivo no trae columna de estado; se infiere Contabilizado) | K41: El lado proveedor + retenciones coincide exacto con la DIAN, pero las líneas de gasto/IVA no están completas en el Journal exportado (el archivo se corta en la fila 16.383); no se puede confirmar la suma de conceptos. | L41: — | M41: INFORMACIÓN INSUFICIENTE | N41: DIAN | O41: 001-DSE-00001713 | P41: 8047 | Q41: referencia | R41: No (gasto/IVA cortado en la exportación)
A42: CHRISTIAN CAMILO QUEVEDO OCHOA | B42: 1130588761 | C42: ETPC406 | D42: No disponible | E42: 28000 | F42: No encontrado | G42: =IF(AND(ISNUMBER(E42),ISNUMBER(F42)),E42-F42,"No disponible") -> No disponible | H42: No disponible | I42: Aprobado con notificación (Factura electrónica, Recibido) | J42: No encontrado | K42: El tercero no aparece en el Journal. | L42: NIT sin movimientos en el archivo del Journal. | M42: PENDIENTE | N42: DIAN | O42: No encontrado | Q42: No encontrado | R42: No disponible
A43: CHRISTIAN CAMILO QUEVEDO OCHOA | B43: 1130588761 | C43: ETPC418 | D43: No disponible | E43: 23000 | F43: No encontrado | G43: =IF(AND(ISNUMBER(E43),ISNUMBER(F43)),E43-F43,"No disponible") -> No disponible | H43: No disponible | I43: Aprobado con notificación (Factura electrónica, Recibido) | J43: No encontrado | K43: El tercero no aparece en el Journal. | L43: NIT sin movimientos en el archivo del Journal. | M43: PENDIENTE | N43: DIAN | O43: No encontrado | Q43: No encontrado | R43: No disponible
A44: CIMEX COLOMBIA S.A.S | B44: 800202146 | C44: 2FE84768 | D44: 23359501 OTROS | E44: 28000 | F44: 28000 | G44: =IF(AND(ISNUMBER(E44),ISNUMBER(F44)),E44-F44,"No disponible") -> 0 | H44: Retenciones (crédito): 0.00 | Gasto/otros: No disponible (líneas fuera del archivo exportado) | I44: Aprobado con notificación (Factura electrónica, Recibido) | J44: Presente en el auxiliar (el archivo no trae columna de estado; se infiere Contabilizado) | K44: Coincide el NIT y el valor exacto, pero ninguna línea del Journal cita el número del documento; no se puede identificar con certeza. | L44: — | M44: INFORMACIÓN INSUFICIENTE | N44: DIAN | O44: 001-FSC-00011490 | P44: 7581 | Q44: NIT + valor (sin folio) | R44: No (gasto/IVA cortado en la exportación)
A45: CIMEX COLOMBIA S.A.S | B45: 800202146 | C45: 2FE85515 | D45: 23359501 OTROS; 24081510 IVA TRANSITORIO COMPRAS 19% | E45: 60999.9 | F45: 61000 | G45: =IF(AND(ISNUMBER(E45),ISNUMBER(F45)),E45-F45,"No disponible") -> -0.1 | H45: IVA: 4,790.00 | Retenciones (crédito): 0.00 | Gasto/otros: No disponible (líneas fuera del archivo exportado) | I45: Aprobado con notificación (Factura electrónica, Recibido) | J45: Presente en el auxiliar (el archivo no trae columna de estado; se infiere Contabilizado) | K45: El lado proveedor + retenciones del Journal no coincide con el total de la DIAN. | L45: — | M45: PENDIENTE | N45: DIAN | O45: 001-FSC-00011547 | P45: 7583, 11073 | Q45: referencia | R45: No (gasto/IVA cortado en la exportación)
A46: CLINICA DEL COLON S A S | B46: 805019003 | C46: FEPC9504 | D46: 23359501 OTROS; 24081510 IVA TRANSITORIO COMPRAS 19%; 51058401 GASTOS MEDICOS Y DROGAS | E46: 418000 | F46: 418001 | G46: =IF(AND(ISNUMBER(E46),ISNUMBER(F46)),E46-F46,"No disponible") -> -1 | H46: IVA: 66,740.00 | Gastos: 351,261.00 | Retenciones (crédito): 0.00 | I46: Aprobado con notificación (Factura electrónica, Recibido) | J46: Presente en el auxiliar (el archivo no trae columna de estado; se infiere Contabilizado) | K46: La suma de los conceptos contables no coincide con el total de la DIAN. | L46: — | M46: PENDIENTE | N46: DIAN | O46: 001-FSC-00011514 | P46: 7651, 11098, 16192 | Q46: referencia | R46: Sí
A47: COEXITO S.A.S. | B47: 890300225 | C47: 129B89379 | D47: No disponible | E47: 15000 | F47: No encontrado | G47: =IF(AND(ISNUMBER(E47),ISNUMBER(F47)),E47-F47,"No disponible") -> No disponible | H47: No disponible | I47: Aprobado con notificación (Factura electrónica, Recibido) | J47: No encontrado | K47: El tercero no aparece en el Journal. | L47: NIT sin movimientos en el archivo del Journal. | M47: PENDIENTE | N47: DIAN | O47: No encontrado | Q47: No encontrado | R47: No disponible
A48: COEXITO S.A.S. | B48: 890300225 | C48: 129B92054 | D48: No disponible | E48: 10000 | F48: No encontrado | G48: =IF(AND(ISNUMBER(E48),ISNUMBER(F48)),E48-F48,"No disponible") -> No disponible | H48: No disponible | I48: Aprobado con notificación (Factura electrónica, Recibido) | J48: No encontrado | K48: El tercero no aparece en el Journal. | L48: NIT sin movimientos en el archivo del Journal. | M48: PENDIENTE | N48: DIAN | O48: No encontrado | Q48: No encontrado | R48: No disponible
A49: COLOMBIA TELECOMUNICACIONES S.A. E.S.P. BIC | B49: 830122566 | C49: BEC546849816 | D49: 23359501 OTROS; 24081513 IVA TRANSITORIO SERVICIOS 19% | E49: 21995 | F49: 21995 | G49: =IF(AND(ISNUMBER(E49),ISNUMBER(F49)),E49-F49,"No disponible") -> 0 | H49: IVA: 3,498.00 | Retenciones (crédito): 0.00 | Gasto/otros: No disponible (líneas fuera del archivo exportado) | I49: Aprobado con notificación (Factura electrónica, Recibido) | J49: Presente en el auxiliar (el archivo no trae columna de estado; se infiere Contabilizado) | K49: El lado proveedor + retenciones coincide exacto con la DIAN, pero las líneas de gasto/IVA no están completas en el Journal exportado (el archivo se corta en la fila 16.383); no se puede confirmar la suma de conceptos. | L49: — | M49: INFORMACIÓN INSUFICIENTE | N49: DIAN | O49: 001-FSC-00011434 | P49: 7703, 11291 | Q49: referencia | R49: No (gasto/IVA cortado en la exportación)
A50: COLOMBIA TELECOMUNICACIONES S.A. E.S.P. BIC | B50: 830122566 | C50: BEC546849819 | D50: 23359501 OTROS; 24081513 IVA TRANSITORIO SERVICIOS 19% | E50: 10996 | F50: 10996 | G50: =IF(AND(ISNUMBER(E50),ISNUMBER(F50)),E50-F50,"No disponible") -> 0 | H50: IVA: 1,756.00 | Retenciones (crédito): 0.00 | Gasto/otros: No disponible (líneas fuera del archivo exportado) | I50: Aprobado con notificación (Factura electrónica, Recibido) | J50: Presente en el auxiliar (el archivo no trae columna de estado; se infiere Contabilizado) | K50: Coincide el NIT y el valor exacto, pero ninguna línea del Journal cita el número del documento; no se puede identificar con certeza. | L50: — | M50: INFORMACIÓN INSUFICIENTE | N50: DIAN | O50: 001-FSC-00011435 | P50: 7704, 11292 | Q50: NIT + valor (sin folio) | R50: No (gasto/IVA cortado en la exportación)
A51: COLOMBIA TELECOMUNICACIONES S.A. E.S.P. BIC | B51: 830122566 | C51: BEC546850762 | D51: 23359501 OTROS; 24081513 IVA TRANSITORIO SERVICIOS 19% | E51: 44875 | F51: 44875 | G51: =IF(AND(ISNUMBER(E51),ISNUMBER(F51)),E51-F51,"No disponible") -> 0 | H51: IVA: 7,152.00 | Retenciones (crédito): 0.00 | Gasto/otros: No disponible (líneas fuera del archivo exportado) | I51: Aprobado con notificación (Factura electrónica, Recibido) | J51: Presente en el auxiliar (el archivo no trae columna de estado; se infiere Contabilizado) | K51: El lado proveedor + retenciones coincide exacto con la DIAN, pero las líneas de gasto/IVA no están completas en el Journal exportado (el archivo se corta en la fila 16.383); no se puede confirmar la suma de conceptos. | L51: — | M51: INFORMACIÓN INSUFICIENTE | N51: DIAN | O51: 001-FSC-00011428 | P51: 7697, 11285 | Q51: referencia | R51: No (gasto/IVA cortado en la exportación)
A52: COLOMBIA TELECOMUNICACIONES S.A. E.S.P. BIC | B52: 830122566 | C52: BEC546850764 | D52: 23359501 OTROS; 24081513 IVA TRANSITORIO SERVICIOS 19% | E52: 21995 | F52: 21995 | G52: =IF(AND(ISNUMBER(E52),ISNUMBER(F52)),E52-F52,"No disponible") -> 0 | H52: IVA: 3,498.00 | Retenciones (crédito): 0.00 | Gasto/otros: No disponible (líneas fuera del archivo exportado) | I52: Aprobado con notificación (Factura electrónica, Recibido) | J52: Presente en el auxiliar (el archivo no trae columna de estado; se infiere Contabilizado) | K52: El lado proveedor + retenciones coincide exacto con la DIAN, pero las líneas de gasto/IVA no están completas en el Journal exportado (el archivo se corta en la fila 16.383); no se puede confirmar la suma de conceptos. | L52: — | M52: INFORMACIÓN INSUFICIENTE | N52: DIAN | O52: 001-FSC-00011433 | P52: 7702, 11290 | Q52: referencia | R52: No (gasto/IVA cortado en la exportación)
A53: COLOMBIA TELECOMUNICACIONES S.A. E.S.P. BIC | B53: 830122566 | C53: BEC546850765 | D53: 23359501 OTROS; 24081513 IVA TRANSITORIO SERVICIOS 19% | E53: 66348 | F53: 66348 | G53: =IF(AND(ISNUMBER(E53),ISNUMBER(F53)),E53-F53,"No disponible") -> 0 | H53: IVA: 10,580.00 | Retenciones (crédito): 0.00 | Gasto/otros: No disponible (líneas fuera del archivo exportado) | I53: Aprobado con notificación (Factura electrónica, Recibido) | J53: Presente en el auxiliar (el archivo no trae columna de estado; se infiere Contabilizado) | K53: El lado proveedor + retenciones coincide exacto con la DIAN, pero las líneas de gasto/IVA no están completas en el Journal exportado (el archivo se corta en la fila 16.383); no se puede confirmar la suma de conceptos. | L53: — | M53: INFORMACIÓN INSUFICIENTE | N53: DIAN | O53: 001-FSC-00011430 | P53: 7699, 11287 | Q53: referencia | R53: No (gasto/IVA cortado en la exportación)
A54: COLOMBIA TELECOMUNICACIONES S.A. E.S.P. BIC | B54: 830122566 | C54: BEC546851208 | D54: 23359501 OTROS; 24081513 IVA TRANSITORIO SERVICIOS 19% | E54: 10996 | F54: 10996 | G54: =IF(AND(ISNUMBER(E54),ISNUMBER(F54)),E54-F54,"No disponible") -> 0 | H54: IVA: 1,756.00 | Retenciones (crédito): 0.00 | Gasto/otros: No disponible (líneas fuera del archivo exportado) | I54: Aprobado con notificación (Factura electrónica, Recibido) | J54: Presente en el auxiliar (el archivo no trae columna de estado; se infiere Contabilizado) | K54: El lado proveedor + retenciones coincide exacto con la DIAN, pero las líneas de gasto/IVA no están completas en el Journal exportado (el archivo se corta en la fila 16.383); no se puede confirmar la suma de conceptos. | L54: — | M54: INFORMACIÓN INSUFICIENTE | N54: DIAN | O54: 001-FSC-00011435 | P54: 7704, 11292 | Q54: referencia | R54: No (gasto/IVA cortado en la exportación)
A55: COLOMBIA TELECOMUNICACIONES S.A. E.S.P. BIC | B55: 830122566 | C55: BEC546851212 | D55: 23359501 OTROS; 24081513 IVA TRANSITORIO SERVICIOS 19% | E55: 21995 | F55: 21995 | G55: =IF(AND(ISNUMBER(E55),ISNUMBER(F55)),E55-F55,"No disponible") -> 0 | H55: IVA: 3,498.00 | Retenciones (crédito): 0.00 | Gasto/otros: No disponible (líneas fuera del archivo exportado) | I55: Aprobado con notificación (Factura electrónica, Recibido) | J55: Presente en el auxiliar (el archivo no trae columna de estado; se infiere Contabilizado) | K55: El lado proveedor + retenciones coincide exacto con la DIAN, pero las líneas de gasto/IVA no están completas en el Journal exportado (el archivo se corta en la fila 16.383); no se puede confirmar la suma de conceptos. | L55: — | M55: INFORMACIÓN INSUFICIENTE | N55: DIAN | O55: 001-FSC-00011427 | P55: 7696, 11284 | Q55: referencia | R55: No (gasto/IVA cortado en la exportación)
A56: COLOMBIA TELECOMUNICACIONES S.A. E.S.P. BIC | B56: 830122566 | C56: BEC546906901 | D56: 23359501 OTROS; 24081513 IVA TRANSITORIO SERVICIOS 19%; 51159502 IMPUESTO AL CONSUMO 8% | E56: 65852 | F56: 65852 | G56: =IF(AND(ISNUMBER(E56),ISNUMBER(F56)),E56-F56,"No disponible") -> 0 | H56: IVA: 10,501.00 | Otros impuestos: 82.00 | Retenciones (crédito): 0.00 | Gasto/otros: No disponible (líneas fuera del archivo exportado) | I56: Aprobado con notificación (Factura electrónica, Recibido) | J56: Presente en el auxiliar (el archivo no trae columna de estado; se infiere Contabilizado) | K56: El lado proveedor + retenciones coincide exacto con la DIAN, pero las líneas de gasto/IVA no están completas en el Journal exportado (el archivo se corta en la fila 16.383); no se puede confirmar la suma de conceptos. | L56: — | M56: INFORMACIÓN INSUFICIENTE | N56: DIAN | O56: 001-FSC-00011425 | P56: 7694, 11282, 16329 | Q56: referencia | R56: No (gasto/IVA cortado en la exportación)
A57: COLOMBIA TELECOMUNICACIONES S.A. E.S.P. BIC | B57: 830122566 | C57: BEC546906902 | D57: 23359501 OTROS; 24081513 IVA TRANSITORIO SERVICIOS 19%; 51159502 IMPUESTO AL CONSUMO 8% | E57: 21995 | F57: 21995 | G57: =IF(AND(ISNUMBER(E57),ISNUMBER(F57)),E57-F57,"No disponible") -> 0 | H57: IVA: 3,498.00 | Otros impuestos: 84.00 | Retenciones (crédito): 0.00 | Gasto/otros: No disponible (líneas fuera del archivo exportado) | I57: Aprobado con notificación (Factura electrónica, Recibido) | J57: Presente en el auxiliar (el archivo no trae columna de estado; se infiere Contabilizado) | K57: El lado proveedor + retenciones coincide exacto con la DIAN, pero las líneas de gasto/IVA no están completas en el Journal exportado (el archivo se corta en la fila 16.383); no se puede confirmar la suma de conceptos. | L57: — | M57: INFORMACIÓN INSUFICIENTE | N57: DIAN | O57: 001-FSC-00011422 | P57: 7691, 11279, 16327 | Q57: referencia | R57: No (gasto/IVA cortado en la exportación)
A58: COLOMBIA TELECOMUNICACIONES S.A. E.S.P. BIC | B58: 830122566 | C58: BEC546906905 | D58: 23359501 OTROS; 24081513 IVA TRANSITORIO SERVICIOS 19% | E58: 44875 | F58: 44875 | G58: =IF(AND(ISNUMBER(E58),ISNUMBER(F58)),E58-F58,"No disponible") -> 0 | H58: IVA: 7,152.00 | Retenciones (crédito): 0.00 | Gasto/otros: No disponible (líneas fuera del archivo exportado) | I58: Aprobado con notificación (Factura electrónica, Recibido) | J58: Presente en el auxiliar (el archivo no trae columna de estado; se infiere Contabilizado) | K58: El lado proveedor + retenciones coincide exacto con la DIAN, pero las líneas de gasto/IVA no están completas en el Journal exportado (el archivo se corta en la fila 16.383); no se puede confirmar la suma de conceptos. | L58: — | M58: INFORMACIÓN INSUFICIENTE | N58: DIAN | O58: 001-FSC-00011432 | P58: 7701, 11289 | Q58: referencia | R58: No (gasto/IVA cortado en la exportación)
A59: COLOMBIA TELECOMUNICACIONES S.A. E.S.P. BIC | B59: 830122566 | C59: BEC546906906 | D59: 23359501 OTROS; 24081513 IVA TRANSITORIO SERVICIOS 19% | E59: 12000 | F59: 12000 | G59: =IF(AND(ISNUMBER(E59),ISNUMBER(F59)),E59-F59,"No disponible") -> 0 | H59: IVA: 1,916.00 | Retenciones (crédito): 0.00 | Gasto/otros: No disponible (líneas fuera del archivo exportado) | I59: Aprobado con notificación (Factura electrónica, Recibido) | J59: Presente en el auxiliar (el archivo no trae columna de estado; se infiere Contabilizado) | K59: El lado proveedor + retenciones coincide exacto con la DIAN, pero las líneas de gasto/IVA no están completas en el Journal exportado (el archivo se corta en la fila 16.383); no se puede confirmar la suma de conceptos. | L59: — | M59: INFORMACIÓN INSUFICIENTE | N59: DIAN | O59: 001-FSC-00011429 | P59: 7698, 11286 | Q59: referencia | R59: No (gasto/IVA cortado en la exportación)
A60: COLOMBIA TELECOMUNICACIONES S.A. E.S.P. BIC | B60: 830122566 | C60: BEC546906982 | D60: 23359501 OTROS; 24081513 IVA TRANSITORIO SERVICIOS 19% | E60: 53293 | F60: 53293 | G60: =IF(AND(ISNUMBER(E60),ISNUMBER(F60)),E60-F60,"No disponible") -> 0 | H60: IVA: 8,490.00 | Retenciones (crédito): 0.00 | Gasto/otros: No disponible (líneas fuera del archivo exportado) | I60: Aprobado con notificación (Factura electrónica, Recibido) | J60: Presente en el auxiliar (el archivo no trae columna de estado; se infiere Contabilizado) | K60: El lado proveedor + retenciones coincide exacto con la DIAN, pero las líneas de gasto/IVA no están completas en el Journal exportado (el archivo se corta en la fila 16.383); no se puede confirmar la suma de conceptos. | L60: — | M60: INFORMACIÓN INSUFICIENTE | N60: DIAN | O60: 001-FSC-00011431 | P60: 7700, 11288 | Q60: referencia | R60: No (gasto/IVA cortado en la exportación)
... A67: COLOMBIA TELECOMUNICACIONES S.A. E.S.P. BIC | B67: 830122566 | C67: BEC546906989 | D67: 23359501 OTROS; 24081513 IVA TRANSITORIO SERVICIOS 19% | E67: 44875 | F67: 44875 | G67: =IF(AND(ISNUMBER(E67),ISNUMBER(F67)),E67-F67,"No disponible") -> 0 | H67: IVA: 7,152.00 | Retenciones (crédito): 0.00 | Gasto/otros: No disponible (líneas fuera del archivo exportado) | I67: Aprobado con notificación (Factura electrónica, Recibido) | J67: Presente en el auxiliar (el archivo no trae columna de estado; se infiere Contabilizado) | K67: El lado proveedor + retenciones coincide exacto con la DIAN, pero las líneas de gasto/IVA no están completas en el Journal exportado (el archivo se corta en la fila 16.383); no se puede confirmar la suma de conceptos. | L67: — | M67: INFORMACIÓN INSUFICIENTE | N67: DIAN | O67: 001-FSC-00011426 | P67: 7695, 11283 | Q67: referencia | R67: No (gasto/IVA cortado en la exportación)
A68: COLOMBIA TELECOMUNICACIONES S.A. E.S.P. BIC | B68: 830122566 | C68: BEV25925571 | D68: No disponible | E68: 8800 | F68: No encontrado | G68: =IF(AND(ISNUMBER(E68),ISNUMBER(F68)),E68-F68,"No disponible") -> No disponible | H68: No disponible | I68: Aprobado con notificación (Factura electrónica, Recibido) | J68: No encontrado | K68: No se encontró el documento en el Journal (el tercero sí tiene otros movimientos). | L68: El tercero aparece en el Journal pero ninguna línea cita este folio ni coincide su valor. | M68: PENDIENTE | N68: DIAN | O68: No encontrado | Q68: No encontrado | R68: No disponible
A69: COLOMBIA TELECOMUNICACIONES S.A. E.S.P. BIC | B69: 830122566 | C69: BEV25925624 | D69: No disponible | E69: 8800 | F69: No encontrado | G69: =IF(AND(ISNUMBER(E69),ISNUMBER(F69)),E69-F69,"No disponible") -> No disponible | H69: No disponible | I69: Aprobado con notificación (Factura electrónica, Recibido) | J69: No encontrado | K69: No se encontró el documento en el Journal (el tercero sí tiene otros movimientos). | L69: El tercero aparece en el Journal pero ninguna línea cita este folio ni coincide su valor. | M69: PENDIENTE | N69: DIAN | O69: No encontrado | Q69: No encontrado | R69: No disponible
A70: COLVANES S.A.S | B70: 800185306 | C70: FE02172053 | D70: 23354501 TRANSPORTES, FLETES Y ACARREOS | E70: 843093 | F70: 843093 | G70: =IF(AND(ISNUMBER(E70),ISNUMBER(F70)),E70-F70,"No disponible") -> 0 | H70: Retenciones (crédito): 0.00 | Gasto/otros: No disponible (líneas fuera del archivo exportado) | I70: Aprobado con notificación (Factura electrónica, Recibido) | J70: Presente en el auxiliar (el archivo no trae columna de estado; se infiere Contabilizado) | K70: El lado proveedor + retenciones coincide exacto con la DIAN, pero las líneas de gasto/IVA no están completas en el Journal exportado (el archivo se corta en la fila 16.383); no se puede confirmar la suma de conceptos. | L70: — | M70: INFORMACIÓN INSUFICIENTE | N70: DIAN | O70: 001-FSC-00011466 | P70: 7338 | Q70: referencia | R70: No (gasto/IVA cortado en la exportación)
A71: COLVANES S.A.S | B71: 800185306 | C71: FE02172101 | D71: 23354501 TRANSPORTES, FLETES Y ACARREOS | E71: 8375367 | F71: 8375367 | G71: =IF(AND(ISNUMBER(E71),ISNUMBER(F71)),E71-F71,"No disponible") -> 0 | H71: Retenciones (crédito): 0.00 | Gasto/otros: No disponible (líneas fuera del archivo exportado) | I71: Aprobado con notificación (Factura electrónica, Recibido) | J71: Presente en el auxiliar (el archivo no trae columna de estado; se infiere Contabilizado) | K71: El lado proveedor + retenciones coincide exacto con la DIAN, pero las líneas de gasto/IVA no están completas en el Journal exportado (el archivo se corta en la fila 16.383); no se puede confirmar la suma de conceptos. | L71: — | M71: INFORMACIÓN INSUFICIENTE | N71: DIAN | O71: 001-FSC-00011461 | P71: 7337 | Q71: referencia | R71: No (gasto/IVA cortado en la exportación)
A72: COLVANES S.A.S | B72: 800185306 | C72: FE02172909 | D72: 23354501 TRANSPORTES, FLETES Y ACARREOS | E72: 584463 | F72: 584463 | G72: =IF(AND(ISNUMBER(E72),ISNUMBER(F72)),E72-F72,"No disponible") -> 0 | H72: Retenciones (crédito): 0.00 | Gasto/otros: No disponible (líneas fuera del archivo exportado) | I72: Aprobado con notificación (Factura electrónica, Recibido) | J72: Presente en el auxiliar (el archivo no trae columna de estado; se infiere Contabilizado) | K72: El lado proveedor + retenciones coincide exacto con la DIAN, pero las líneas de gasto/IVA no están completas en el Journal exportado (el archivo se corta en la fila 16.383); no se puede confirmar la suma de conceptos. | L72: — | M72: INFORMACIÓN INSUFICIENTE | N72: DIAN | O72: 001-FSC-00011571 | P72: 7339 | Q72: referencia | R72: No (gasto/IVA cortado en la exportación)
A73: COLVANES S.A.S | B73: 800185306 | C73: FE02172910 | D73: 23354501 TRANSPORTES, FLETES Y ACARREOS | E73: 8723906 | F73: 8723906 | G73: =IF(AND(ISNUMBER(E73),ISNUMBER(F73)),E73-F73,"No disponible") -> 0 | H73: Retenciones (crédito): 0.00 | Gasto/otros: No disponible (líneas fuera del archivo exportado) | I73: Aprobado con notificación (Factura electrónica, Recibido) | J73: Presente en el auxiliar (el archivo no trae columna de estado; se infiere Contabilizado) | K73: El lado proveedor + retenciones coincide exacto con la DIAN, pero las líneas de gasto/IVA no están completas en el Journal exportado (el archivo se corta en la fila 16.383); no se puede confirmar la suma de conceptos. | L73: — | M73: INFORMACIÓN INSUFICIENTE | N73: DIAN | O73: 001-FSC-00011572 | P73: 7340 | Q73: referencia | R73: No (gasto/IVA cortado en la exportación)
A74: COMBUSTIBLES LIQUIDOS DE COLOMBIA SA ESP | B74: 900175830 | C74: 2YUM22779 | D74: 23359501 OTROS | E74: 96900 | F74: 96900 | G74: =IF(AND(ISNUMBER(E74),ISNUMBER(F74)),E74-F74,"No disponible") -> 0 | H74: Retenciones (crédito): 0.00 | Gasto/otros: No disponible (líneas fuera del archivo exportado) | I74: Aprobado con notificación (Factura electrónica, Recibido) | J74: Presente en el auxiliar (el archivo no trae columna de estado; se infiere Contabilizado) | K74: Coincide el NIT y el valor exacto, pero ninguna línea del Journal cita el número del documento; no se puede identificar con certeza. | L74: — | M74: INFORMACIÓN INSUFICIENTE | N74: DIAN | O74: 001-FSC-00011407 | P74: 7850 | Q74: NIT + valor (sin folio) | R74: No (gasto/IVA cortado en la exportación)
A75: COMBUSTIBLES LIQUIDOS DE COLOMBIA SA ESP | B75: 900175830 | C75: 2YUM23349 | D75: 23359501 OTROS | E75: 98900 | F75: 98900 | G75: =IF(AND(ISNUMBER(E75),ISNUMBER(F75)),E75-F75,"No disponible") -> 0 | H75: Retenciones (crédito): 0.00 | Gasto/otros: No disponible (líneas fuera del archivo exportado) | I75: Aprobado con notificación (Factura electrónica, Recibido) | J75: Presente en el auxiliar (el archivo no trae columna de estado; se infiere Contabilizado) | K75: Coincide el NIT y el valor exacto, pero ninguna línea del Journal cita el número del documento; no se puede identificar con certeza. | L75: — | M75: INFORMACIÓN INSUFICIENTE | N75: DIAN | O75: 001-FSC-00011516 | P75: 7852 | Q75: NIT + valor (sin folio) | R75: No (gasto/IVA cortado en la exportación)
A76: COMERCIALIZADORA MARDEN LTDA | B76: 800004599 | C76: PECO410957 | D76: 23359501 OTROS; 24081510 IVA TRANSITORIO COMPRAS 19% | E76: 27399.75 | F76: 27400 | G76: =IF(AND(ISNUMBER(E76),ISNUMBER(F76)),E76-F76,"No disponible") -> -0.25 | H76: IVA: 4,375.00 | Retenciones (crédito): 0.00 | Gasto/otros: No disponible (líneas fuera del archivo exportado) | I76: Aprobado con notificación (Factura electrónica, Recibido) | J76: Presente en el auxiliar (el archivo no trae columna de estado; se infiere Contabilizado) | K76: El lado proveedor + retenciones del Journal no coincide con el total de la DIAN. | L76: — | M76: PENDIENTE | N76: DIAN | O76: 001-FSC-00011549 | P76: 7552, 11060 | Q76: referencia | R76: No (gasto/IVA cortado en la exportación)
A77: COMPAÑÍA MUNDIAL DE SEGUROS S.A. | B77: 860037013 | C77: 014F21554007 | D77: No disponible | E77: 946600 | F77: No encontrado | G77: =IF(AND(ISNUMBER(E77),ISNUMBER(F77)),E77-F77,"No disponible") -> No disponible | H77: No disponible | I77: Aprobado con notificación (Factura electrónica, Recibido) | J77: No encontrado | K77: El tercero no aparece en el Journal. | L77: NIT sin movimientos en el archivo del Journal. | M77: PENDIENTE | N77: DIAN | O77: No encontrado | Q77: No encontrado | R77: No disponible
A78: COMUNICACION CELULAR S A COMCEL S A | B78: 800153993 | C78: 3292734891 | D78: 23359501 OTROS; 24081513 IVA TRANSITORIO SERVICIOS 19% | E78: 511867 | F78: 511867 | G78: =IF(AND(ISNUMBER(E78),ISNUMBER(F78)),E78-F78,"No disponible") -> 0 | H78: IVA: 81,727.00 | Retenciones (crédito): 0.00 | Gasto/otros: No disponible (líneas fuera del archivo exportado) | I78: Aprobado con notificación (Factura electrónica, Recibido) | J78: Presente en el auxiliar (el archivo no trae columna de estado; se infiere Contabilizado) | K78: El lado proveedor + retenciones coincide exacto con la DIAN, pero las líneas de gasto/IVA no están completas en el Journal exportado (el archivo se corta en la fila 16.383); no se puede confirmar la suma de conceptos. | L78: — | M78: INFORMACIÓN INSUFICIENTE | N78: DIAN | O78: 001-FSC-00011355 | P78: 7578, 11245 | Q78: referencia | R78: No (gasto/IVA cortado en la exportación)
A79: CONSTRUIR INGENIERIA S.A.S. | B79: 800222034 | C79: FEH417 | D79: 23359501 OTROS; 23652507 SERVICIOS GENERALES (DECLARANTES) 4%; 23680203 DEMAS ACTIVIDADES SERVICIOS 10 X 1000; 24081513 IVA TRANSITORIO SERVICIOS 19% | E79: 9520000 | F79: 9520000 | G79: =IF(AND(ISNUMBER(E79),ISNUMBER(F79)),E79-F79,"No disponible") -> 0 | H79: IVA: 1,520,000.00 | Retenciones (crédito): 400,000.00 | Gasto/otros: No disponible (líneas fuera del archivo exportado) | I79: Aprobado con notificación (Factura electrónica, Recibido) | J79: Presente en el auxiliar (el archivo no trae columna de estado; se infiere Contabilizado) | K79: El lado proveedor + retenciones coincide exacto con la DIAN, pero las líneas de gasto/IVA no están completas en el Journal exportado (el archivo se corta en la fila 16.383); no se puede confirmar la suma de conceptos. | L79: — | M79: INFORMACIÓN INSUFICIENTE | N79: DIAN | O79: 001-NT-00012705 | P79: 7586, 8245, 9204, 11251 | Q79: referencia | R79: No (gasto/IVA cortado en la exportación)
A80: COOPERATIVA INTEGRAL DE TAXIS BELALCAZAR | B80: 891500277 | C80: FTPI650564 | D80: No disponible | E80: 6500 | F80: No encontrado | G80: =IF(AND(ISNUMBER(E80),ISNUMBER(F80)),E80-F80,"No disponible") -> No disponible | H80: No disponible | I80: Aprobado (Documento equivalente - Transporte pasajeros terrestre, Recibido) | J80: No encontrado | K80: El tercero no aparece en el Journal. | L80: NIT sin movimientos en el archivo del Journal. | M80: PENDIENTE | N80: DIAN | O80: No encontrado | Q80: No encontrado | R80: No disponible
A81: COOPERATIVA INTEGRAL DE TAXIS BELALCAZAR | B81: 891500277 | C81: FTPO614139 | D81: No disponible | E81: 33000 | F81: No encontrado | G81: =IF(AND(ISNUMBER(E81),ISNUMBER(F81)),E81-F81,"No disponible") -> No disponible | H81: No disponible | I81: Aprobado (Documento equivalente - Transporte pasajeros terrestre, Recibido) | J81: No encontrado | K81: El tercero no aparece en el Journal. | L81: NIT sin movimientos en el archivo del Journal. | M81: PENDIENTE | N81: DIAN | O81: No encontrado | Q81: No encontrado | R81: No disponible
A82: COORDINADORA MERCANTIL S.A. | B82: 890904713 | C82: D03194001448 | D82: 23359501 OTROS | E82: 65830 | F82: 65830 | G82: =IF(AND(ISNUMBER(E82),ISNUMBER(F82)),E82-F82,"No disponible") -> 0 | H82: Retenciones (crédito): 0.00 | Gasto/otros: No disponible (líneas fuera del archivo exportado) | I82: Aprobado con notificación (Factura electrónica, Recibido) | J82: Presente en el auxiliar (el archivo no trae columna de estado; se infiere Contabilizado) | K82: Coincide el NIT y el valor exacto, pero ninguna línea del Journal cita el número del documento; no se puede identificar con certeza. | L82: — | M82: INFORMACIÓN INSUFICIENTE | N82: DIAN | O82: 001-FSC-00011517 | P82: 7827 | Q82: NIT + valor (sin folio) | R82: No (gasto/IVA cortado en la exportación)
A83: COQUEZ GONZALEZ JHON ALEXANDER | B83: 94501120 | C83: NDSE1714 | D83: 23359501 OTROS | E83: 80000 | F83: 80000 | G83: =IF(AND(ISNUMBER(E83),ISNUMBER(F83)),E83-F83,"No disponible") -> 0 | H83: Retenciones (crédito): 0.00 | Gasto/otros: No disponible (líneas fuera del archivo exportado) | I83: Aprobado con notificación (Documento soporte con no obligados, Emitido) | J83: Presente en el auxiliar (el archivo no trae columna de estado; se infiere Contabilizado) | K83: El lado proveedor + retenciones coincide exacto con la DIAN, pero las líneas de gasto/IVA no están completas en el Journal exportado (el archivo se corta en la fila 16.383); no se puede confirmar la suma de conceptos. | L83: — | M83: INFORMACIÓN INSUFICIENTE | N83: DIAN | O83: 001-DSE-00001714 | P83: 8053 | Q83: referencia | R83: No (gasto/IVA cortado en la exportación)
A84: CORREDOR DEL PACIFICO S.A.S. | B84: 900394298 | C84: 12054711 | D84: No disponible | E84: 42000 | F84: No encontrado | G84: =IF(AND(ISNUMBER(E84),ISNUMBER(F84)),E84-F84,"No disponible") -> No disponible | H84: No disponible | I84: Aprobado con notificación (Documento equivalente - Transporte pasajeros terrestre, Recibido) | J84: No encontrado | K84: El tercero no aparece en el Journal. | L84: NIT sin movimientos en el archivo del Journal. | M84: PENDIENTE | N84: DIAN | O84: No encontrado | Q84: No encontrado | R84: No disponible
A85: CORTES CAMPANA JOSE DAVID | B85: 1144187764 | C85: NDSE1728 | D85: 23359501 OTROS | E85: 600000 | F85: 600000 | G85: =IF(AND(ISNUMBER(E85),ISNUMBER(F85)),E85-F85,"No disponible") -> 0 | H85: Retenciones (crédito): 0.00 | Gasto/otros: No disponible (líneas fuera del archivo exportado) | I85: Aprobado con notificación (Documento soporte con no obligados, Emitido) | J85: Presente en el auxiliar (el archivo no trae columna de estado; se infiere Contabilizado) | K85: El lado proveedor + retenciones coincide exacto con la DIAN, pero las líneas de gasto/IVA no están completas en el Journal exportado (el archivo se corta en la fila 16.383); no se puede confirmar la suma de conceptos. | L85: — | M85: INFORMACIÓN INSUFICIENTE | N85: DIAN | O85: 001-DSE-00001728 | P85: 7404 | Q85: referencia | R85: No (gasto/IVA cortado en la exportación)
A86: CORTULUA FUTBOL CLUB S.A. | B86: 800097185 | C86: FEDV540 | D86: 23359501 OTROS; 23651505 HONORARIOS 11%; 24081513 IVA TRANSITORIO SERVICIOS 19% | E86: 11656675 | F86: 11656675 | G86: =IF(AND(ISNUMBER(E86),ISNUMBER(F86)),E86-F86,"No disponible") -> 0 | H86: IVA: 1,861,150.00 | Retenciones (crédito): 1,077,508.00 | Gasto/otros: No disponible (líneas fuera del archivo exportado) | I86: Aprobado con notificación (Factura electrónica, Recibido) | J86: Presente en el auxiliar (el archivo no trae columna de estado; se infiere Contabilizado) | K86: El lado proveedor + retenciones coincide exacto con la DIAN, pero las líneas de gasto/IVA no están completas en el Journal exportado (el archivo se corta en la fila 16.383); no se puede confirmar la suma de conceptos. | L86: — | M86: INFORMACIÓN INSUFICIENTE | N86: DIAN | O86: 001-FSC-00011583 | P86: 7574, 8150, 11240 | Q86: referencia | R86: No (gasto/IVA cortado en la exportación)
A87: CUEVAS COLORADO WALTER ARNULFO | B87: 94527988 | C87: 1462 | D87: 23359501 OTROS; 23652507 SERVICIOS GENERALES (DECLARANTES) 4% | E87: 250000 | F87: 250000 | G87: =IF(AND(ISNUMBER(E87),ISNUMBER(F87)),E87-F87,"No disponible") -> 0 | H87: Retenciones (crédito): 10,000.00 | Gasto/otros: No disponible (líneas fuera del archivo exportado) | I87: Aprobado con notificación (Factura electrónica, Recibido) | J87: Presente en el auxiliar (el archivo no trae columna de estado; se infiere Contabilizado) | K87: El lado proveedor + retenciones coincide exacto con la DIAN, pero las líneas de gasto/IVA no están completas en el Journal exportado (el archivo se corta en la fila 16.383); no se puede confirmar la suma de conceptos. | L87: — | M87: INFORMACIÓN INSUFICIENTE | N87: DIAN | O87: 001-FSC-00011351 | P87: 8061, 8286 | Q87: referencia | R87: No (gasto/IVA cortado en la exportación)
A88: Catalina Zuniga Araujo | B88: 66990687 | C88: FE17 | D88: 23359501 OTROS; 24081513 IVA TRANSITORIO SERVICIOS 19% | E88: 10710000 | F88: 10710000 | G88: =IF(AND(ISNUMBER(E88),ISNUMBER(F88)),E88-F88,"No disponible") -> 0 | H88: IVA: 1,710,000.00 | Retenciones (crédito): 0.00 | Gasto/otros: No disponible (líneas fuera del archivo exportado) | I88: Aprobado con notificación (Factura electrónica, Recibido) | J88: Presente en el auxiliar (el archivo no trae columna de estado; se infiere Contabilizado) | K88: El lado proveedor + retenciones coincide exacto con la DIAN, pero las líneas de gasto/IVA no están completas en el Journal exportado (el archivo se corta en la fila 16.383); no se puede confirmar la suma de conceptos. | L88: — | M88: INFORMACIÓN INSUFICIENTE | N88: DIAN | O88: 001-FSC-00011350 | P88: 7514, 11236 | Q88: referencia | R88: No (gasto/IVA cortado en la exportación)
A89: Catalina Zuniga Araujo | B89: 66990687 | C89: FE18 | D89: 23359501 OTROS; 23651505 HONORARIOS 11%; 24081513 IVA TRANSITORIO SERVICIOS 19%; 23359501 OTROS; 23651505 HONORARIOS 11% | E89: 10710000 | F89: 10710000 | G89: =IF(AND(ISNUMBER(E89),ISNUMBER(F89)),E89-F89,"No disponible") -> 0 | H89: IVA: 1,710,000.00 | Retenciones (crédito): 0.00 | Gasto/otros: No disponible (líneas fuera del archivo exportado) | I89: Aprobado con notificación (Factura electrónica, Recibido) | J89: Presente en el auxiliar (el archivo no trae columna de estado; se infiere Contabilizado) | K89: El lado proveedor + retenciones coincide exacto con la DIAN, pero las líneas de gasto/IVA no están completas en el Journal exportado (el archivo se corta en la fila 16.383); no se puede confirmar la suma de conceptos. | L89: Contabilizado en 2 comprobantes del Journal (001-FSC-00011539, 001-NT-00012685); se sumaron todos. | M89: INFORMACIÓN INSUFICIENTE | N89: DIAN | O89: 001-FSC-00011539, 001-NT-00012685 | P89: 7516, 8147, 11237, 7517, 8148 | Q89: referencia | R89: No (gasto/IVA cortado en la exportación)
A90: Colmena Seguros de Vida S.A. | B90: 901528731 | C90: VT25555830 | D90: 23359501 OTROS | E90: 374594.27 | F90: 374595 | G90: =IF(AND(ISNUMBER(E90),ISNUMBER(F90)),E90-F90,"No disponible") -> -0.73 | H90: Retenciones (crédito): 0.00 | Gasto/otros: No disponible (líneas fuera del archivo exportado) | I90: Aprobado con notificación (Factura electrónica, Recibido) | J90: Presente en el auxiliar (el archivo no trae columna de estado; se infiere Contabilizado) | K90: El lado proveedor + retenciones del Journal no coincide con el total de la DIAN. | L90: — | M90: PENDIENTE | N90: DIAN | O90: 001-FSC-00011564 | P90: 7986 | Q90: referencia | R90: No (gasto/IVA cortado en la exportación)
A91: D1 S A S | B91: 900276962 | C91: G5I0261523 | D91: No disponible | E91: 29049.99 | F91: No encontrado | G91: =IF(AND(ISNUMBER(E91),ISNUMBER(F91)),E91-F91,"No disponible") -> No disponible | H91: No disponible | I91: Aprobado con notificación (Factura electrónica, Recibido) | J91: No encontrado | K91: No se encontró el documento en el Journal (el tercero sí tiene otros movimientos). | L91: El tercero aparece en el Journal pero ninguna línea cita este folio ni coincide su valor. | M91: PENDIENTE | N91: DIAN | O91: No encontrado | Q91: No encontrado | R91: No disponible
A92: D1 S A S | B92: 900276962 | C92: M3F859913 | D92: 23359501 OTROS | E92: 5380 | F92: 5380 | G92: =IF(AND(ISNUMBER(E92),ISNUMBER(F92)),E92-F92,"No disponible") -> 0 | H92: Retenciones (crédito): 0.00 | Gasto/otros: No disponible (líneas fuera del archivo exportado) | I92: Aprobado con notificación (Factura electrónica, Recibido) | J92: Presente en el auxiliar (el archivo no trae columna de estado; se infiere Contabilizado) | K92: Coincide el NIT y el valor exacto, pero ninguna línea del Journal cita el número del documento; no se puede identificar con certeza. | L92: — | M92: INFORMACIÓN INSUFICIENTE | N92: DIAN | O92: 001-FSC-00011470 | P92: 7863 | Q92: NIT + valor (sin folio) | R92: No (gasto/IVA cortado en la exportación)
A93: D1 S A S | B93: 900276962 | C93: M3F859914 | D93: 23359501 OTROS | E93: 1950 | F93: 2000 | G93: =IF(AND(ISNUMBER(E93),ISNUMBER(F93)),E93-F93,"No disponible") -> -50 | H93: Retenciones (crédito): 0.00 | Gasto/otros: No disponible (líneas fuera del archivo exportado) | I93: Aprobado con notificación (Factura electrónica, Recibido) | J93: Presente en el auxiliar (el archivo no trae columna de estado; se infiere Contabilizado) | K93: El lado proveedor + retenciones del Journal no coincide con el total de la DIAN. | L93: — | M93: PENDIENTE | N93: DIAN | O93: 001-FSC-00011446 | P93: 7861 | Q93: referencia | R93: No (gasto/IVA cortado en la exportación)
A94: D1 S A S | B94: 900276962 | C94: M3F964991 | D94: 23359501 OTROS | E94: 1950 | F94: 1980 | G94: =IF(AND(ISNUMBER(E94),ISNUMBER(F94)),E94-F94,"No disponible") -> -30 | H94: Retenciones (crédito): 0.00 | Gasto/otros: No disponible (líneas fuera del archivo exportado) | I94: Aprobado con notificación (Factura electrónica, Recibido) | J94: Presente en el auxiliar (el archivo no trae columna de estado; se infiere Contabilizado) | K94: El lado proveedor + retenciones del Journal no coincide con el total de la DIAN. | L94: — | M94: PENDIENTE | N94: DIAN | O94: 001-FSC-00011479 | P94: 7864 | Q94: referencia | R94: No (gasto/IVA cortado en la exportación)
A95: DE LA PAVA Y COMPANIA S A S | B95: 805002135 | C95: NORT57479 | D95: 23359501 OTROS; 24081510 IVA TRANSITORIO COMPRAS 19% | E95: 4500 | F95: 4501 | G95: =IF(AND(ISNUMBER(E95),ISNUMBER(F95)),E95-F95,"No disponible") -> -1 | H95: IVA: 719.00 | Retenciones (crédito): 0.00 | Gasto/otros: No disponible (líneas fuera del archivo exportado) | I95: Aprobado con notificación (Factura electrónica, Recibido) | J95: Presente en el auxiliar (el archivo no trae columna de estado; se infiere Contabilizado) | K95: El lado proveedor + retenciones del Journal no coincide con el total de la DIAN. | L95: — | M95: PENDIENTE | N95: DIAN | O95: 001-FSC-00011409 | P95: 7639, 11093 | Q95: referencia | R95: No (gasto/IVA cortado en la exportación)
A96: DESPEGAR COLOMBIA SAS | B96: 900610518 | C96: FV10521699 | D96: No disponible | E96: 844372 | F96: No encontrado | G96: =IF(AND(ISNUMBER(E96),ISNUMBER(F96)),E96-F96,"No disponible") -> No disponible | H96: No disponible | I96: Aprobado con notificación (Factura electrónica, Recibido) | J96: No encontrado | K96: El tercero no aparece en el Journal. | L96: NIT sin movimientos en el archivo del Journal. | M96: PENDIENTE | N96: DIAN | O96: No encontrado | Q96: No encontrado | R96: No disponible
A97: DISTRACOM S.A. | B97: 811009788 | C97: DST7544954 | D97: No disponible | E97: 12000 | F97: No encontrado | G97: =IF(AND(ISNUMBER(E97),ISNUMBER(F97)),E97-F97,"No disponible") -> No disponible | H97: No disponible | I97: Aprobado con notificación (Factura electrónica, Recibido) | J97: No encontrado | K97: El tercero no aparece en el Journal. | L97: NIT sin movimientos en el archivo del Journal. | M97: PENDIENTE | N97: DIAN | O97: No encontrado | Q97: No encontrado | R97: No disponible
A98: DISTRIBUIDORA MAYORISTA LIMITADA | B98: 800239989 | C98: DMFE832 | D98: 22050501 PROVEEDORES NACIONALES; 23652507 SERVICIOS GENERALES (DECLARANTES) 4% | E98: 163377 | F98: 163377 | G98: =IF(AND(ISNUMBER(E98),ISNUMBER(F98)),E98-F98,"No disponible") -> 0 | H98: Retenciones (crédito): 6,535.00 | Gasto/otros: No disponible (líneas fuera del archivo exportado) | I98: Aprobado con notificación (Factura electrónica, Recibido) | J98: Presente en el auxiliar (el archivo no trae columna de estado; se infiere Contabilizado) | K98: El lado proveedor + retenciones coincide exacto con la DIAN, pero las líneas de gasto/IVA no están completas en el Journal exportado (el archivo se corta en la fila 16.383); no se puede confirmar la suma de conceptos. | L98: — | M98: INFORMACIÓN INSUFICIENTE | N98: DIAN | O98: 001-FSC-00011384 | P98: 7214, 8247 | Q98: referencia | R98: No (gasto/IVA cortado en la exportación)
A99: DISTRIBUIDORA MAYORISTA LIMITADA | B99: 800239989 | C99: DMFE833 | D99: No disponible | E99: 17284533 | F99: No encontrado | G99: =IF(AND(ISNUMBER(E99),ISNUMBER(F99)),E99-F99,"No disponible") -> No disponible | H99: No disponible | I99: Aprobado con notificación (Factura electrónica, Recibido) | J99: Solo comprobantes de pago/legalización, sin causación | K99: El documento se cita en comprobantes que no lo causan (pago, legalización o anticipo), pero no hay un comprobante de causación para él. | L99: Revisar: 001-FSC-00011386, 001-NT-00012655 | M99: PENDIENTE | N99: DIAN | O99: 001-FSC-00011386, 001-NT-00012655 | Q99: referencia | R99: No disponible
A100: DISTRIBUIDORA MAYORISTA LIMITADA | B100: 800239989 | C100: DMFE835 | D100: 22050501 PROVEEDORES NACIONALES; 23652507 SERVICIOS GENERALES (DECLARANTES) 4% | E100: 936203 | F100: 936203 | G100: =IF(AND(ISNUMBER(E100),ISNUMBER(F100)),E100-F100,"No disponible") -> 0 | H100: Retenciones (crédito): 37,448.00 | Gasto/otros: No disponible (líneas fuera del archivo exportado) | I100: Aprobado con notificación (Factura electrónica, Recibido) | J100: Presente en el auxiliar (el archivo no trae columna de estado; se infiere Contabilizado) | K100: El lado proveedor + retenciones coincide exacto con la DIAN, pero las líneas de gasto/IVA no están completas en el Journal exportado (el archivo se corta en la fila 16.383); no se puede confirmar la suma de conceptos. | L100: — | M100: INFORMACIÓN INSUFICIENTE | N100: DIAN | O100: 001-FSC-00011417 | P100: 7219, 8248 | Q100: referencia | R100: No (gasto/IVA cortado en la exportación)
A101: DISTRIBUIDORA MAYORISTA LIMITADA | B101: 800239989 | C101: DMFE837 | D101: 22050501 PROVEEDORES NACIONALES; 23652507 SERVICIOS GENERALES (DECLARANTES) 4% | E101: 1524400 | F101: 1524400 | G101: =IF(AND(ISNUMBER(E101),ISNUMBER(F101)),E101-F101,"No disponible") -> 0 | H101: Retenciones (crédito): 60,976.00 | Gasto/otros: No disponible (líneas fuera del archivo exportado) | I101: Aprobado con notificación (Factura electrónica, Recibido) | J101: Presente en el auxiliar (el archivo no trae columna de estado; se infiere Contabilizado) | K101: El lado proveedor + retenciones coincide exacto con la DIAN, pero las líneas de gasto/IVA no están completas en el Journal exportado (el archivo se corta en la fila 16.383); no se puede confirmar la suma de conceptos. | L101: — | M101: INFORMACIÓN INSUFICIENTE | N101: DIAN | O101: 001-FSC-00011460 | P101: 7221, 8249 | Q101: referencia | R101: No (gasto/IVA cortado en la exportación)
A102: DISTRIBUIDORA MAYORISTA LIMITADA | B102: 800239989 | C102: DMFE838 | D102: 22050501 PROVEEDORES NACIONALES; 23652501 TRANSPORTE 1% | E102: 17182828 | F102: 17182828 | G102: =IF(AND(ISNUMBER(E102),ISNUMBER(F102)),E102-F102,"No disponible") -> 0 | H102: Retenciones (crédito): 171,828.00 | Gasto/otros: No disponible (líneas fuera del archivo exportado) | I102: Aprobado con notificación (Factura electrónica, Recibido) | J102: Presente en el auxiliar (el archivo no trae columna de estado; se infiere Contabilizado) | K102: El lado proveedor + retenciones coincide exacto con la DIAN, pero las líneas de gasto/IVA no están completas en el Journal exportado (el archivo se corta en la fila 16.383); no se puede confirmar la suma de conceptos. | L102: — | M102: INFORMACIÓN INSUFICIENTE | N102: DIAN | O102: 001-FSC-00011536 | P102: 7226, 8185 | Q102: referencia | R102: No (gasto/IVA cortado en la exportación)
A103: DROGUERIA ALONSO LTDA | B103: 800126903 | C103: CENT1165 | D103: 23359501 OTROS; 23652507 SERVICIOS GENERALES (DECLARANTES) 4%; 23680203 DEMAS ACTIVIDADES SERVICIOS 10 X 1000; 24081513 IVA TRANSITORIO SERVICIOS 19% | E103: 954751.28 | F103: 954751 | G103: =IF(AND(ISNUMBER(E103),ISNUMBER(F103)),E103-F103,"No disponible") -> 0.28 | H103: IVA: 152,439.00 | Retenciones (crédito): 40,115.00 | Gasto/otros: No disponible (líneas fuera del archivo exportado) | I103: Aprobado con notificación (Factura electrónica, Recibido) | J103: Presente en el auxiliar (el archivo no trae columna de estado; se infiere Contabilizado) | K103: El lado proveedor + retenciones del Journal no coincide con el total de la DIAN. | L103: — | M103: PENDIENTE | N103: DIAN | O103: 001-FSC-00011581 | P103: 7576, 8241, 9202, 11242 | Q103: referencia | R103: No (gasto/IVA cortado en la exportación)
A104: EL COMERCIO ELECTRICO S.A.S. | B104: 890323635 | C104: NCEN2097 | D104: 23359501 OTROS; 24081510 IVA TRANSITORIO COMPRAS 19% | E104: 9639 | F104: 9639 | G104: =IF(AND(ISNUMBER(E104),ISNUMBER(F104)),E104-F104,"No disponible") -> 0 | H104: IVA: 1,539.00 | Retenciones (crédito): 0.00 | Gasto/otros: No disponible (líneas fuera del archivo exportado) | I104: Aprobado con notificación (Nota de crédito electrónica, Recibido) | J104: Presente en el auxiliar (el archivo no trae columna de estado; se infiere Contabilizado) | K104: El lado proveedor + retenciones coincide exacto con la DIAN, pero las líneas de gasto/IVA no están completas en el Journal exportado (el archivo se corta en la fila 16.383); no se puede confirmar la suma de conceptos. | L104: — | M104: INFORMACIÓN INSUFICIENTE | N104: DIAN | O104: 001-NT-00012673 | P104: 7795, 11124 | Q104: texto/descripción | R104: No (gasto/IVA cortado en la exportación)
A105: EL COMERCIO ELECTRICO S.A.S. | B105: 890323635 | C105: NFFN31709 | D105: 23359501 OTROS; 24081510 IVA TRANSITORIO COMPRAS 19% | E105: 291312 | F105: 291312 | G105: =IF(AND(ISNUMBER(E105),ISNUMBER(F105)),E105-F105,"No disponible") -> 0 | H105: IVA: 46,512.00 | Retenciones (crédito): 0.00 | Gasto/otros: No disponible (líneas fuera del archivo exportado) | I105: Aprobado con notificación (Factura electrónica, Recibido) | J105: Presente en el auxiliar (el archivo no trae columna de estado; se infiere Contabilizado) | K105: El lado proveedor + retenciones coincide exacto con la DIAN, pero las líneas de gasto/IVA no están completas en el Journal exportado (el archivo se corta en la fila 16.383); no se puede confirmar la suma de conceptos. | L105: — | M105: INFORMACIÓN INSUFICIENTE | N105: DIAN | O105: 001-FSC-00011530 | P105: 7794, 11123 | Q105: referencia | R105: No (gasto/IVA cortado en la exportación)
A106: EL COMERCIO ELECTRICO S.A.S. | B106: 890323635 | C106: NFFN31988 | D106: 23359501 OTROS; 24081510 IVA TRANSITORIO COMPRAS 19% | E106: 67026.75 | F106: 67027 | G106: =IF(AND(ISNUMBER(E106),ISNUMBER(F106)),E106-F106,"No disponible") -> -0.25 | H106: IVA: 10,702.00 | Retenciones (crédito): 0.00 | Gasto/otros: No disponible (líneas fuera del archivo exportado) | I106: Aprobado con notificación (Factura electrónica, Recibido) | J106: Presente en el auxiliar (el archivo no trae columna de estado; se infiere Contabilizado) | K106: El lado proveedor + retenciones del Journal no coincide con el total de la DIAN. | L106: — | M106: PENDIENTE | N106: DIAN | O106: 001-FSC-00011526 | P106: 7792, 11121 | Q106: referencia | R106: No (gasto/IVA cortado en la exportación)
...
