Workbook

Sheet CAJAS REEMBOLSO 
C4: NATURAL SYSTEMS INTERNATIONAL SAS
C5: LEGALIZACION DE EDGAR YEPES
B7: NIT/CC | C7: PREFIJO | D7: NUMERO FACTURA | E7: FECHA FACTURA | F7: TERCERO | G7: CONCEPTO | H7: CENTRO DE COSTO | I7: SUB TOTAL GRAVADO | J7: SUB TOTAL SIN IVA | K7: IVA | L7: INC | M7: TOTAL
A9: 1 | D9: 292607292419034102111508 | E9: 29/01/2026 | F9: PANDA EXPRESS | G9: ALMUERZO | J9: 22.8 | K9: 1.6 | M9: =J9+K9 -> 24.4
A10: 2 | D10: 332405324915 | E10: 20/01/2026 | F10: BEST BUY | G10: CARGADOR DE COMPUTADOR | J10: 39.99 | K10: 2.8 | M10: =J10+K10 -> 42.79
A11: 3 | D11: 020381039221 | E11: 17/07/2026 | F11: THE HOME DEPOT | G11: HERRAMIENTAS | J11: 162.84 | K11: 10.36 | M11: =J11+K11 -> 173.2
A12: 4 | D12: 63438235160 | E12: 08/07/2026 | F12: THE HOME DEPOT | G12: MATERIALES DE CONTRUCCION | J12: 249.36 | K12: 17.46 | M12: =J12+K12 -> 266.82
A13: 5 | D13: 990032327006800009062626 | E13: 26/06/2026 | F13: IKEA | G13: FORRO DE COLCHON Y CUBIERTOS | J13: 28.98 | K13: 2.03 | M13: =J13+K13 -> 31.01
A14: 6 | D14: SHVU28 | E14: 46215 | F14: HOLLYWOOD FL | G14: PARQUEADERO | J14: 4.5 | M14: =J14+K14 -> 4.5
A15: 7 | D15: 5980203649 | E15: 46220 | F15: COSTCO | G15: MERCADO | J15: 13.99 | M15: =J15+K15 -> 13.99
A16: 8 | D16: 02057SR039301 | E16: 46230 | F16: PUBLIX | G16: MERCADO | J16: 7.28 | K16: 0.51 | M16: =J16+K16 -> 7.79
A17: 9 | D17: 05300730000031184821 | E17: 46233 | F17: STEAK N SHAKE | G17: ALMUERZO | J17: 9.68 | K17: 0.68 | M17: =J17+K17 -> 10.36
A18: 10 | D18: 89890723601011 | E18: 46229 | F18: DOLLAR TREE | G18: MERCADO | J18: 4.5 | K18: 0.32 | M18: =J18+K18 -> 4.82
A19: 11 | D19: 702771302108429 | E19: 46231 | F19: BURGER KING | G19: COMIDA | J19: 12.99 | K19: 0.91 | M19: =J19+K19 -> 13.9
A20: 12 | D20: 63248 | E20: 46221 | F20: TRADER JOES | G20: MERCADO | J20: 12.27 | M20: =J20+K20 -> 12.27
A21: 13 | D21: 164 | E21: 46232 | F21: CHASE | G21: PAGO DE ENERGIA | J21: 160.44 | M21: =J21+K21 -> 160.44
A22: 14 | D22: 4730 FA04 | E22: 45880 | F22: ALDI | G22: MERCADO | J22: 57.67 | K22: 0.85 | M22: =J22+K22 -> 58.52
A23: 15 | D23: 56869813583243057951 | E23: 46217 | F23: WALMART | G23: MERCADO | J23: 40.3 | K23: 0.8 | M23: =J23+K23 -> 41.1
A24: 16 | D24: 9199337126 | E24: 46214 | F24: COSTCO | G24: MERCADO | J24: 26.99 | K24: 1.89 | M24: =J24+K24 -> 28.88
A25: 17 | D25: 91205225705 | E25: 46214 | F25: COSTCO | G25: MERCADO | J25: 69.03 | K25: 2.93 | M25: =J25+K25 -> 71.96
A26: 18 | D26: 91233213733 | E26: 46214 | F26: COSTCO | G26: ALMUERZO | J26: 3.49 | K26: 0.24 | M26: =J26+K26 -> 3.73
A27: 19 | D27: 6178081500794130 | E27: 46200 | F27: TARGET | G27: MERCADO | J27: 34.96 | K27: 2.17 | M27: =J27+K27 -> 37.13
A28: 20 | D28: 34870723602023 | E28: 46204 | F28: DOLLAR TREE | G28: MERCADO | J28: 7.5 | K28: 0.32 | M28: =J28+K28 -> 7.82
A29: 21 | D29: 49460723601012 | E29: 46214 | F29: DOLLAR TREE | G29: MERCADO | J29: 8.25 | K29: 0.21 | M29: =J29+K29 -> 8.46
A30: 22 | D30: 40065 | E30: 46234 | F30: CHURCHS | G30: ALMUERZO | J30: 11.28 | K30: 0.79 | M30: =J30+K30 -> 12.07
A31: 23 | D31: 306495 | E31: 46200 | F31: ASIAN CHAO | G31: ALMUERZO | J31: 13.99 | K31: 0.98 | M31: =J31+K31 -> 14.97
A32: 24 | D32: 02225275369 | E32: 46213 | F32: THE HOME DEPOT | G32: TRONILLOS Y TAB | J32: 31.8 | K32: 2.23 | M32: =J32+K32 -> 34.03
A33: 25 | D33: 02220002715449 | E33: 46213 | F33: THE HOME DEPOT | G33: ENCHUFES Y REGLETA | J33: 40.32 | K33: 2.82 | M33: =J33+K33 -> 43.14
A34: 26 | D34: 22043346110686495322 | E34: 46211 | F34: WALMART | G34: MERCADO | J34: 9.47 | M34: =J34+K34 -> 9.47
A35: 27 | D35: 199974 | E35: 46208 | F35: POLLO TROPICAL | G35: ALMUERZO | J35: 10.29 | K35: 0.72 | M35: =J35+K35 -> 11.01
A36: 28 | D36: 199977 | E36: 46208 | F36: POLLO TROPICAL | G36: ALMUERZO | J36: 4.79 | K36: 0.34 | M36: =J36+K36 -> 5.13
A37: 29 | D37: 233156733 | E37: 46212 | F37: COSTCO | G37: ALMUERZO | J37: 5.48 | K37: 0.38 | M37: =J37+K37 -> 5.86
A38: 30 | D38: 0354FS76 | E38: 46209 | F38: ALDI | G38: MERCADO | J38: 12.7 | K38: 0.01 | M38: =J38+K38 -> 12.71
A39: 31 | D39: 02225370259 | E39: 46212 | F39: THE HOME DEPOT | G39: MESA | J39: 38.2 | K39: 2.67 | M39: =J39+K39 -> 40.87
A40: 32 | D40: 2750FA04 | E40: 46231 | F40: ALDI | G40: MERCADO | J40: 9.96 | M40: =J40+K40 -> 9.96
A41: 33 | D41: 261171516654 | E41: 46232 | F41: WENDYS | G41: ALMUERZO | J41: 8 | K41: 0.56 | M41: =J41+K41 -> 8.56
A42: 34 | D42: 9930014904647 | E42: 46197 | F42: SEDANOS | G42: MERCADO | J42: 4.734 | K42: 0.2 | M42: =J42+K42 -> 4.934
A43: 35 | D43: 10314 | E43: 46198 | F43: CHIPOTLE | G43: ALMUERZO | J43: 13.45 | K43: 0.94 | M43: =J43+K43 -> 14.39
A44: 36 | D44: 76320971240197904112 | E44: 46201 | F44: WALMART | G44: ALMUERZO | J44: 41.05 | K44: 2.22 | M44: =J44+K44 -> 43.27
A45: 37 | D45: 91636664 | E45: 46195 | F45: COSTCO | G45: MERCADO | J45: 193.23 | K45: 3.78 | M45: =J45+K45 -> 197.01
A46: 38 | D46: 91234476734 | E46: 46195 | F46: COSTCO | G46: ALMUERZO | J46: 3.49 | K46: 0.24 | M46: =J46+K46 -> 3.73
A47: 39 | D47: 911120612 | E47: 46204 | F47: COSTCO | G47: MERCADO | J47: 20.87 | K47: 0.49 | M47: =J47+K47 -> 21.36
A48: 40 | D48: 91233120733 | E48: 46206 | F48: COSTCO | G48: ALMUERZO | J48: 3.49 | K48: 0.24 | M48: =J48+K48 -> 3.73
A49: 41 | D49: 91233178733 | E49: 46204 | F49: COSTCO | G49: COMIDA | J49: 2.49 | K49: 0.17 | M49: =J49+K49 -> 2.66
A50: 42 | D50: 54904224208513900000 | E50: 46229 | F50: WALMART | G50: MERCADO | J50: 79.09 | K50: 1.77 | M50: =J50+K50 -> 80.86
A51: 43 | D51: 1070260002007000000 | E51: 46208 | F51: BRANDS MART | G51: SANDUCHERA | J51: 19.98 | K51: 1.4 | M51: =J51+K51 -> 21.38
A52: 44 | D52: 22120723603031 | E52: 46203 | F52: DOLLAR TREE | G52: MERCADO | J52: 4.5 | M52: =J52+K52 -> 4.5
A53: 45 | D53: 220 | E53: 46201 | F53: CHIPOTLE | G53: ALMUERZO | J53: 17.95 | K53: 1.26 | M53: =J53+K53 -> 19.21
A54: 46 | D54: 8303FS76 | E54: 46199 | F54: ALDI | G54: MERCADO | J54: 17.83 | M54: =J54+K54 -> 17.83
A55: 47 | D55: 10042394 | E55: 46199 | F55: IKEA | G55: ALMUERZO | J55: 11.99 | K55: 0.84 | M55: =J55+K55 -> 12.83
A56: 48 | D56: 9197352 | E56: 46236 | F56: COSTCO | G56: MERCADO | J56: 99.8 | K56: 2.8 | M56: =J56+K56 -> 102.6
A57: 49 | D57: 91205155705 | E57: 46227 | F57: COSTCO | G57: MERCADO | J57: 86.53 | K57: 0.98 | M57: =J57+K57 -> 87.51
A58: 50 | D58: 3F1F90976653E94A | E58: 46220 | F58: THE TACO STAD | G58: ALMUERZO | J58: 19.08 | K58: 1.34 | M58: =J58+K58 -> 20.42
A59: 51 | D59: 227598 | E59: 46226 | F59: PANDA EXPRESS | G59: ALMUERZO | J59: 10.5 | K59: 0.74 | M59: =J59+K59 -> 11.24
A60: 52 | D60: 000243902374 | E60: 46225 | F60: PUBLIX | G60: ALMUERZO | J60: 9.81 | K60: 0.69 | M60: =J60+K60 -> 10.5
A61: 53 | D61: 02527JR020008 | E61: 46222 | F61: PUBLIX | G61: MERCADO | J61: 7.98 | M61: =J61+K61 -> 7.98
A62: 54 | D62: 5051072360031 | E62: 46221 | F62: DOLLAR TREE | G62: MERCADO | J62: 36 | K62: 1.77 | M62: =J62+K62 -> 37.77
A63: 55 | D63: 7WSLJT11BRNS | E63: 46219 | F63: WALMART | G63: MERCADO | J63: 61.54 | K63: 0.67 | M63: =J63+K63 -> 62.21
A64: 56 | D64: 66456 | E64: 46224 | F64: TRADER JOES | G64: MERCADO | J64: 11.66 | M64: =J64+K64 -> 11.66
A65: 57 | D65: 04003236723426071903 | E65: 46222 | F65: WALGREENS | G65: DROGUERIA | J65: 5.29 | M65: =J65+K65 -> 5.29
A66: 58 | D66: 533088000018013 | E66: 46235 | F66: WINGSTOP | G66: ALMUERZO | J66: 11.99 | K66: 0.84 | M66: =J66+K66 -> 12.83
A67: 59 | D67: 101695 | E67: 46210 | F67: UNIVERSITY DRIVE | G67: ALMUERZO | J67: 19.04 | M67: =J67+K67 -> 19.04
A68: 60 | D68: 2932427 | E68: 46225 | F68: FPL | J68: 24.65 | K68: 2.11 | M68: =J68+K68 -> 26.76
A69: 61 | D69: 32386729 | E69: 46205 | F69: COUNTRY TAX COLLECTOR | G69: LICENCIA DRIVER | J69: 6.25 | M69: =J69+K69 -> 6.25
A70: 62 | D70: 32384944 | E70: 46205 | F70: COUNTRY TAX COLLECTOR | G70: LICENCIA DRIVER | J70: 56.75 | M70: =J70+K70 -> 56.75
A71: 63 | D71: GGS2144SMD | E71: 46229 | F71: GOLDGAR USA | G71: RENOV PAR TACOMA | J71: 25 | M71: =J71+K71 -> 25
A72: 64 | D72: 2932427 | E72: 46195 | F72: FPL | G72: PAGO DE ENERGIA | J72: 160.44 | M72: =J72+K72 -> 160.44
A73: 65 | D73: 8017215176174556905367 | E73: 46203 | F73: FPL | G73: ENERGIA | J73: 76.35 | M73: =J73+K73 -> 76.35
A74: 66 | D74: 17617-45569 | E74: 46203 | F74: FPL | G74: ENERGIA | J74: 8.01 | M74: =J74+K74 -> 8.01
A75: 67 | E75: 46255 | F75: FPL | G75: ENERGIA | J75: 65.43 | M75: =J75+K75 -> 65.43
A76: 68 | E76: 46285 | F76: FPL | G76: ENERGIA | J76: 88.97 | M76: =J76+K76 -> 88.97
A77: 69 | E77: 46200 | F77: INFINITY | G77: INTERNET JUN | J77: 41.05 | M77: =J77+K77 -> 41.05
A78: 70 | E78: 46292 | F78: INFINITY | G78: INTERNET SEP | J78: 41.05 | M78: =J78+K78 -> 41.05
A79: 71 | E79: 46262 | F79: INFINITY | G79: INTERNET AGOST | J79: 41.05 | M79: =J79+K79 -> 41.05
A80: 72 | E80: 46203 | F80: FPL | G80: ENERGIA | J80: 76.35 | M80: =J80+K80 -> 76.35
M81: =SUM(M9:M80) -> 2781.874
C82: SCHANTAL BENITEZ | G82: JULIAN CASTAÑEDA V.
C83: Elaborado | G83: Autorizado

Sheet Por tercero
A1: REEMBOLSO EDGAR YEPES — valores en DÓLARES (USD) por tercero; use + / − (o botones 1/2) para ver las facturas de cada tercero
D2: TOTAL GENERAL | E2: =SUMIF($H$5:$H$300,"TOTAL TERCERO",E5:E300) -> 2698.804 | F2: =SUMIF($H$5:$H$300,"TOTAL TERCERO",F5:F300) -> 83.07 | G2: =SUMIF($H$5:$H$300,"TOTAL TERCERO",G5:G300) -> 2781.874
A4: Tercero | B4: N° factura | C4: Fecha | D4: Concepto | E4: Subtotal sin IVA (USD) | F4: IVA (USD) | G4: Total (USD) | H4: Tipo / # facturas | I4: Ítem
A5: ALDI | B5: =COUNTIFS('CAJAS REEMBOLSO '!$F$9:$F$80,A5) -> 4 | E5: =SUMIFS('CAJAS REEMBOLSO '!$J$9:$J$80,'CAJAS REEMBOLSO '!$F$9:$F$80,$A5) -> 98.16 | F5: =SUMIFS('CAJAS REEMBOLSO '!$K$9:$K$80,'CAJAS REEMBOLSO '!$F$9:$F$80,$A5) -> 0.86 | G5: =SUMIFS('CAJAS REEMBOLSO '!$M$9:$M$80,'CAJAS REEMBOLSO '!$F$9:$F$80,$A5) -> 99.02 | H5: TOTAL TERCERO
A6: ALDI | B6: 4730 FA04 | C6: 45880 | D6: MERCADO | E6: =N('CAJAS REEMBOLSO '!J22) -> 57.67 | F6: =N('CAJAS REEMBOLSO '!K22) -> 0.85 | G6: ='CAJAS REEMBOLSO '!M22 -> 58.52 | H6: Factura | I6: 14
A7: ALDI | B7: 8303FS76 | C7: 46199 | D7: MERCADO | E7: =N('CAJAS REEMBOLSO '!J54) -> 17.83 | F7: =N('CAJAS REEMBOLSO '!K54) -> 0 | G7: ='CAJAS REEMBOLSO '!M54 -> 17.83 | H7: Factura | I7: 46
A8: ALDI | B8: 0354FS76 | C8: 46209 | D8: MERCADO | E8: =N('CAJAS REEMBOLSO '!J38) -> 12.7 | F8: =N('CAJAS REEMBOLSO '!K38) -> 0.01 | G8: ='CAJAS REEMBOLSO '!M38 -> 12.71 | H8: Factura | I8: 30
A9: ALDI | B9: 2750FA04 | C9: 46231 | D9: MERCADO | E9: =N('CAJAS REEMBOLSO '!J40) -> 9.96 | F9: =N('CAJAS REEMBOLSO '!K40) -> 0 | G9: ='CAJAS REEMBOLSO '!M40 -> 9.96 | H9: Factura | I9: 32
A10: ASIAN CHAO | B10: =COUNTIFS('CAJAS REEMBOLSO '!$F$9:$F$80,A10) -> 1 | E10: =SUMIFS('CAJAS REEMBOLSO '!$J$9:$J$80,'CAJAS REEMBOLSO '!$F$9:$F$80,$A10) -> 13.99 | F10: =SUMIFS('CAJAS REEMBOLSO '!$K$9:$K$80,'CAJAS REEMBOLSO '!$F$9:$F$80,$A10) -> 0.98 | G10: =SUMIFS('CAJAS REEMBOLSO '!$M$9:$M$80,'CAJAS REEMBOLSO '!$F$9:$F$80,$A10) -> 14.97 | H10: TOTAL TERCERO
A11: ASIAN CHAO | B11: 306495 | C11: 46200 | D11: ALMUERZO | E11: =N('CAJAS REEMBOLSO '!J31) -> 13.99 | F11: =N('CAJAS REEMBOLSO '!K31) -> 0.98 | G11: ='CAJAS REEMBOLSO '!M31 -> 14.97 | H11: Factura | I11: 23
A12: BEST BUY | B12: =COUNTIFS('CAJAS REEMBOLSO '!$F$9:$F$80,A12) -> 1 | E12: =SUMIFS('CAJAS REEMBOLSO '!$J$9:$J$80,'CAJAS REEMBOLSO '!$F$9:$F$80,$A12) -> 39.99 | F12: =SUMIFS('CAJAS REEMBOLSO '!$K$9:$K$80,'CAJAS REEMBOLSO '!$F$9:$F$80,$A12) -> 2.8 | G12: =SUMIFS('CAJAS REEMBOLSO '!$M$9:$M$80,'CAJAS REEMBOLSO '!$F$9:$F$80,$A12) -> 42.79 | H12: TOTAL TERCERO
A13: BEST BUY | B13: 332405324915 | C13: 46042 | D13: CARGADOR DE COMPUTADOR | E13: =N('CAJAS REEMBOLSO '!J10) -> 39.99 | F13: =N('CAJAS REEMBOLSO '!K10) -> 2.8 | G13: ='CAJAS REEMBOLSO '!M10 -> 42.79 | H13: Factura | I13: 2
A14: BRANDS MART | B14: =COUNTIFS('CAJAS REEMBOLSO '!$F$9:$F$80,A14) -> 1 | E14: =SUMIFS('CAJAS REEMBOLSO '!$J$9:$J$80,'CAJAS REEMBOLSO '!$F$9:$F$80,$A14) -> 19.98 | F14: =SUMIFS('CAJAS REEMBOLSO '!$K$9:$K$80,'CAJAS REEMBOLSO '!$F$9:$F$80,$A14) -> 1.4 | G14: =SUMIFS('CAJAS REEMBOLSO '!$M$9:$M$80,'CAJAS REEMBOLSO '!$F$9:$F$80,$A14) -> 21.38 | H14: TOTAL TERCERO
A15: BRANDS MART | B15: 1070260002007000000 | C15: 46208 | D15: SANDUCHERA | E15: =N('CAJAS REEMBOLSO '!J51) -> 19.98 | F15: =N('CAJAS REEMBOLSO '!K51) -> 1.4 | G15: ='CAJAS REEMBOLSO '!M51 -> 21.38 | H15: Factura | I15: 43
A16: BURGER KING | B16: =COUNTIFS('CAJAS REEMBOLSO '!$F$9:$F$80,A16) -> 1 | E16: =SUMIFS('CAJAS REEMBOLSO '!$J$9:$J$80,'CAJAS REEMBOLSO '!$F$9:$F$80,$A16) -> 12.99 | F16: =SUMIFS('CAJAS REEMBOLSO '!$K$9:$K$80,'CAJAS REEMBOLSO '!$F$9:$F$80,$A16) -> 0.91 | G16: =SUMIFS('CAJAS REEMBOLSO '!$M$9:$M$80,'CAJAS REEMBOLSO '!$F$9:$F$80,$A16) -> 13.9 | H16: TOTAL TERCERO
A17: BURGER KING | B17: 702771302108429 | C17: 46231 | D17: COMIDA | E17: =N('CAJAS REEMBOLSO '!J19) -> 12.99 | F17: =N('CAJAS REEMBOLSO '!K19) -> 0.91 | G17: ='CAJAS REEMBOLSO '!M19 -> 13.9 | H17: Factura | I17: 11
A18: CHASE | B18: =COUNTIFS('CAJAS REEMBOLSO '!$F$9:$F$80,A18) -> 1 | E18: =SUMIFS('CAJAS REEMBOLSO '!$J$9:$J$80,'CAJAS REEMBOLSO '!$F$9:$F$80,$A18) -> 160.44 | F18: =SUMIFS('CAJAS REEMBOLSO '!$K$9:$K$80,'CAJAS REEMBOLSO '!$F$9:$F$80,$A18) -> 0 | G18: =SUMIFS('CAJAS REEMBOLSO '!$M$9:$M$80,'CAJAS REEMBOLSO '!$F$9:$F$80,$A18) -> 160.44 | H18: TOTAL TERCERO
A19: CHASE | B19: 164 | C19: 46232 | D19: PAGO DE ENERGIA | E19: =N('CAJAS REEMBOLSO '!J21) -> 160.44 | F19: =N('CAJAS REEMBOLSO '!K21) -> 0 | G19: ='CAJAS REEMBOLSO '!M21 -> 160.44 | H19: Factura | I19: 13
A20: CHIPOTLE | B20: =COUNTIFS('CAJAS REEMBOLSO '!$F$9:$F$80,A20) -> 2 | E20: =SUMIFS('CAJAS REEMBOLSO '!$J$9:$J$80,'CAJAS REEMBOLSO '!$F$9:$F$80,$A20) -> 31.4 | F20: =SUMIFS('CAJAS REEMBOLSO '!$K$9:$K$80,'CAJAS REEMBOLSO '!$F$9:$F$80,$A20) -> 2.2 | G20: =SUMIFS('CAJAS REEMBOLSO '!$M$9:$M$80,'CAJAS REEMBOLSO '!$F$9:$F$80,$A20) -> 33.6 | H20: TOTAL TERCERO
A21: CHIPOTLE | B21: 10314 | C21: 46198 | D21: ALMUERZO | E21: =N('CAJAS REEMBOLSO '!J43) -> 13.45 | F21: =N('CAJAS REEMBOLSO '!K43) -> 0.94 | G21: ='CAJAS REEMBOLSO '!M43 -> 14.39 | H21: Factura | I21: 35
A22: CHIPOTLE | B22: 220 | C22: 46201 | D22: ALMUERZO | E22: =N('CAJAS REEMBOLSO '!J53) -> 17.95 | F22: =N('CAJAS REEMBOLSO '!K53) -> 1.26 | G22: ='CAJAS REEMBOLSO '!M53 -> 19.21 | H22: Factura | I22: 45
A23: CHURCHS | B23: =COUNTIFS('CAJAS REEMBOLSO '!$F$9:$F$80,A23) -> 1 | E23: =SUMIFS('CAJAS REEMBOLSO '!$J$9:$J$80,'CAJAS REEMBOLSO '!$F$9:$F$80,$A23) -> 11.28 | F23: =SUMIFS('CAJAS REEMBOLSO '!$K$9:$K$80,'CAJAS REEMBOLSO '!$F$9:$F$80,$A23) -> 0.79 | G23: =SUMIFS('CAJAS REEMBOLSO '!$M$9:$M$80,'CAJAS REEMBOLSO '!$F$9:$F$80,$A23) -> 12.07 | H23: TOTAL TERCERO
A24: CHURCHS | B24: 40065 | C24: 46234 | D24: ALMUERZO | E24: =N('CAJAS REEMBOLSO '!J30) -> 11.28 | F24: =N('CAJAS REEMBOLSO '!K30) -> 0.79 | G24: ='CAJAS REEMBOLSO '!M30 -> 12.07 | H24: Factura | I24: 22
A25: COSTCO | B25: =COUNTIFS('CAJAS REEMBOLSO '!$F$9:$F$80,A25) -> 12 | E25: =SUMIFS('CAJAS REEMBOLSO '!$J$9:$J$80,'CAJAS REEMBOLSO '!$F$9:$F$80,$A25) -> 528.88 | F25: =SUMIFS('CAJAS REEMBOLSO '!$K$9:$K$80,'CAJAS REEMBOLSO '!$F$9:$F$80,$A25) -> 14.14 | G25: =SUMIFS('CAJAS REEMBOLSO '!$M$9:$M$80,'CAJAS REEMBOLSO '!$F$9:$F$80,$A25) -> 543.02 | H25: TOTAL TERCERO
A26: COSTCO | B26: 91636664 | C26: 46195 | D26: MERCADO | E26: =N('CAJAS REEMBOLSO '!J45) -> 193.23 | F26: =N('CAJAS REEMBOLSO '!K45) -> 3.78 | G26: ='CAJAS REEMBOLSO '!M45 -> 197.01 | H26: Factura | I26: 37
A27: COSTCO | B27: 91234476734 | C27: 46195 | D27: ALMUERZO | E27: =N('CAJAS REEMBOLSO '!J46) -> 3.49 | F27: =N('CAJAS REEMBOLSO '!K46) -> 0.24 | G27: ='CAJAS REEMBOLSO '!M46 -> 3.73 | H27: Factura | I27: 38
A28: COSTCO | B28: 911120612 | C28: 46204 | D28: MERCADO | E28: =N('CAJAS REEMBOLSO '!J47) -> 20.87 | F28: =N('CAJAS REEMBOLSO '!K47) -> 0.49 | G28: ='CAJAS REEMBOLSO '!M47 -> 21.36 | H28: Factura | I28: 39
A29: COSTCO | B29: 91233178733 | C29: 46204 | D29: COMIDA | E29: =N('CAJAS REEMBOLSO '!J49) -> 2.49 | F29: =N('CAJAS REEMBOLSO '!K49) -> 0.17 | G29: ='CAJAS REEMBOLSO '!M49 -> 2.66 | H29: Factura | I29: 41
A30: COSTCO | B30: 91233120733 | C30: 46206 | D30: ALMUERZO | E30: =N('CAJAS REEMBOLSO '!J48) -> 3.49 | F30: =N('CAJAS REEMBOLSO '!K48) -> 0.24 | G30: ='CAJAS REEMBOLSO '!M48 -> 3.73 | H30: Factura | I30: 40
A31: COSTCO | B31: 233156733 | C31: 46212 | D31: ALMUERZO | E31: =N('CAJAS REEMBOLSO '!J37) -> 5.48 | F31: =N('CAJAS REEMBOLSO '!K37) -> 0.38 | G31: ='CAJAS REEMBOLSO '!M37 -> 5.86 | H31: Factura | I31: 29
A32: COSTCO | B32: 9199337126 | C32: 46214 | D32: MERCADO | E32: =N('CAJAS REEMBOLSO '!J24) -> 26.99 | F32: =N('CAJAS REEMBOLSO '!K24) -> 1.89 | G32: ='CAJAS REEMBOLSO '!M24 -> 28.88 | H32: Factura | I32: 16
A33: COSTCO | B33: 91205225705 | C33: 46214 | D33: MERCADO | E33: =N('CAJAS REEMBOLSO '!J25) -> 69.03 | F33: =N('CAJAS REEMBOLSO '!K25) -> 2.93 | G33: ='CAJAS REEMBOLSO '!M25 -> 71.96 | H33: Factura | I33: 17
A34: COSTCO | B34: 91233213733 | C34: 46214 | D34: ALMUERZO | E34: =N('CAJAS REEMBOLSO '!J26) -> 3.49 | F34: =N('CAJAS REEMBOLSO '!K26) -> 0.24 | G34: ='CAJAS REEMBOLSO '!M26 -> 3.73 | H34: Factura | I34: 18
A35: COSTCO | B35: 5980203649 | C35: 46220 | D35: MERCADO | E35: =N('CAJAS REEMBOLSO '!J15) -> 13.99 | F35: =N('CAJAS REEMBOLSO '!K15) -> 0 | G35: ='CAJAS REEMBOLSO '!M15 -> 13.99 | H35: Factura | I35: 7
A36: COSTCO | B36: 91205155705 | C36: 46227 | D36: MERCADO | E36: =N('CAJAS REEMBOLSO '!J57) -> 86.53 | F36: =N('CAJAS REEMBOLSO '!K57) -> 0.98 | G36: ='CAJAS REEMBOLSO '!M57 -> 87.51 | H36: Factura | I36: 49
A37: COSTCO | B37: 9197352 | C37: 46236 | D37: MERCADO | E37: =N('CAJAS REEMBOLSO '!J56) -> 99.8 | F37: =N('CAJAS REEMBOLSO '!K56) -> 2.8 | G37: ='CAJAS REEMBOLSO '!M56 -> 102.6 | H37: Factura | I37: 48
A38: COUNTRY TAX COLLECTOR | B38: =COUNTIFS('CAJAS REEMBOLSO '!$F$9:$F$80,A38) -> 2 | E38: =SUMIFS('CAJAS REEMBOLSO '!$J$9:$J$80,'CAJAS REEMBOLSO '!$F$9:$F$80,$A38) -> 63 | F38: =SUMIFS('CAJAS REEMBOLSO '!$K$9:$K$80,'CAJAS REEMBOLSO '!$F$9:$F$80,$A38) -> 0 | G38: =SUMIFS('CAJAS REEMBOLSO '!$M$9:$M$80,'CAJAS REEMBOLSO '!$F$9:$F$80,$A38) -> 63 | H38: TOTAL TERCERO
A39: COUNTRY TAX COLLECTOR | B39: 32386729 | C39: 46205 | D39: LICENCIA DRIVER | E39: =N('CAJAS REEMBOLSO '!J69) -> 6.25 | F39: =N('CAJAS REEMBOLSO '!K69) -> 0 | G39: ='CAJAS REEMBOLSO '!M69 -> 6.25 | H39: Factura | I39: 61
A40: COUNTRY TAX COLLECTOR | B40: 32384944 | C40: 46205 | D40: LICENCIA DRIVER | E40: =N('CAJAS REEMBOLSO '!J70) -> 56.75 | F40: =N('CAJAS REEMBOLSO '!K70) -> 0 | G40: ='CAJAS REEMBOLSO '!M70 -> 56.75 | H40: Factura | I40: 62
A41: DOLLAR TREE | B41: =COUNTIFS('CAJAS REEMBOLSO '!$F$9:$F$80,A41) -> 5 | E41: =SUMIFS('CAJAS REEMBOLSO '!$J$9:$J$80,'CAJAS REEMBOLSO '!$F$9:$F$80,$A41) -> 60.75 | F41: =SUMIFS('CAJAS REEMBOLSO '!$K$9:$K$80,'CAJAS REEMBOLSO '!$F$9:$F$80,$A41) -> 2.62 | G41: =SUMIFS('CAJAS REEMBOLSO '!$M$9:$M$80,'CAJAS REEMBOLSO '!$F$9:$F$80,$A41) -> 63.37 | H41: TOTAL TERCERO
A42: DOLLAR TREE | B42: 22120723603031 | C42: 46203 | D42: MERCADO | E42: =N('CAJAS REEMBOLSO '!J52) -> 4.5 | F42: =N('CAJAS REEMBOLSO '!K52) -> 0 | G42: ='CAJAS REEMBOLSO '!M52 -> 4.5 | H42: Factura | I42: 44
A43: DOLLAR TREE | B43: 34870723602023 | C43: 46204 | D43: MERCADO | E43: =N('CAJAS REEMBOLSO '!J28) -> 7.5 | F43: =N('CAJAS REEMBOLSO '!K28) -> 0.32 | G43: ='CAJAS REEMBOLSO '!M28 -> 7.82 | H43: Factura | I43: 20
A44: DOLLAR TREE | B44: 49460723601012 | C44: 46214 | D44: MERCADO | E44: =N('CAJAS REEMBOLSO '!J29) -> 8.25 | F44: =N('CAJAS REEMBOLSO '!K29) -> 0.21 | G44: ='CAJAS REEMBOLSO '!M29 -> 8.46 | H44: Factura | I44: 21
A45: DOLLAR TREE | B45: 5051072360031 | C45: 46221 | D45: MERCADO | E45: =N('CAJAS REEMBOLSO '!J62) -> 36 | F45: =N('CAJAS REEMBOLSO '!K62) -> 1.77 | G45: ='CAJAS REEMBOLSO '!M62 -> 37.77 | H45: Factura | I45: 54
A46: DOLLAR TREE | B46: 89890723601011 | C46: 46229 | D46: MERCADO | E46: =N('CAJAS REEMBOLSO '!J18) -> 4.5 | F46: =N('CAJAS REEMBOLSO '!K18) -> 0.32 | G46: ='CAJAS REEMBOLSO '!M18 -> 4.82 | H46: Factura | I46: 10
A47: FPL | B47: =COUNTIFS('CAJAS REEMBOLSO '!$F$9:$F$80,A47) -> 7 | E47: =SUMIFS('CAJAS REEMBOLSO '!$J$9:$J$80,'CAJAS REEMBOLSO '!$F$9:$F$80,$A47) -> 500.2 | F47: =SUMIFS('CAJAS REEMBOLSO '!$K$9:$K$80,'CAJAS REEMBOLSO '!$F$9:$F$80,$A47) -> 2.11 | G47: =SUMIFS('CAJAS REEMBOLSO '!$M$9:$M$80,'CAJAS REEMBOLSO '!$F$9:$F$80,$A47) -> 502.31 | H47: TOTAL TERCERO
A48: FPL | B48: 2932427 | C48: 46195 | D48: PAGO DE ENERGIA | E48: =N('CAJAS REEMBOLSO '!J72) -> 160.44 | F48: =N('CAJAS REEMBOLSO '!K72) -> 0 | G48: ='CAJAS REEMBOLSO '!M72 -> 160.44 | H48: Factura | I48: 64
A49: FPL | B49: 8017215176174556905367 | C49: 46203 | D49: ENERGIA | E49: =N('CAJAS REEMBOLSO '!J73) -> 76.35 | F49: =N('CAJAS REEMBOLSO '!K73) -> 0 | G49: ='CAJAS REEMBOLSO '!M73 -> 76.35 | H49: Factura | I49: 65
A50: FPL | B50: 17617-45569 | C50: 46203 | D50: ENERGIA | E50: =N('CAJAS REEMBOLSO '!J74) -> 8.01 | F50: =N('CAJAS REEMBOLSO '!K74) -> 0 | G50: ='CAJAS REEMBOLSO '!M74 -> 8.01 | H50: Factura | I50: 66
A51: FPL | B51: (sin número) | C51: 46203 | D51: ENERGIA | E51: =N('CAJAS REEMBOLSO '!J80) -> 76.35 | F51: =N('CAJAS REEMBOLSO '!K80) -> 0 | G51: ='CAJAS REEMBOLSO '!M80 -> 76.35 | H51: Factura | I51: 72
A52: FPL | B52: 2932427 | C52: 46225 | E52: =N('CAJAS REEMBOLSO '!J68) -> 24.65 | F52: =N('CAJAS REEMBOLSO '!K68) -> 2.11 | G52: ='CAJAS REEMBOLSO '!M68 -> 26.76 | H52: Factura | I52: 60
A53: FPL | B53: (sin número) | C53: 46255 | D53: ENERGIA | E53: =N('CAJAS REEMBOLSO '!J75) -> 65.43 | F53: =N('CAJAS REEMBOLSO '!K75) -> 0 | G53: ='CAJAS REEMBOLSO '!M75 -> 65.43 | H53: Factura | I53: 67
A54: FPL | B54: (sin número) | C54: 46285 | D54: ENERGIA | E54: =N('CAJAS REEMBOLSO '!J76) -> 88.97 | F54: =N('CAJAS REEMBOLSO '!K76) -> 0 | G54: ='CAJAS REEMBOLSO '!M76 -> 88.97 | H54: Factura | I54: 68
A55: GOLDGAR USA | B55: =COUNTIFS('CAJAS REEMBOLSO '!$F$9:$F$80,A55) -> 1 | E55: =SUMIFS('CAJAS REEMBOLSO '!$J$9:$J$80,'CAJAS REEMBOLSO '!$F$9:$F$80,$A55) -> 25 | F55: =SUMIFS('CAJAS REEMBOLSO '!$K$9:$K$80,'CAJAS REEMBOLSO '!$F$9:$F$80,$A55) -> 0 | G55: =SUMIFS('CAJAS REEMBOLSO '!$M$9:$M$80,'CAJAS REEMBOLSO '!$F$9:$F$80,$A55) -> 25 | H55: TOTAL TERCERO
A56: GOLDGAR USA | B56: GGS2144SMD | C56: 46229 | D56: RENOV PAR TACOMA | E56: =N('CAJAS REEMBOLSO '!J71) -> 25 | F56: =N('CAJAS REEMBOLSO '!K71) -> 0 | G56: ='CAJAS REEMBOLSO '!M71 -> 25 | H56: Factura | I56: 63
A57: HOLLYWOOD FL | B57: =COUNTIFS('CAJAS REEMBOLSO '!$F$9:$F$80,A57) -> 1 | E57: =SUMIFS('CAJAS REEMBOLSO '!$J$9:$J$80,'CAJAS REEMBOLSO '!$F$9:$F$80,$A57) -> 4.5 | F57: =SUMIFS('CAJAS REEMBOLSO '!$K$9:$K$80,'CAJAS REEMBOLSO '!$F$9:$F$80,$A57) -> 0 | G57: =SUMIFS('CAJAS REEMBOLSO '!$M$9:$M$80,'CAJAS REEMBOLSO '!$F$9:$F$80,$A57) -> 4.5 | H57: TOTAL TERCERO
A58: HOLLYWOOD FL | B58: SHVU28 | C58: 46215 | D58: PARQUEADERO | E58: =N('CAJAS REEMBOLSO '!J14) -> 4.5 | F58: =N('CAJAS REEMBOLSO '!K14) -> 0 | G58: ='CAJAS REEMBOLSO '!M14 -> 4.5 | H58: Factura | I58: 6
A59: IKEA | B59: =COUNTIFS('CAJAS REEMBOLSO '!$F$9:$F$80,A59) -> 2 | E59: =SUMIFS('CAJAS REEMBOLSO '!$J$9:$J$80,'CAJAS REEMBOLSO '!$F$9:$F$80,$A59) -> 40.97 | F59: =SUMIFS('CAJAS REEMBOLSO '!$K$9:$K$80,'CAJAS REEMBOLSO '!$F$9:$F$80,$A59) -> 2.87 | G59: =SUMIFS('CAJAS REEMBOLSO '!$M$9:$M$80,'CAJAS REEMBOLSO '!$F$9:$F$80,$A59) -> 43.84 | H59: TOTAL TERCERO
A60: IKEA | B60: 990032327006800009062626 | C60: 46199 | D60: FORRO DE COLCHON Y CUBIERTOS | E60: =N('CAJAS REEMBOLSO '!J13) -> 28.98 | F60: =N('CAJAS REEMBOLSO '!K13) -> 2.03 | G60: ='CAJAS REEMBOLSO '!M13 -> 31.01 | H60: Factura | I60: 5
A61: IKEA | B61: 10042394 | C61: 46199 | D61: ALMUERZO | E61: =N('CAJAS REEMBOLSO '!J55) -> 11.99 | F61: =N('CAJAS REEMBOLSO '!K55) -> 0.84 | G61: ='CAJAS REEMBOLSO '!M55 -> 12.83 | H61: Factura | I61: 47
A62: INFINITY | B62: =COUNTIFS('CAJAS REEMBOLSO '!$F$9:$F$80,A62) -> 3 | E62: =SUMIFS('CAJAS REEMBOLSO '!$J$9:$J$80,'CAJAS REEMBOLSO '!$F$9:$F$80,$A62) -> 123.15 | F62: =SUMIFS('CAJAS REEMBOLSO '!$K$9:$K$80,'CAJAS REEMBOLSO '!$F$9:$F$80,$A62) -> 0 | G62: =SUMIFS('CAJAS REEMBOLSO '!$M$9:$M$80,'CAJAS REEMBOLSO '!$F$9:$F$80,$A62) -> 123.15 | H62: TOTAL TERCERO
A63: INFINITY | B63: (sin número) | C63: 46200 | D63: INTERNET JUN | E63: =N('CAJAS REEMBOLSO '!J77) -> 41.05 | F63: =N('CAJAS REEMBOLSO '!K77) -> 0 | G63: ='CAJAS REEMBOLSO '!M77 -> 41.05 | H63: Factura | I63: 69
A64: INFINITY | B64: (sin número) | C64: 46262 | D64: INTERNET AGOST | E64: =N('CAJAS REEMBOLSO '!J79) -> 41.05 | F64: =N('CAJAS REEMBOLSO '!K79) -> 0 | G64: ='CAJAS REEMBOLSO '!M79 -> 41.05 | H64: Factura | I64: 71
A65: INFINITY | B65: (sin número) | C65: 46292 | D65: INTERNET SEP | E65: =N('CAJAS REEMBOLSO '!J78) -> 41.05 | F65: =N('CAJAS REEMBOLSO '!K78) -> 0 | G65: ='CAJAS REEMBOLSO '!M78 -> 41.05 | H65: Factura | I65: 70
A66: PANDA EXPRESS | B66: =COUNTIFS('CAJAS REEMBOLSO '!$F$9:$F$80,A66) -> 2 | E66: =SUMIFS('CAJAS REEMBOLSO '!$J$9:$J$80,'CAJAS REEMBOLSO '!$F$9:$F$80,$A66) -> 33.3 | F66: =SUMIFS('CAJAS REEMBOLSO '!$K$9:$K$80,'CAJAS REEMBOLSO '!$F$9:$F$80,$A66) -> 2.34 | G66: =SUMIFS('CAJAS REEMBOLSO '!$M$9:$M$80,'CAJAS REEMBOLSO '!$F$9:$F$80,$A66) -> 35.64 | H66: TOTAL TERCERO
A67: PANDA EXPRESS | B67: 292607292419034102111508 | C67: 46051 | D67: ALMUERZO | E67: =N('CAJAS REEMBOLSO '!J9) -> 22.8 | F67: =N('CAJAS REEMBOLSO '!K9) -> 1.6 | G67: ='CAJAS REEMBOLSO '!M9 -> 24.4 | H67: Factura | I67: 1
A68: PANDA EXPRESS | B68: 227598 | C68: 46226 | D68: ALMUERZO | E68: =N('CAJAS REEMBOLSO '!J59) -> 10.5 | F68: =N('CAJAS REEMBOLSO '!K59) -> 0.74 | G68: ='CAJAS REEMBOLSO '!M59 -> 11.24 | H68: Factura | I68: 51
A69: POLLO TROPICAL | B69: =COUNTIFS('CAJAS REEMBOLSO '!$F$9:$F$80,A69) -> 2 | E69: =SUMIFS('CAJAS REEMBOLSO '!$J$9:$J$80,'CAJAS REEMBOLSO '!$F$9:$F$80,$A69) -> 15.08 | F69: =SUMIFS('CAJAS REEMBOLSO '!$K$9:$K$80,'CAJAS REEMBOLSO '!$F$9:$F$80,$A69) -> 1.06 | G69: =SUMIFS('CAJAS REEMBOLSO '!$M$9:$M$80,'CAJAS REEMBOLSO '!$F$9:$F$80,$A69) -> 16.14 | H69: TOTAL TERCERO
A70: POLLO TROPICAL | B70: 199974 | C70: 46208 | D70: ALMUERZO | E70: =N('CAJAS REEMBOLSO '!J35) -> 10.29 | F70: =N('CAJAS REEMBOLSO '!K35) -> 0.72 | G70: ='CAJAS REEMBOLSO '!M35 -> 11.01 | H70: Factura | I70: 27
A71: POLLO TROPICAL | B71: 199977 | C71: 46208 | D71: ALMUERZO | E71: =N('CAJAS REEMBOLSO '!J36) -> 4.79 | F71: =N('CAJAS REEMBOLSO '!K36) -> 0.34 | G71: ='CAJAS REEMBOLSO '!M36 -> 5.13 | H71: Factura | I71: 28
A72: PUBLIX | B72: =COUNTIFS('CAJAS REEMBOLSO '!$F$9:$F$80,A72) -> 3 | E72: =SUMIFS('CAJAS REEMBOLSO '!$J$9:$J$80,'CAJAS REEMBOLSO '!$F$9:$F$80,$A72) -> 25.07 | F72: =SUMIFS('CAJAS REEMBOLSO '!$K$9:$K$80,'CAJAS REEMBOLSO '!$F$9:$F$80,$A72) -> 1.2 | G72: =SUMIFS('CAJAS REEMBOLSO '!$M$9:$M$80,'CAJAS REEMBOLSO '!$F$9:$F$80,$A72) -> 26.27 | H72: TOTAL TERCERO
A73: PUBLIX | B73: 02527JR020008 | C73: 46222 | D73: MERCADO | E73: =N('CAJAS REEMBOLSO '!J61) -> 7.98 | F73: =N('CAJAS REEMBOLSO '!K61) -> 0 | G73: ='CAJAS REEMBOLSO '!M61 -> 7.98 | H73: Factura | I73: 53
A74: PUBLIX | B74: 000243902374 | C74: 46225 | D74: ALMUERZO | E74: =N('CAJAS REEMBOLSO '!J60) -> 9.81 | F74: =N('CAJAS REEMBOLSO '!K60) -> 0.69 | G74: ='CAJAS REEMBOLSO '!M60 -> 10.5 | H74: Factura | I74: 52
A75: PUBLIX | B75: 02057SR039301 | C75: 46230 | D75: MERCADO | E75: =N('CAJAS REEMBOLSO '!J16) -> 7.28 | F75: =N('CAJAS REEMBOLSO '!K16) -> 0.51 | G75: ='CAJAS REEMBOLSO '!M16 -> 7.79 | H75: Factura | I75: 8
A76: SEDANOS | B76: =COUNTIFS('CAJAS REEMBOLSO '!$F$9:$F$80,A76) -> 1 | E76: =SUMIFS('CAJAS REEMBOLSO '!$J$9:$J$80,'CAJAS REEMBOLSO '!$F$9:$F$80,$A76) -> 4.734 | F76: =SUMIFS('CAJAS REEMBOLSO '!$K$9:$K$80,'CAJAS REEMBOLSO '!$F$9:$F$80,$A76) -> 0.2 | G76: =SUMIFS('CAJAS REEMBOLSO '!$M$9:$M$80,'CAJAS REEMBOLSO '!$F$9:$F$80,$A76) -> 4.934 | H76: TOTAL TERCERO
A77: SEDANOS | B77: 9930014904647 | C77: 46197 | D77: MERCADO | E77: =N('CAJAS REEMBOLSO '!J42) -> 4.734 | F77: =N('CAJAS REEMBOLSO '!K42) -> 0.2 | G77: ='CAJAS REEMBOLSO '!M42 -> 4.934 | H77: Factura | I77: 34
A78: STEAK N SHAKE | B78: =COUNTIFS('CAJAS REEMBOLSO '!$F$9:$F$80,A78) -> 1 | E78: =SUMIFS('CAJAS REEMBOLSO '!$J$9:$J$80,'CAJAS REEMBOLSO '!$F$9:$F$80,$A78) -> 9.68 | F78: =SUMIFS('CAJAS REEMBOLSO '!$K$9:$K$80,'CAJAS REEMBOLSO '!$F$9:$F$80,$A78) -> 0.68 | G78: =SUMIFS('CAJAS REEMBOLSO '!$M$9:$M$80,'CAJAS REEMBOLSO '!$F$9:$F$80,$A78) -> 10.36 | H78: TOTAL TERCERO
A79: STEAK N SHAKE | B79: 05300730000031184821 | C79: 46233 | D79: ALMUERZO | E79: =N('CAJAS REEMBOLSO '!J17) -> 9.68 | F79: =N('CAJAS REEMBOLSO '!K17) -> 0.68 | G79: ='CAJAS REEMBOLSO '!M17 -> 10.36 | H79: Factura | I79: 9
A80: TARGET | B80: =COUNTIFS('CAJAS REEMBOLSO '!$F$9:$F$80,A80) -> 1 | E80: =SUMIFS('CAJAS REEMBOLSO '!$J$9:$J$80,'CAJAS REEMBOLSO '!$F$9:$F$80,$A80) -> 34.96 | F80: =SUMIFS('CAJAS REEMBOLSO '!$K$9:$K$80,'CAJAS REEMBOLSO '!$F$9:$F$80,$A80) -> 2.17 | G80: =SUMIFS('CAJAS REEMBOLSO '!$M$9:$M$80,'CAJAS REEMBOLSO '!$F$9:$F$80,$A80) -> 37.13 | H80: TOTAL TERCERO
A81: TARGET | B81: 6178081500794130 | C81: 46200 | D81: MERCADO | E81: =N('CAJAS REEMBOLSO '!J27) -> 34.96 | F81: =N('CAJAS REEMBOLSO '!K27) -> 2.17 | G81: ='CAJAS REEMBOLSO '!M27 -> 37.13 | H81: Factura | I81: 19
A82: THE HOME DEPOT | B82: =COUNTIFS('CAJAS REEMBOLSO '!$F$9:$F$80,A82) -> 5 | E82: =SUMIFS('CAJAS REEMBOLSO '!$J$9:$J$80,'CAJAS REEMBOLSO '!$F$9:$F$80,$A82) -> 522.52 | F82: =SUMIFS('CAJAS REEMBOLSO '!$K$9:$K$80,'CAJAS REEMBOLSO '!$F$9:$F$80,$A82) -> 35.54 | G82: =SUMIFS('CAJAS REEMBOLSO '!$M$9:$M$80,'CAJAS REEMBOLSO '!$F$9:$F$80,$A82) -> 558.06 | H82: TOTAL TERCERO
A83: THE HOME DEPOT | B83: 63438235160 | C83: 46211 | D83: MATERIALES DE CONTRUCCION | E83: =N('CAJAS REEMBOLSO '!J12) -> 249.36 | F83: =N('CAJAS REEMBOLSO '!K12) -> 17.46 | G83: ='CAJAS REEMBOLSO '!M12 -> 266.82 | H83: Factura | I83: 4
A84: THE HOME DEPOT | B84: 02225370259 | C84: 46212 | D84: MESA | E84: =N('CAJAS REEMBOLSO '!J39) -> 38.2 | F84: =N('CAJAS REEMBOLSO '!K39) -> 2.67 | G84: ='CAJAS REEMBOLSO '!M39 -> 40.87 | H84: Factura | I84: 31
A85: THE HOME DEPOT | B85: 02225275369 | C85: 46213 | D85: TRONILLOS Y TAB | E85: =N('CAJAS REEMBOLSO '!J32) -> 31.8 | F85: =N('CAJAS REEMBOLSO '!K32) -> 2.23 | G85: ='CAJAS REEMBOLSO '!M32 -> 34.03 | H85: Factura | I85: 24
A86: THE HOME DEPOT | B86: 02220002715449 | C86: 46213 | D86: ENCHUFES Y REGLETA | E86: =N('CAJAS REEMBOLSO '!J33) -> 40.32 | F86: =N('CAJAS REEMBOLSO '!K33) -> 2.82 | G86: ='CAJAS REEMBOLSO '!M33 -> 43.14 | H86: Factura | I86: 25
A87: THE HOME DEPOT | B87: 020381039221 | C87: 46220 | D87: HERRAMIENTAS | E87: =N('CAJAS REEMBOLSO '!J11) -> 162.84 | F87: =N('CAJAS REEMBOLSO '!K11) -> 10.36 | G87: ='CAJAS REEMBOLSO '!M11 -> 173.2 | H87: Factura | I87: 3
A88: THE TACO STAD | B88: =COUNTIFS('CAJAS REEMBOLSO '!$F$9:$F$80,A88) -> 1 | E88: =SUMIFS('CAJAS REEMBOLSO '!$J$9:$J$80,'CAJAS REEMBOLSO '!$F$9:$F$80,$A88) -> 19.08 | F88: =SUMIFS('CAJAS REEMBOLSO '!$K$9:$K$80,'CAJAS REEMBOLSO '!$F$9:$F$80,$A88) -> 1.34 | G88: =SUMIFS('CAJAS REEMBOLSO '!$M$9:$M$80,'CAJAS REEMBOLSO '!$F$9:$F$80,$A88) -> 20.42 | H88: TOTAL TERCERO
A89: THE TACO STAD | B89: 3F1F90976653E94A | C89: 46220 | D89: ALMUERZO | E89: =N('CAJAS REEMBOLSO '!J58) -> 19.08 | F89: =N('CAJAS REEMBOLSO '!K58) -> 1.34 | G89: ='CAJAS REEMBOLSO '!M58 -> 20.42 | H89: Factura | I89: 50
A90: TRADER JOES | B90: =COUNTIFS('CAJAS REEMBOLSO '!$F$9:$F$80,A90) -> 2 | E90: =SUMIFS('CAJAS REEMBOLSO '!$J$9:$J$80,'CAJAS REEMBOLSO '!$F$9:$F$80,$A90) -> 23.93 | F90: =SUMIFS('CAJAS REEMBOLSO '!$K$9:$K$80,'CAJAS REEMBOLSO '!$F$9:$F$80,$A90) -> 0 | G90: =SUMIFS('CAJAS REEMBOLSO '!$M$9:$M$80,'CAJAS REEMBOLSO '!$F$9:$F$80,$A90) -> 23.93 | H90: TOTAL TERCERO
A91: TRADER JOES | B91: 63248 | C91: 46221 | D91: MERCADO | E91: =N('CAJAS REEMBOLSO '!J20) -> 12.27 | F91: =N('CAJAS REEMBOLSO '!K20) -> 0 | G91: ='CAJAS REEMBOLSO '!M20 -> 12.27 | H91: Factura | I91: 12
A92: TRADER JOES | B92: 66456 | C92: 46224 | D92: MERCADO | E92: =N('CAJAS REEMBOLSO '!J64) -> 11.66 | F92: =N('CAJAS REEMBOLSO '!K64) -> 0 | G92: ='CAJAS REEMBOLSO '!M64 -> 11.66 | H92: Factura | I92: 56
A93: UNIVERSITY DRIVE | B93: =COUNTIFS('CAJAS REEMBOLSO '!$F$9:$F$80,A93) -> 1 | E93: =SUMIFS('CAJAS REEMBOLSO '!$J$9:$J$80,'CAJAS REEMBOLSO '!$F$9:$F$80,$A93) -> 19.04 | F93: =SUMIFS('CAJAS REEMBOLSO '!$K$9:$K$80,'CAJAS REEMBOLSO '!$F$9:$F$80,$A93) -> 0 | G93: =SUMIFS('CAJAS REEMBOLSO '!$M$9:$M$80,'CAJAS REEMBOLSO '!$F$9:$F$80,$A93) -> 19.04 | H93: TOTAL TERCERO
A94: UNIVERSITY DRIVE | B94: 101695 | C94: 46210 | D94: ALMUERZO | E94: =N('CAJAS REEMBOLSO '!J67) -> 19.04 | F94: =N('CAJAS REEMBOLSO '!K67) -> 0 | G94: ='CAJAS REEMBOLSO '!M67 -> 19.04 | H94: Factura | I94: 59
A95: WALGREENS | B95: =COUNTIFS('CAJAS REEMBOLSO '!$F$9:$F$80,A95) -> 1 | E95: =SUMIFS('CAJAS REEMBOLSO '!$J$9:$J$80,'CAJAS REEMBOLSO '!$F$9:$F$80,$A95) -> 5.29 | F95: =SUMIFS('CAJAS REEMBOLSO '!$K$9:$K$80,'CAJAS REEMBOLSO '!$F$9:$F$80,$A95) -> 0 | G95: =SUMIFS('CAJAS REEMBOLSO '!$M$9:$M$80,'CAJAS REEMBOLSO '!$F$9:$F$80,$A95) -> 5.29 | H95: TOTAL TERCERO
A96: WALGREENS | B96: 04003236723426071903 | C96: 46222 | D96: DROGUERIA | E96: =N('CAJAS REEMBOLSO '!J65) -> 5.29 | F96: =N('CAJAS REEMBOLSO '!K65) -> 0 | G96: ='CAJAS REEMBOLSO '!M65 -> 5.29 | H96: Factura | I96: 57
A97: WALMART | B97: =COUNTIFS('CAJAS REEMBOLSO '!$F$9:$F$80,A97) -> 5 | E97: =SUMIFS('CAJAS REEMBOLSO '!$J$9:$J$80,'CAJAS REEMBOLSO '!$F$9:$F$80,$A97) -> 231.45 | F97: =SUMIFS('CAJAS REEMBOLSO '!$K$9:$K$80,'CAJAS REEMBOLSO '!$F$9:$F$80,$A97) -> 5.46 | G97: =SUMIFS('CAJAS REEMBOLSO '!$M$9:$M$80,'CAJAS REEMBOLSO '!$F$9:$F$80,$A97) -> 236.91 | H97: TOTAL TERCERO
A98: WALMART | B98: 76320971240197904112 | C98: 46201 | D98: ALMUERZO | E98: =N('CAJAS REEMBOLSO '!J44) -> 41.05 | F98: =N('CAJAS REEMBOLSO '!K44) -> 2.22 | G98: ='CAJAS REEMBOLSO '!M44 -> 43.27 | H98: Factura | I98: 36
A99: WALMART | B99: 22043346110686495322 | C99: 46211 | D99: MERCADO | E99: =N('CAJAS REEMBOLSO '!J34) -> 9.47 | F99: =N('CAJAS REEMBOLSO '!K34) -> 0 | G99: ='CAJAS REEMBOLSO '!M34 -> 9.47 | H99: Factura | I99: 26
A100: WALMART | B100: 56869813583243057951 | C100: 46217 | D100: MERCADO | E100: =N('CAJAS REEMBOLSO '!J23) -> 40.3 | F100: =N('CAJAS REEMBOLSO '!K23) -> 0.8 | G100: ='CAJAS REEMBOLSO '!M23 -> 41.1 | H100: Factura | I100: 15
A101: WALMART | B101: 7WSLJT11BRNS | C101: 46219 | D101: MERCADO | E101: =N('CAJAS REEMBOLSO '!J63) -> 61.54 | F101: =N('CAJAS REEMBOLSO '!K63) -> 0.67 | G101: ='CAJAS REEMBOLSO '!M63 -> 62.21 | H101: Factura | I101: 55
...
